Workbook

Sheet 目次
A5: お直し限界値早見表 | B5: お直し限界値早見表 | D5: ビジカジ総裏判定 | E5: ビジカジ総裏 生地替え再製作可否シート
B7: お直し対応シート1
A8: 新宿 | B8: お直し対応シート2 | E8: OPEX原因分類定義一覧
E9: ポロシャツサイズわかるくん
A10: 吉祥寺 | B10: お直し対応シート | D10: その他 | E10: CS受付可能範囲
A12: MODI | B12: お直し対応シート
B14: お直し対応シート1 | D14: 関西用 | E14: こちらのシート
A15: 日本橋 | B15: お直し対応シート2
B17: お直し対応シート1
A18: 有楽町 | B18: お直し対応シート2
B20: お直し対応シート1
A21: 横浜 | B21: お直し対応シート2
A23: ウィメンズ | B23: お直し対応シート
A26: 表参道 | B26: お直し対応シート1
E32: 新お直し入庫処理伝票
E33: 再製作品送付伝票
D34: 配送伝票 | E34: 縫製汚れ伝票
E37: お直し預かり票印刷用 - スーツ
D38: 印刷物 | E38: お直し品預かり票印刷用 - シャツ

Sheet 新アイテム別限界値判別早見表
A1: =IFERROR(__xludf.DUMMYFUNCTION("IMPORTRANGE(""1rvkHoPE2oZB-0k4vlmjA8cgHMdBuXe9EcqpHysy6UW8"", ""'新アイテム別限界値判別早見表（作業中）'!A:BE"") "),"") | C1: =IFERROR(__xludf.DUMMYFUNCTION("""COMPUTED_VALUE"""),45991.0) -> 45991
B2: =IFERROR(__xludf.DUMMYFUNCTION("""COMPUTED_VALUE"""),"再製作") -> 再製作 | C2: =IFERROR(__xludf.DUMMYFUNCTION("""COMPUTED_VALUE"""),"基本WEB表示納期 ダブルセッティング生地は、業務チーム確認") -> 基本WEB表示納期 ダブルセッティング生地は、業務チーム確認
B3: =IFERROR(__xludf.DUMMYFUNCTION("""COMPUTED_VALUE"""),"1箇所納期") -> 1箇所納期 | C3: =IFERROR(__xludf.DUMMYFUNCTION("""COMPUTED_VALUE"""),"各項目ごとに設定された納期を参照") -> 各項目ごとに設定された納期を参照
B4: =IFERROR(__xludf.DUMMYFUNCTION("""COMPUTED_VALUE"""),"上物納期：（2箇所以内）") -> 上物納期：（2箇所以内） | C4: =IFERROR(__xludf.DUMMYFUNCTION("""COMPUTED_VALUE"""),46003.0) -> 46003 | E4: =IFERROR(__xludf.DUMMYFUNCTION("""COMPUTED_VALUE"""),"上物納期：（3箇所以上）") -> 上物納期：（3箇所以上） | H4: =IFERROR(__xludf.DUMMYFUNCTION("""COMPUTED_VALUE"""),46008.0) -> 46008
B5: =IFERROR(__xludf.DUMMYFUNCTION("""COMPUTED_VALUE"""),"下物納期：（2箇所以内）") -> 下物納期：（2箇所以内） | C5: =IFERROR(__xludf.DUMMYFUNCTION("""COMPUTED_VALUE"""),46002.0) -> 46002 | E5: =IFERROR(__xludf.DUMMYFUNCTION("""COMPUTED_VALUE"""),"下物納期：（3箇所以上）") -> 下物納期：（3箇所以上） | H5: =IFERROR(__xludf.DUMMYFUNCTION("""COMPUTED_VALUE"""),46007.0) -> 46007
B7: =IFERROR(__xludf.DUMMYFUNCTION("""COMPUTED_VALUE"""),"袖丈・裄丈・股下は左右であっても1箇所換算でOK") -> 袖丈・裄丈・股下は左右であっても1箇所換算でOK
B8: =IFERROR(__xludf.DUMMYFUNCTION("""COMPUTED_VALUE"""),"スーツ上下、3Pでお直しが発生した場合、納期は長い方（上物）に合わせてください。") -> スーツ上下、3Pでお直しが発生した場合、納期は長い方（上物）に合わせてください。
B11: =IFERROR(__xludf.DUMMYFUNCTION("""COMPUTED_VALUE"""),"上物納期") -> 上物納期 | AD11: =IFERROR(__xludf.DUMMYFUNCTION("""COMPUTED_VALUE"""),"下物納期") -> 下物納期 | BB11: =IFERROR(__xludf.DUMMYFUNCTION("""COMPUTED_VALUE"""),"特殊生地一覧") -> 特殊生地一覧
B12: =IFERROR(__xludf.DUMMYFUNCTION("""COMPUTED_VALUE"""),"アイテム") -> アイテム | C12: =IFERROR(__xludf.DUMMYFUNCTION("""COMPUTED_VALUE"""),"ジャンル") -> ジャンル | D12: =IFERROR(__xludf.DUMMYFUNCTION("""COMPUTED_VALUE"""),"部位") -> 部位 | E12: =IFERROR(__xludf.DUMMYFUNCTION("""COMPUTED_VALUE"""),"カスタマイズや条件") -> カスタマイズや条件 | F12: =IFERROR(__xludf.DUMMYFUNCTION("""COMPUTED_VALUE"""),"←詰め") -> ←詰め | Q12: =IFERROR(__xludf.DUMMYFUNCTION("""COMPUTED_VALUE"""),"出し→") -> 出し→ | V12: =IFERROR(__xludf.DUMMYFUNCTION("""COMPUTED_VALUE"""),"営業日") -> 営業日 | W12: =IFERROR(__xludf.DUMMYFUNCTION("""COMPUTED_VALUE"""),"1箇所納期") -> 1箇所納期 | X12: =IFERROR(__xludf.DUMMYFUNCTION("""COMPUTED_VALUE"""),"2箇所納期") -> 2箇所納期 | Y12: =IFERROR(__xludf.DUMMYFUNCTION("""COMPUTED_VALUE"""),"3箇所以上") -> 3箇所以上 | Z12: =IFERROR(__xludf.DUMMYFUNCTION("""COMPUTED_VALUE"""),"サポ外料金 （原価）") -> サポ外料金 （原価） | AA12: =IFERROR(__xludf.DUMMYFUNCTION("""COMPUTED_VALUE"""),"サポ外料金 現状（請求）") -> サポ外料金 現状（請求） | AB12: =IFERROR(__xludf.DUMMYFUNCTION("""COMPUTED_VALUE"""),"サポ外料金 新（請求）") -> サポ外料金 新（請求） | AD12: =IFERROR(__xludf.DUMMYFUNCTION("""COMPUTED_VALUE"""),"アイテム") -> アイテム | AE12: =IFERROR(__xludf.DUMMYFUNCTION("""COMPUTED_VALUE"""),"ジャンル") -> ジャンル | AF12: =IFERROR(__xludf.DUMMYFUNCTION("""COMPUTED_VALUE"""),"部位") -> 部位 | AG12: =IFERROR(__xludf.DUMMYFUNCTION("""COMPUTED_VALUE"""),"カスタマイズや条件") -> カスタマイズや条件 | AH12: =IFERROR(__xludf.DUMMYFUNCTION("""COMPUTED_VALUE"""),"←詰め") -> ←詰め | AO12: =IFERROR(__xludf.DUMMYFUNCTION("""COMPUTED_VALUE"""),"出し→") -> 出し→ | AT12: =IFERROR(__xludf.DUMMYFUNCTION("""COMPUTED_VALUE"""),"営業日") -> 営業日 | AU12: =IFERROR(__xludf.DUMMYFUNCTION("""COMPUTED_VALUE"""),"1箇所納期") -> 1箇所納期 | AV12: =IFERROR(__xludf.DUMMYFUNCTION("""COMPUTED_VALUE"""),"2箇所納期") -> 2箇所納期 | AW12: =IFERROR(__xludf.DUMMYFUNCTION("""COMPUTED_VALUE"""),"3箇所以上") -> 3箇所以上 | AX12: =IFERROR(__xludf.DUMMYFUNCTION("""COMPUTED_VALUE"""),"サポ外料金 （原価）") -> サポ外料金 （原価） | AY12: =IFERROR(__xludf.DUMMYFUNCTION("""COMPUTED_VALUE"""),"サポ外料金 現状（請求）") -> サポ外料金 現状（請求） | AZ12: =IFERROR(__xludf.DUMMYFUNCTION("""COMPUTED_VALUE"""),"サポ外料金 新（請求）") -> サポ外料金 新（請求） | BB12: =IFERROR(__xludf.DUMMYFUNCTION("""COMPUTED_VALUE"""),"商品名") -> 商品名 | BC12: =IFERROR(__xludf.DUMMYFUNCTION("""COMPUTED_VALUE"""),"生地コード") -> 生地コード | BD12: =IFERROR(__xludf.DUMMYFUNCTION("""COMPUTED_VALUE"""),"特殊対応内容") -> 特殊対応内容
B13: =IFERROR(__xludf.DUMMYFUNCTION("""COMPUTED_VALUE""")," ジャケット カジュアルジャケット ジャコット") -> ジャケット カジュアルジャケット ジャコット | C13: =IFERROR(__xludf.DUMMYFUNCTION("""COMPUTED_VALUE"""),"サイズ") -> サイズ | D13: =IFERROR(__xludf.DUMMYFUNCTION("""COMPUTED_VALUE"""),"肩巾") -> 肩巾 | F13: =IFERROR(__xludf.DUMMYFUNCTION("""COMPUTED_VALUE"""),-10.0) -> -10 | G13: =IFERROR(__xludf.DUMMYFUNCTION("""COMPUTED_VALUE"""),-9.0) -> -9 | H13: =IFERROR(__xludf.DUMMYFUNCTION("""COMPUTED_VALUE"""),-8.0) -> -8 | I13: =IFERROR(__xludf.DUMMYFUNCTION("""COMPUTED_VALUE"""),-7.0) -> -7 | J13: =IFERROR(__xludf.DUMMYFUNCTION("""COMPUTED_VALUE"""),-6.0) -> -6 | K13: =IFERROR(__xludf.DUMMYFUNCTION("""COMPUTED_VALUE"""),-5.0) -> -5 | L13: =IFERROR(__xludf.DUMMYFUNCTION("""COMPUTED_VALUE"""),-4.0) -> -4 | M13: =IFERROR(__xludf.DUMMYFUNCTION("""COMPUTED_VALUE"""),-3.0) -> -3 | N13: =IFERROR(__xludf.DUMMYFUNCTION("""COMPUTED_VALUE"""),-2.0) -> -2 | O13: =IFERROR(__xludf.DUMMYFUNCTION("""COMPUTED_VALUE"""),-1.0) -> -1 | P13: =IFERROR(__xludf.DUMMYFUNCTION("""COMPUTED_VALUE"""),0.0) -> 0 | Q13: =IFERROR(__xludf.DUMMYFUNCTION("""COMPUTED_VALUE"""),0.5) -> 0.5 | R13: =IFERROR(__xludf.DUMMYFUNCTION("""COMPUTED_VALUE"""),1.0) -> 1 | S13: =IFERROR(__xludf.DUMMYFUNCTION("""COMPUTED_VALUE"""),2.0) -> 2 | T13: =IFERROR(__xludf.DUMMYFUNCTION("""COMPUTED_VALUE"""),3.0) -> 3 | U13: =IFERROR(__xludf.DUMMYFUNCTION("""COMPUTED_VALUE"""),4.0) -> 4 | V13: =IFERROR(__xludf.DUMMYFUNCTION("""COMPUTED_VALUE"""),7.0) -> 7 | W13: =IFERROR(__xludf.DUMMYFUNCTION("""COMPUTED_VALUE"""),46000.0) -> 46000 | X13: =IFERROR(__xludf.DUMMYFUNCTION("""COMPUTED_VALUE"""),46003.0) -> 46003 | Y13: =IFERROR(__xludf.DUMMYFUNCTION("""COMPUTED_VALUE"""),46008.0) -> 46008 | Z13: =IFERROR(__xludf.DUMMYFUNCTION("""COMPUTED_VALUE"""),3500.0) -> 3500 | AD13: =IFERROR(__xludf.DUMMYFUNCTION("""COMPUTED_VALUE"""),"スラックス カジュアルパンツ") -> スラックス カジュアルパンツ | AE13: =IFERROR(__xludf.DUMMYFUNCTION("""COMPUTED_VALUE"""),"サイズ") -> サイズ | AF13: =IFERROR(__xludf.DUMMYFUNCTION("""COMPUTED_VALUE"""),"ウエスト") -> ウエスト | AH13: =IFERROR(__xludf.DUMMYFUNCTION("""COMPUTED_VALUE"""),-6.0) -> -6 | AI13: =IFERROR(__xludf.DUMMYFUNCTION("""COMPUTED_VALUE"""),-5.0) -> -5 | AJ13: =IFERROR(__xludf.DUMMYFUNCTION("""COMPUTED_VALUE"""),-4.0) -> -4 | AK13: =IFERROR(__xludf.DUMMYFUNCTION("""COMPUTED_VALUE"""),-3.0) -> -3 | AL13: =IFERROR(__xludf.DUMMYFUNCTION("""COMPUTED_VALUE"""),-2.0) -> -2 | AM13: =IFERROR(__xludf.DUMMYFUNCTION("""COMPUTED_VALUE"""),-1.0) -> -1 | AN13: =IFERROR(__xludf.DUMMYFUNCTION("""COMPUTED_VALUE"""),0.0) -> 0 | AO13: =IFERROR(__xludf.DUMMYFUNCTION("""COMPUTED_VALUE"""),1.0) -> 1 | AP13: =IFERROR(__xludf.DUMMYFUNCTION("""COMPUTED_VALUE"""),2.0) -> 2 | AQ13: =IFERROR(__xludf.DUMMYFUNCTION("""COMPUTED_VALUE"""),3.0) -> 3 | AR13: =IFERROR(__xludf.DUMMYFUNCTION("""COMPUTED_VALUE"""),4.0) -> 4 | AS13: =IFERROR(__xludf.DUMMYFUNCTION("""COMPUTED_VALUE"""),5.0) -> 5 | AT13: =IFERROR(__xludf.DUMMYFUNCTION("""COMPUTED_VALUE"""),5.0) -> 5 | AU13: =IFERROR(__xludf.DUMMYFUNCTION("""COMPUTED_VALUE"""),45996.0) -> 45996 | AV13: =IFERROR(__xludf.DUMMYFUNCTION("""COMPUTED_VALUE"""),46002.0) -> 46002 | AW13: =IFERROR(__xludf.DUMMYFUNCTION("""COMPUTED_VALUE"""),46007.0) -> 46007 | BB13: =IFERROR(__xludf.DUMMYFUNCTION("""COMPUTED_VALUE"""),"EASY CARE COTTON JAPAN FABRIC from BANSHU") -> EASY CARE COTTON JAPAN FABRIC from BANSHU | BC13: =IFERROR(__xludf.DUMMYFUNCTION("""COMPUTED_VALUE"""),"C220355〜C220359") -> C220355〜C220359 | BD13: =IFERROR(__xludf.DUMMYFUNCTION("""COMPUTED_VALUE"""),"出しNG（再製作）ジャケット・スラックス・") -> 出しNG（再製作）ジャケット・スラックス・
D14: =IFERROR(__xludf.DUMMYFUNCTION("""COMPUTED_VALUE"""),"袖丈") -> 袖丈 | E14: =IFERROR(__xludf.DUMMYFUNCTION("""COMPUTED_VALUE"""),"本切羽有り") -> 本切羽有り | F14: =IFERROR(__xludf.DUMMYFUNCTION("""COMPUTED_VALUE"""),-10.0) -> -10 | G14: =IFERROR(__xludf.DUMMYFUNCTION("""COMPUTED_VALUE"""),-9.0) -> -9 | H14: =IFERROR(__xludf.DUMMYFUNCTION("""COMPUTED_VALUE"""),-8.0) -> -8 | I14: =IFERROR(__xludf.DUMMYFUNCTION("""COMPUTED_VALUE"""),-7.0) -> -7 | J14: =IFERROR(__xludf.DUMMYFUNCTION("""COMPUTED_VALUE"""),-6.0) -> -6 | K14: =IFERROR(__xludf.DUMMYFUNCTION("""COMPUTED_VALUE"""),-5.0) -> -5 | L14: =IFERROR(__xludf.DUMMYFUNCTION("""COMPUTED_VALUE"""),-4.0) -> -4 | M14: =IFERROR(__xludf.DUMMYFUNCTION("""COMPUTED_VALUE"""),-3.0) -> -3 | N14: =IFERROR(__xludf.DUMMYFUNCTION("""COMPUTED_VALUE"""),-2.0) -> -2 | O14: =IFERROR(__xludf.DUMMYFUNCTION("""COMPUTED_VALUE"""),-1.0) -> -1 | P14: =IFERROR(__xludf.DUMMYFUNCTION("""COMPUTED_VALUE"""),0.0) -> 0 | Q14: =IFERROR(__xludf.DUMMYFUNCTION("""COMPUTED_VALUE"""),0.5) -> 0.5 | R14: =IFERROR(__xludf.DUMMYFUNCTION("""COMPUTED_VALUE"""),1.0) -> 1 | S14: =IFERROR(__xludf.DUMMYFUNCTION("""COMPUTED_VALUE"""),2.0) -> 2 | T14: =IFERROR(__xludf.DUMMYFUNCTION("""COMPUTED_VALUE"""),3.0) -> 3 | U14: =IFERROR(__xludf.DUMMYFUNCTION("""COMPUTED_VALUE"""),4.0) -> 4 | V14: =IFERROR(__xludf.DUMMYFUNCTION("""COMPUTED_VALUE"""),8.0) -> 8 | W14: =IFERROR(__xludf.DUMMYFUNCTION("""COMPUTED_VALUE"""),46001.0) -> 46001 | X14: =IFERROR(__xludf.DUMMYFUNCTION("""COMPUTED_VALUE"""),46003.0) -> 46003 | Y14: =IFERROR(__xludf.DUMMYFUNCTION("""COMPUTED_VALUE"""),46008.0) -> 46008 | Z14: =IFERROR(__xludf.DUMMYFUNCTION("""COMPUTED_VALUE"""),6500.0) -> 6500 | AF14: =IFERROR(__xludf.DUMMYFUNCTION("""COMPUTED_VALUE"""),"股上") -> 股上 | AH14: =IFERROR(__xludf.DUMMYFUNCTION("""COMPUTED_VALUE"""),-6.0) -> -6 | AI14: =IFERROR(__xludf.DUMMYFUNCTION("""COMPUTED_VALUE"""),-5.0) -> -5 | AJ14: =IFERROR(__xludf.DUMMYFUNCTION("""COMPUTED_VALUE"""),-3.0) -> -3 | AK14: =IFERROR(__xludf.DUMMYFUNCTION("""COMPUTED_VALUE"""),-2.0) -> -2 | AL14: =IFERROR(__xludf.DUMMYFUNCTION("""COMPUTED_VALUE"""),-1.0) -> -1 | AM14: =IFERROR(__xludf.DUMMYFUNCTION("""COMPUTED_VALUE"""),-0.5) -> -0.5 | AN14: =IFERROR(__xludf.DUMMYFUNCTION("""COMPUTED_VALUE"""),0.0) -> 0 | AO14: =IFERROR(__xludf.DUMMYFUNCTION("""COMPUTED_VALUE"""),0.5) -> 0.5 | AP14: =IFERROR(__xludf.DUMMYFUNCTION("""COMPUTED_VALUE"""),2.0) -> 2 | AQ14: =IFERROR(__xludf.DUMMYFUNCTION("""COMPUTED_VALUE"""),3.0) -> 3 | AR14: =IFERROR(__xludf.DUMMYFUNCTION("""COMPUTED_VALUE"""),4.0) -> 4 | AS14: =IFERROR(__xludf.DUMMYFUNCTION("""COMPUTED_VALUE"""),5.0) -> 5 | AT14: =IFERROR(__xludf.DUMMYFUNCTION("""COMPUTED_VALUE"""),7.0) -> 7 | AU14: =IFERROR(__xludf.DUMMYFUNCTION("""COMPUTED_VALUE"""),46000.0) -> 46000 | AV14: =IFERROR(__xludf.DUMMYFUNCTION("""COMPUTED_VALUE"""),46002.0) -> 46002 | AW14: =IFERROR(__xludf.DUMMYFUNCTION("""COMPUTED_VALUE"""),46007.0) -> 46007 | BB14: =IFERROR(__xludf.DUMMYFUNCTION("""COMPUTED_VALUE"""),"BUCOL FRENCH GABARDINE") -> BUCOL FRENCH GABARDINE | BC14: =IFERROR(__xludf.DUMMYFUNCTION("""COMPUTED_VALUE"""),"A230233〜A230234") -> A230233〜A230234 | BD14: =IFERROR(__xludf.DUMMYFUNCTION("""COMPUTED_VALUE"""),"出しNG（再製作）ジャケット・スラックス") -> 出しNG（再製作）ジャケット・スラックス
E15: =IFERROR(__xludf.DUMMYFUNCTION("""COMPUTED_VALUE"""),"本切羽無し ※±1cmは切羽移動なし") -> 本切羽無し ※±1cmは切羽移動なし | F15: =IFERROR(__xludf.DUMMYFUNCTION("""COMPUTED_VALUE"""),-10.0) -> -10 | G15: =IFERROR(__xludf.DUMMYFUNCTION("""COMPUTED_VALUE"""),-9.0) -> -9 | H15: =IFERROR(__xludf.DUMMYFUNCTION("""COMPUTED_VALUE"""),-8.0) -> -8 | I15: =IFERROR(__xludf.DUMMYFUNCTION("""COMPUTED_VALUE"""),-7.0) -> -7 | J15: =IFERROR(__xludf.DUMMYFUNCTION("""COMPUTED_VALUE"""),-6.0) -> -6 | K15: =IFERROR(__xludf.DUMMYFUNCTION("""COMPUTED_VALUE"""),-5.0) -> -5 | L15: =IFERROR(__xludf.DUMMYFUNCTION("""COMPUTED_VALUE"""),-4.0) -> -4 | M15: =IFERROR(__xludf.DUMMYFUNCTION("""COMPUTED_VALUE"""),-3.0) -> -3 | N15: =IFERROR(__xludf.DUMMYFUNCTION("""COMPUTED_VALUE"""),-2.0) -> -2 | O15: =IFERROR(__xludf.DUMMYFUNCTION("""COMPUTED_VALUE"""),-1.0) -> -1 | P15: =IFERROR(__xludf.DUMMYFUNCTION("""COMPUTED_VALUE"""),0.0) -> 0 | Q15: =IFERROR(__xludf.DUMMYFUNCTION("""COMPUTED_VALUE"""),1.0) -> 1 | R15: =IFERROR(__xludf.DUMMYFUNCTION("""COMPUTED_VALUE"""),2.5) -> 2.5 | S15: =IFERROR(__xludf.DUMMYFUNCTION("""COMPUTED_VALUE"""),3.0) -> 3 | T15: =IFERROR(__xludf.DUMMYFUNCTION("""COMPUTED_VALUE"""),4.0) -> 4 | U15: =IFERROR(__xludf.DUMMYFUNCTION("""COMPUTED_VALUE"""),5.0) -> 5 | V15: =IFERROR(__xludf.DUMMYFUNCTION("""COMPUTED_VALUE"""),7.0) -> 7 | W15: =IFERROR(__xludf.DUMMYFUNCTION("""COMPUTED_VALUE"""),46000.0) -> 46000 | X15: =IFERROR(__xludf.DUMMYFUNCTION("""COMPUTED_VALUE"""),46003.0) -> 46003 | Y15: =IFERROR(__xludf.DUMMYFUNCTION("""COMPUTED_VALUE"""),46008.0) -> 46008 | Z15: =IFERROR(__xludf.DUMMYFUNCTION("""COMPUTED_VALUE"""),1300.0) -> 1300 | AF15: =IFERROR(__xludf.DUMMYFUNCTION("""COMPUTED_VALUE"""),"股下") -> 股下 | AG15: =IFERROR(__xludf.DUMMYFUNCTION("""COMPUTED_VALUE"""),"シングル") -> シングル | AH15: =IFERROR(__xludf.DUMMYFUNCTION("""COMPUTED_VALUE"""),-6.0) -> -6 | AI15: =IFERROR(__xludf.DUMMYFUNCTION("""COMPUTED_VALUE"""),-5.0) -> -5 | AJ15: =IFERROR(__xludf.DUMMYFUNCTION("""COMPUTED_VALUE"""),-4.0) -> -4 | AK15: =IFERROR(__xludf.DUMMYFUNCTION("""COMPUTED_VALUE"""),-3.0) -> -3 | AL15: =IFERROR(__xludf.DUMMYFUNCTION("""COMPUTED_VALUE"""),-2.0) -> -2 | AM15: =IFERROR(__xludf.DUMMYFUNCTION("""COMPUTED_VALUE"""),-1.0) -> -1 | AN15: =IFERROR(__xludf.DUMMYFUNCTION("""COMPUTED_VALUE"""),0.0) -> 0 | AO15: =IFERROR(__xludf.DUMMYFUNCTION("""COMPUTED_VALUE"""),1.0) -> 1 | AP15: =IFERROR(__xludf.DUMMYFUNCTION("""COMPUTED_VALUE"""),2.0) -> 2 | AQ15: =IFERROR(__xludf.DUMMYFUNCTION("""COMPUTED_VALUE"""),3.0) -> 3 | AR15: =IFERROR(__xludf.DUMMYFUNCTION("""COMPUTED_VALUE"""),4.0) -> 4 | AS15: =IFERROR(__xludf.DUMMYFUNCTION("""COMPUTED_VALUE"""),5.0) -> 5 | AT15: =IFERROR(__xludf.DUMMYFUNCTION("""COMPUTED_VALUE"""),5.0) -> 5 | AU15: =IFERROR(__xludf.DUMMYFUNCTION("""COMPUTED_VALUE"""),45996.0) -> 45996 | AV15: =IFERROR(__xludf.DUMMYFUNCTION("""COMPUTED_VALUE"""),46002.0) -> 46002 | AW15: =IFERROR(__xludf.DUMMYFUNCTION("""COMPUTED_VALUE"""),46007.0) -> 46007 | BB15: =IFERROR(__xludf.DUMMYFUNCTION("""COMPUTED_VALUE"""),"SPENCE BRYSON PREMIUM LINEN") -> SPENCE BRYSON PREMIUM LINEN | BC15: =IFERROR(__xludf.DUMMYFUNCTION("""COMPUTED_VALUE"""),"A250036〜A250039") -> A250036〜A250039 | BD15: =IFERROR(__xludf.DUMMYFUNCTION("""COMPUTED_VALUE"""),"出しNG（再製作）ジャケット・スラックス") -> 出しNG（再製作）ジャケット・スラックス
D16: =IFERROR(__xludf.DUMMYFUNCTION("""COMPUTED_VALUE"""),"バスト") -> バスト | F16: =IFERROR(__xludf.DUMMYFUNCTION("""COMPUTED_VALUE"""),-10.0) -> -10 | G16: =IFERROR(__xludf.DUMMYFUNCTION("""COMPUTED_VALUE"""),-9.0) -> -9 | H16: =IFERROR(__xludf.DUMMYFUNCTION("""COMPUTED_VALUE"""),-8.0) -> -8 | I16: =IFERROR(__xludf.DUMMYFUNCTION("""COMPUTED_VALUE"""),-7.0) -> -7 | J16: =IFERROR(__xludf.DUMMYFUNCTION("""COMPUTED_VALUE"""),-6.0) -> -6 | K16: =IFERROR(__xludf.DUMMYFUNCTION("""COMPUTED_VALUE"""),-5.0) -> -5 | L16: =IFERROR(__xludf.DUMMYFUNCTION("""COMPUTED_VALUE"""),-4.0) -> -4 | M16: =IFERROR(__xludf.DUMMYFUNCTION("""COMPUTED_VALUE"""),-3.0) -> -3 | N16: =IFERROR(__xludf.DUMMYFUNCTION("""COMPUTED_VALUE"""),-2.0) -> -2 | O16: =IFERROR(__xludf.DUMMYFUNCTION("""COMPUTED_VALUE"""),-1.0) -> -1 | P16: =IFERROR(__xludf.DUMMYFUNCTION("""COMPUTED_VALUE"""),0.0) -> 0 | Q16: =IFERROR(__xludf.DUMMYFUNCTION("""COMPUTED_VALUE"""),1.0) -> 1 | R16: =IFERROR(__xludf.DUMMYFUNCTION("""COMPUTED_VALUE"""),2.0) -> 2 | S16: =IFERROR(__xludf.DUMMYFUNCTION("""COMPUTED_VALUE"""),3.0) -> 3 | T16: =IFERROR(__xludf.DUMMYFUNCTION("""COMPUTED_VALUE"""),4.0) -> 4 | U16: =IFERROR(__xludf.DUMMYFUNCTION("""COMPUTED_VALUE"""),5.0) -> 5 | V16: =IFERROR(__xludf.DUMMYFUNCTION("""COMPUTED_VALUE"""),7.0) -> 7 | W16: =IFERROR(__xludf.DUMMYFUNCTION("""COMPUTED_VALUE"""),46000.0) -> 46000 | X16: =IFERROR(__xludf.DUMMYFUNCTION("""COMPUTED_VALUE"""),46003.0) -> 46003 | Y16: =IFERROR(__xludf.DUMMYFUNCTION("""COMPUTED_VALUE"""),46008.0) -> 46008 | Z16: =IFERROR(__xludf.DUMMYFUNCTION("""COMPUTED_VALUE"""),3000.0) -> 3000 | AG16: =IFERROR(__xludf.DUMMYFUNCTION("""COMPUTED_VALUE"""),"W幅の3.5cm以下（3cmと3.5cm）のものは、股下1.5cm出しまで") -> W幅の3.5cm以下（3cmと3.5cm）のものは、股下1.5cm出しまで | AH16: =IFERROR(__xludf.DUMMYFUNCTION("""COMPUTED_VALUE"""),-6.0) -> -6 | AI16: =IFERROR(__xludf.DUMMYFUNCTION("""COMPUTED_VALUE"""),-5.0) -> -5 | AJ16: =IFERROR(__xludf.DUMMYFUNCTION("""COMPUTED_VALUE"""),-4.0) -> -4 | AK16: =IFERROR(__xludf.DUMMYFUNCTION("""COMPUTED_VALUE"""),-3.0) -> -3 | AL16: =IFERROR(__xludf.DUMMYFUNCTION("""COMPUTED_VALUE"""),-2.0) -> -2 | AM16: =IFERROR(__xludf.DUMMYFUNCTION("""COMPUTED_VALUE"""),-1.0) -> -1 | AN16: =IFERROR(__xludf.DUMMYFUNCTION("""COMPUTED_VALUE"""),0.0) -> 0 | AO16: =IFERROR(__xludf.DUMMYFUNCTION("""COMPUTED_VALUE"""),1.0) -> 1 | AP16: =IFERROR(__xludf.DUMMYFUNCTION("""COMPUTED_VALUE"""),1.5) -> 1.5 | AQ16: =IFERROR(__xludf.DUMMYFUNCTION("""COMPUTED_VALUE"""),3.0) -> 3 | AR16: =IFERROR(__xludf.DUMMYFUNCTION("""COMPUTED_VALUE"""),4.0) -> 4 | AS16: =IFERROR(__xludf.DUMMYFUNCTION("""COMPUTED_VALUE"""),5.0) -> 5 | AT16: =IFERROR(__xludf.DUMMYFUNCTION("""COMPUTED_VALUE"""),5.0) -> 5 | AU16: =IFERROR(__xludf.DUMMYFUNCTION("""COMPUTED_VALUE"""),45996.0) -> 45996 | AV16: =IFERROR(__xludf.DUMMYFUNCTION("""COMPUTED_VALUE"""),46002.0) -> 46002 | AW16: =IFERROR(__xludf.DUMMYFUNCTION("""COMPUTED_VALUE"""),46007.0) -> 46007 | BB16: =IFERROR(__xludf.DUMMYFUNCTION("""COMPUTED_VALUE"""),"COLOR WOOL") -> COLOR WOOL | BC16: =IFERROR(__xludf.DUMMYFUNCTION("""COMPUTED_VALUE"""),"A210144〜A210153") -> A210144〜A210153 | BD16: =IFERROR(__xludf.DUMMYFUNCTION("""COMPUTED_VALUE"""),"チノパンカテゴリーだが、スラックスと同様出しOK") -> チノパンカテゴリーだが、スラックスと同様出しOK
D17: =IFERROR(__xludf.DUMMYFUNCTION("""COMPUTED_VALUE"""),"着丈") -> 着丈 | F17: =IFERROR(__xludf.DUMMYFUNCTION("""COMPUTED_VALUE"""),-10.0) -> -10 | G17: =IFERROR(__xludf.DUMMYFUNCTION("""COMPUTED_VALUE"""),-9.0) -> -9 | H17: =IFERROR(__xludf.DUMMYFUNCTION("""COMPUTED_VALUE"""),-8.0) -> -8 | I17: =IFERROR(__xludf.DUMMYFUNCTION("""COMPUTED_VALUE"""),-7.0) -> -7 | J17: =IFERROR(__xludf.DUMMYFUNCTION("""COMPUTED_VALUE"""),-6.0) -> -6 | K17: =IFERROR(__xludf.DUMMYFUNCTION("""COMPUTED_VALUE"""),-5.0) -> -5 | L17: =IFERROR(__xludf.DUMMYFUNCTION("""COMPUTED_VALUE"""),-4.0) -> -4 | M17: =IFERROR(__xludf.DUMMYFUNCTION("""COMPUTED_VALUE"""),-3.0) -> -3 | N17: =IFERROR(__xludf.DUMMYFUNCTION("""COMPUTED_VALUE"""),-2.0) -> -2 | O17: =IFERROR(__xludf.DUMMYFUNCTION("""COMPUTED_VALUE"""),-1.0) -> -1 | P17: =IFERROR(__xludf.DUMMYFUNCTION("""COMPUTED_VALUE"""),0.0) -> 0 | Q17: =IFERROR(__xludf.DUMMYFUNCTION("""COMPUTED_VALUE"""),1.0) -> 1 | R17: =IFERROR(__xludf.DUMMYFUNCTION("""COMPUTED_VALUE"""),2.0) -> 2 | S17: =IFERROR(__xludf.DUMMYFUNCTION("""COMPUTED_VALUE"""),3.0) -> 3 | T17: =IFERROR(__xludf.DUMMYFUNCTION("""COMPUTED_VALUE"""),4.0) -> 4 | U17: =IFERROR(__xludf.DUMMYFUNCTION("""COMPUTED_VALUE"""),5.0) -> 5 | V17: =IFERROR(__xludf.DUMMYFUNCTION("""COMPUTED_VALUE"""),7.0) -> 7 | W17: =IFERROR(__xludf.DUMMYFUNCTION("""COMPUTED_VALUE"""),46000.0) -> 46000 | X17: =IFERROR(__xludf.DUMMYFUNCTION("""COMPUTED_VALUE"""),46003.0) -> 46003 | Y17: =IFERROR(__xludf.DUMMYFUNCTION("""COMPUTED_VALUE"""),46008.0) -> 46008 | Z17: =IFERROR(__xludf.DUMMYFUNCTION("""COMPUTED_VALUE"""),3000.0) -> 3000 | AG17: =IFERROR(__xludf.DUMMYFUNCTION("""COMPUTED_VALUE"""),"W幅の4cm以上（4cmと4.5cm）のものは、股下2cm出しまで") -> W幅の4cm以上（4cmと4.5cm）のものは、股下2cm出しまで | AH17: =IFERROR(__xludf.DUMMYFUNCTION("""COMPUTED_VALUE"""),-6.0) -> -6 | AI17: =IFERROR(__xludf.DUMMYFUNCTION("""COMPUTED_VALUE"""),-5.0) -> -5 | AJ17: =IFERROR(__xludf.DUMMYFUNCTION("""COMPUTED_VALUE"""),-4.0) -> -4 | AK17: =IFERROR(__xludf.DUMMYFUNCTION("""COMPUTED_VALUE"""),-3.0) -> -3 | AL17: =IFERROR(__xludf.DUMMYFUNCTION("""COMPUTED_VALUE"""),-2.0) -> -2 | AM17: =IFERROR(__xludf.DUMMYFUNCTION("""COMPUTED_VALUE"""),-1.0) -> -1 | AN17: =IFERROR(__xludf.DUMMYFUNCTION("""COMPUTED_VALUE"""),0.0) -> 0 | AO17: =IFERROR(__xludf.DUMMYFUNCTION("""COMPUTED_VALUE"""),0.5) -> 0.5 | AP17: =IFERROR(__xludf.DUMMYFUNCTION("""COMPUTED_VALUE"""),2.0) -> 2 | AQ17: =IFERROR(__xludf.DUMMYFUNCTION("""COMPUTED_VALUE"""),3.0) -> 3 | AR17: =IFERROR(__xludf.DUMMYFUNCTION("""COMPUTED_VALUE"""),4.0) -> 4 | AS17: =IFERROR(__xludf.DUMMYFUNCTION("""COMPUTED_VALUE"""),5.0) -> 5 | AT17: =IFERROR(__xludf.DUMMYFUNCTION("""COMPUTED_VALUE"""),5.0) -> 5 | AU17: =IFERROR(__xludf.DUMMYFUNCTION("""COMPUTED_VALUE"""),45996.0) -> 45996 | AV17: =IFERROR(__xludf.DUMMYFUNCTION("""COMPUTED_VALUE"""),46002.0) -> 46002 | AW17: =IFERROR(__xludf.DUMMYFUNCTION("""COMPUTED_VALUE"""),46007.0) -> 46007 | BB17: =IFERROR(__xludf.DUMMYFUNCTION("""COMPUTED_VALUE"""),"THE TECH WORK OUT") -> THE TECH WORK OUT | BC17: =IFERROR(__xludf.DUMMYFUNCTION("""COMPUTED_VALUE"""),"C170278〜C170279") -> C170278〜C170279 | BD17: =IFERROR(__xludf.DUMMYFUNCTION("""COMPUTED_VALUE"""),"出しNG（再製作）ジャケット・スラックス") -> 出しNG（再製作）ジャケット・スラックス
D18: =IFERROR(__xludf.DUMMYFUNCTION("""COMPUTED_VALUE"""),"ウエスト") -> ウエスト | E18: =IFERROR(__xludf.DUMMYFUNCTION("""COMPUTED_VALUE"""),"センターベント") -> センターベント | F18: =IFERROR(__xludf.DUMMYFUNCTION("""COMPUTED_VALUE"""),-10.0) -> -10 | G18: =IFERROR(__xludf.DUMMYFUNCTION("""COMPUTED_VALUE"""),-9.0) -> -9 | H18: =IFERROR(__xludf.DUMMYFUNCTION("""COMPUTED_VALUE"""),-8.0) -> -8 | I18: =IFERROR(__xludf.DUMMYFUNCTION("""COMPUTED_VALUE"""),-7.0) -> -7 | J18: =IFERROR(__xludf.DUMMYFUNCTION("""COMPUTED_VALUE"""),-6.0) -> -6 | K18: =IFERROR(__xludf.DUMMYFUNCTION("""COMPUTED_VALUE"""),-5.0) -> -5 | L18: =IFERROR(__xludf.DUMMYFUNCTION("""COMPUTED_VALUE"""),-4.0) -> -4 | M18: =IFERROR(__xludf.DUMMYFUNCTION("""COMPUTED_VALUE"""),-3.0) -> -3 | N18: =IFERROR(__xludf.DUMMYFUNCTION("""COMPUTED_VALUE"""),-2.0) -> -2 | O18: =IFERROR(__xludf.DUMMYFUNCTION("""COMPUTED_VALUE"""),-1.0) -> -1 | P18: =IFERROR(__xludf.DUMMYFUNCTION("""COMPUTED_VALUE"""),0.0) -> 0 | Q18: =IFERROR(__xludf.DUMMYFUNCTION("""COMPUTED_VALUE"""),1.0) -> 1 | R18: =IFERROR(__xludf.DUMMYFUNCTION("""COMPUTED_VALUE"""),2.0) -> 2 | S18: =IFERROR(__xludf.DUMMYFUNCTION("""COMPUTED_VALUE"""),3.0) -> 3 | T18: =IFERROR(__xludf.DUMMYFUNCTION("""COMPUTED_VALUE"""),4.0) -> 4 | U18: =IFERROR(__xludf.DUMMYFUNCTION("""COMPUTED_VALUE"""),5.0) -> 5 | V18: =IFERROR(__xludf.DUMMYFUNCTION("""COMPUTED_VALUE"""),7.0) -> 7 | W18: =IFERROR(__xludf.DUMMYFUNCTION("""COMPUTED_VALUE"""),46000.0) -> 46000 | X18: =IFERROR(__xludf.DUMMYFUNCTION("""COMPUTED_VALUE"""),46003.0) -> 46003 | Y18: =IFERROR(__xludf.DUMMYFUNCTION("""COMPUTED_VALUE"""),46008.0) -> 46008 | Z18: =IFERROR(__xludf.DUMMYFUNCTION("""COMPUTED_VALUE"""),6000.0) -> 6000 | AF18: =IFERROR(__xludf.DUMMYFUNCTION("""COMPUTED_VALUE"""),"ワタリ巾（半寸）") -> ワタリ巾（半寸） | AH18: =IFERROR(__xludf.DUMMYFUNCTION("""COMPUTED_VALUE"""),-6.0) -> -6 | AI18: =IFERROR(__xludf.DUMMYFUNCTION("""COMPUTED_VALUE"""),-5.0) -> -5 | AJ18: =IFERROR(__xludf.DUMMYFUNCTION("""COMPUTED_VALUE"""),-4.0) -> -4 | AK18: =IFERROR(__xludf.DUMMYFUNCTION("""COMPUTED_VALUE"""),-3.0) -> -3 | AL18: =IFERROR(__xludf.DUMMYFUNCTION("""COMPUTED_VALUE"""),-2.0) -> -2 | AM18: =IFERROR(__xludf.DUMMYFUNCTION("""COMPUTED_VALUE"""),-1.0) -> -1 | AN18: =IFERROR(__xludf.DUMMYFUNCTION("""COMPUTED_VALUE"""),0.0) -> 0 | AO18: =IFERROR(__xludf.DUMMYFUNCTION("""COMPUTED_VALUE"""),0.5) -> 0.5 | AP18: =IFERROR(__xludf.DUMMYFUNCTION("""COMPUTED_VALUE"""),2.0) -> 2 | AQ18: =IFERROR(__xludf.DUMMYFUNCTION("""COMPUTED_VALUE"""),3.0) -> 3 | AR18: =IFERROR(__xludf.DUMMYFUNCTION("""COMPUTED_VALUE"""),4.0) -> 4 | AS18: =IFERROR(__xludf.DUMMYFUNCTION("""COMPUTED_VALUE"""),5.0) -> 5 | AT18: =IFERROR(__xludf.DUMMYFUNCTION("""COMPUTED_VALUE"""),5.0) -> 5 | AU18: =IFERROR(__xludf.DUMMYFUNCTION("""COMPUTED_VALUE"""),45996.0) -> 45996 | AV18: =IFERROR(__xludf.DUMMYFUNCTION("""COMPUTED_VALUE"""),46002.0) -> 46002 | AW18: =IFERROR(__xludf.DUMMYFUNCTION("""COMPUTED_VALUE"""),46007.0) -> 46007 | BB18: =IFERROR(__xludf.DUMMYFUNCTION("""COMPUTED_VALUE"""),"KUMOI BEAUTY ORGANIC COTTON CORDUROY") -> KUMOI BEAUTY ORGANIC COTTON CORDUROY | BC18: =IFERROR(__xludf.DUMMYFUNCTION("""COMPUTED_VALUE"""),"C230135〜C230139") -> C230135〜C230139 | BD18: =IFERROR(__xludf.DUMMYFUNCTION("""COMPUTED_VALUE"""),"出しNG（再製作）ジャケット・スラックス") -> 出しNG（再製作）ジャケット・スラックス
E19: =IFERROR(__xludf.DUMMYFUNCTION("""COMPUTED_VALUE"""),"サイドベンツ") -> サイドベンツ | F19: =IFERROR(__xludf.DUMMYFUNCTION("""COMPUTED_VALUE"""),-10.0) -> -10 | G19: =IFERROR(__xludf.DUMMYFUNCTION("""COMPUTED_VALUE"""),-9.0) -> -9 | H19: =IFERROR(__xludf.DUMMYFUNCTION("""COMPUTED_VALUE"""),-8.0) -> -8 | I19: =IFERROR(__xludf.DUMMYFUNCTION("""COMPUTED_VALUE"""),-7.0) -> -7 | J19: =IFERROR(__xludf.DUMMYFUNCTION("""COMPUTED_VALUE"""),-6.0) -> -6 | K19: =IFERROR(__xludf.DUMMYFUNCTION("""COMPUTED_VALUE"""),-5.0) -> -5 | L19: =IFERROR(__xludf.DUMMYFUNCTION("""COMPUTED_VALUE"""),-4.0) -> -4 | M19: =IFERROR(__xludf.DUMMYFUNCTION("""COMPUTED_VALUE"""),-3.0) -> -3 | N19: =IFERROR(__xludf.DUMMYFUNCTION("""COMPUTED_VALUE"""),-2.0) -> -2 | O19: =IFERROR(__xludf.DUMMYFUNCTION("""COMPUTED_VALUE"""),-1.0) -> -1 | P19: =IFERROR(__xludf.DUMMYFUNCTION("""COMPUTED_VALUE"""),0.0) -> 0 | Q19: =IFERROR(__xludf.DUMMYFUNCTION("""COMPUTED_VALUE"""),1.0) -> 1 | R19: =IFERROR(__xludf.DUMMYFUNCTION("""COMPUTED_VALUE"""),2.0) -> 2 | S19: =IFERROR(__xludf.DUMMYFUNCTION("""COMPUTED_VALUE"""),3.0) -> 3 | T19: =IFERROR(__xludf.DUMMYFUNCTION("""COMPUTED_VALUE"""),4.0) -> 4 | U19: =IFERROR(__xludf.DUMMYFUNCTION("""COMPUTED_VALUE"""),5.0) -> 5 | V19: =IFERROR(__xludf.DUMMYFUNCTION("""COMPUTED_VALUE"""),7.0) -> 7 | W19: =IFERROR(__xludf.DUMMYFUNCTION("""COMPUTED_VALUE"""),46000.0) -> 46000 | X19: =IFERROR(__xludf.DUMMYFUNCTION("""COMPUTED_VALUE"""),46003.0) -> 46003 | Y19: =IFERROR(__xludf.DUMMYFUNCTION("""COMPUTED_VALUE"""),46008.0) -> 46008 | AF19: =IFERROR(__xludf.DUMMYFUNCTION("""COMPUTED_VALUE"""),"ヒザ巾（半寸）") -> ヒザ巾（半寸） | AH19: =IFERROR(__xludf.DUMMYFUNCTION("""COMPUTED_VALUE"""),-6.0) -> -6 | AI19: =IFERROR(__xludf.DUMMYFUNCTION("""COMPUTED_VALUE"""),-5.0) -> -5 | AJ19: =IFERROR(__xludf.DUMMYFUNCTION("""COMPUTED_VALUE"""),-4.0) -> -4 | AK19: =IFERROR(__xludf.DUMMYFUNCTION("""COMPUTED_VALUE"""),-3.0) -> -3 | AL19: =IFERROR(__xludf.DUMMYFUNCTION("""COMPUTED_VALUE"""),-2.0) -> -2 | AM19: =IFERROR(__xludf.DUMMYFUNCTION("""COMPUTED_VALUE"""),-1.0) -> -1 | AN19: =IFERROR(__xludf.DUMMYFUNCTION("""COMPUTED_VALUE"""),0.0) -> 0 | AO19: =IFERROR(__xludf.DUMMYFUNCTION("""COMPUTED_VALUE"""),1.0) -> 1 | AP19: =IFERROR(__xludf.DUMMYFUNCTION("""COMPUTED_VALUE"""),2.0) -> 2 | AQ19: =IFERROR(__xludf.DUMMYFUNCTION("""COMPUTED_VALUE"""),3.0) -> 3 | AR19: =IFERROR(__xludf.DUMMYFUNCTION("""COMPUTED_VALUE"""),4.0) -> 4 | AS19: =IFERROR(__xludf.DUMMYFUNCTION("""COMPUTED_VALUE"""),5.0) -> 5 | AT19: =IFERROR(__xludf.DUMMYFUNCTION("""COMPUTED_VALUE"""),5.0) -> 5 | AU19: =IFERROR(__xludf.DUMMYFUNCTION("""COMPUTED_VALUE"""),45996.0) -> 45996 | AV19: =IFERROR(__xludf.DUMMYFUNCTION("""COMPUTED_VALUE"""),46002.0) -> 46002 | AW19: =IFERROR(__xludf.DUMMYFUNCTION("""COMPUTED_VALUE"""),46007.0) -> 46007 | BB19: =IFERROR(__xludf.DUMMYFUNCTION("""COMPUTED_VALUE"""),"STRETCH MOLESKIN") -> STRETCH MOLESKIN | BC19: =IFERROR(__xludf.DUMMYFUNCTION("""COMPUTED_VALUE"""),"C240008~C240015") -> C240008~C240015 | BD19: =IFERROR(__xludf.DUMMYFUNCTION("""COMPUTED_VALUE"""),"出しNG（再製作）ジャケット・スラックス") -> 出しNG（再製作）ジャケット・スラックス
E20: =IFERROR(__xludf.DUMMYFUNCTION("""COMPUTED_VALUE"""),"ノーベント") -> ノーベント | F20: =IFERROR(__xludf.DUMMYFUNCTION("""COMPUTED_VALUE"""),-10.0) -> -10 | G20: =IFERROR(__xludf.DUMMYFUNCTION("""COMPUTED_VALUE"""),-9.0) -> -9 | H20: =IFERROR(__xludf.DUMMYFUNCTION("""COMPUTED_VALUE"""),-8.0) -> -8 | I20: =IFERROR(__xludf.DUMMYFUNCTION("""COMPUTED_VALUE"""),-7.0) -> -7 | J20: =IFERROR(__xludf.DUMMYFUNCTION("""COMPUTED_VALUE"""),-6.0) -> -6 | K20: =IFERROR(__xludf.DUMMYFUNCTION("""COMPUTED_VALUE"""),-5.0) -> -5 | L20: =IFERROR(__xludf.DUMMYFUNCTION("""COMPUTED_VALUE"""),-4.0) -> -4 | M20: =IFERROR(__xludf.DUMMYFUNCTION("""COMPUTED_VALUE"""),-3.0) -> -3 | N20: =IFERROR(__xludf.DUMMYFUNCTION("""COMPUTED_VALUE"""),-2.0) -> -2 | O20: =IFERROR(__xludf.DUMMYFUNCTION("""COMPUTED_VALUE"""),-1.0) -> -1 | P20: =IFERROR(__xludf.DUMMYFUNCTION("""COMPUTED_VALUE"""),0.0) -> 0 | Q20: =IFERROR(__xludf.DUMMYFUNCTION("""COMPUTED_VALUE"""),1.0) -> 1 | R20: =IFERROR(__xludf.DUMMYFUNCTION("""COMPUTED_VALUE"""),2.0) -> 2 | S20: =IFERROR(__xludf.DUMMYFUNCTION("""COMPUTED_VALUE"""),3.0) -> 3 | T20: =IFERROR(__xludf.DUMMYFUNCTION("""COMPUTED_VALUE"""),4.0) -> 4 | U20: =IFERROR(__xludf.DUMMYFUNCTION("""COMPUTED_VALUE"""),5.0) -> 5 | V20: =IFERROR(__xludf.DUMMYFUNCTION("""COMPUTED_VALUE"""),7.0) -> 7 | W20: =IFERROR(__xludf.DUMMYFUNCTION("""COMPUTED_VALUE"""),46000.0) -> 46000 | X20: =IFERROR(__xludf.DUMMYFUNCTION("""COMPUTED_VALUE"""),46003.0) -> 46003 | Y20: =IFERROR(__xludf.DUMMYFUNCTION("""COMPUTED_VALUE"""),46008.0) -> 46008 | AF20: =IFERROR(__xludf.DUMMYFUNCTION("""COMPUTED_VALUE"""),"裾口巾（半寸）") -> 裾口巾（半寸） | AH20: =IFERROR(__xludf.DUMMYFUNCTION("""COMPUTED_VALUE"""),-6.0) -> -6 | AI20: =IFERROR(__xludf.DUMMYFUNCTION("""COMPUTED_VALUE"""),-5.0) -> -5 | AJ20: =IFERROR(__xludf.DUMMYFUNCTION("""COMPUTED_VALUE"""),-4.0) -> -4 | AK20: =IFERROR(__xludf.DUMMYFUNCTION("""COMPUTED_VALUE"""),-3.0) -> -3 | AL20: =IFERROR(__xludf.DUMMYFUNCTION("""COMPUTED_VALUE"""),-2.0) -> -2 | AM20: =IFERROR(__xludf.DUMMYFUNCTION("""COMPUTED_VALUE"""),-1.0) -> -1 | AN20: =IFERROR(__xludf.DUMMYFUNCTION("""COMPUTED_VALUE"""),0.0) -> 0 | AO20: =IFERROR(__xludf.DUMMYFUNCTION("""COMPUTED_VALUE"""),1.0) -> 1 | AP20: =IFERROR(__xludf.DUMMYFUNCTION("""COMPUTED_VALUE"""),2.0) -> 2 | AQ20: =IFERROR(__xludf.DUMMYFUNCTION("""COMPUTED_VALUE"""),3.0) -> 3 | AR20: =IFERROR(__xludf.DUMMYFUNCTION("""COMPUTED_VALUE"""),4.0) -> 4 | AS20: =IFERROR(__xludf.DUMMYFUNCTION("""COMPUTED_VALUE"""),5.0) -> 5 | AT20: =IFERROR(__xludf.DUMMYFUNCTION("""COMPUTED_VALUE"""),5.0) -> 5 | AU20: =IFERROR(__xludf.DUMMYFUNCTION("""COMPUTED_VALUE"""),45996.0) -> 45996 | AV20: =IFERROR(__xludf.DUMMYFUNCTION("""COMPUTED_VALUE"""),46002.0) -> 46002 | AW20: =IFERROR(__xludf.DUMMYFUNCTION("""COMPUTED_VALUE"""),46007.0) -> 46007 | BB20: =IFERROR(__xludf.DUMMYFUNCTION("""COMPUTED_VALUE"""),"EASY CARE COTTON JAPAN FABRIC from BANSHU") -> EASY CARE COTTON JAPAN FABRIC from BANSHU | BC20: =IFERROR(__xludf.DUMMYFUNCTION("""COMPUTED_VALUE"""),"C240016~C240022") -> C240016~C240022 | BD20: =IFERROR(__xludf.DUMMYFUNCTION("""COMPUTED_VALUE"""),"出しNG（再製作）ジャケット・スラックス") -> 出しNG（再製作）ジャケット・スラックス
C21: =IFERROR(__xludf.DUMMYFUNCTION("""COMPUTED_VALUE"""),"補正") -> 補正 | D21: =IFERROR(__xludf.DUMMYFUNCTION("""COMPUTED_VALUE"""),"けまわし") -> けまわし | E21: =IFERROR(__xludf.DUMMYFUNCTION("""COMPUTED_VALUE"""),"※逆補正を含む、補正が入っていない時のみ、お直し可") -> ※逆補正を含む、補正が入っていない時のみ、お直し可 | N21: =IFERROR(__xludf.DUMMYFUNCTION("""COMPUTED_VALUE"""),-1.0) -> -1 | O21: =IFERROR(__xludf.DUMMYFUNCTION("""COMPUTED_VALUE"""),-0.5) -> -0.5 | V21: =IFERROR(__xludf.DUMMYFUNCTION("""COMPUTED_VALUE"""),10.0) -> 10 | W21: =IFERROR(__xludf.DUMMYFUNCTION("""COMPUTED_VALUE"""),46003.0) -> 46003 | X21: =IFERROR(__xludf.DUMMYFUNCTION("""COMPUTED_VALUE"""),46003.0) -> 46003 | Y21: =IFERROR(__xludf.DUMMYFUNCTION("""COMPUTED_VALUE"""),46008.0) -> 46008 | AE21: =IFERROR(__xludf.DUMMYFUNCTION("""COMPUTED_VALUE"""),"縫製") -> 縫製 | AF21: =IFERROR(__xludf.DUMMYFUNCTION("""COMPUTED_VALUE"""),"ベルトループ付け直し") -> ベルトループ付け直し | AG21: =IFERROR(__xludf.DUMMYFUNCTION("""COMPUTED_VALUE"""),"縫製/依頼シートをつけてTB出荷") -> 縫製/依頼シートをつけてTB出荷 | AT21: =IFERROR(__xludf.DUMMYFUNCTION("""COMPUTED_VALUE"""),7.0) -> 7 | AU21: =IFERROR(__xludf.DUMMYFUNCTION("""COMPUTED_VALUE"""),46000.0) -> 46000 | BB21: =IFERROR(__xludf.DUMMYFUNCTION("""COMPUTED_VALUE"""),"STRETCH CORDUROY") -> STRETCH CORDUROY | BC21: =IFERROR(__xludf.DUMMYFUNCTION("""COMPUTED_VALUE"""),"C240131~C240137") -> C240131~C240137 | BD21: =IFERROR(__xludf.DUMMYFUNCTION("""COMPUTED_VALUE"""),"出しNG（再製作）ジャケット・スラックス") -> 出しNG（再製作）ジャケット・スラックス
D22: =IFERROR(__xludf.DUMMYFUNCTION("""COMPUTED_VALUE"""),"つきとり") -> つきとり | E22: =IFERROR(__xludf.DUMMYFUNCTION("""COMPUTED_VALUE"""),"※逆補正を含む、補正が入っていない時のみ、お直し可") -> ※逆補正を含む、補正が入っていない時のみ、お直し可 | O22: =IFERROR(__xludf.DUMMYFUNCTION("""COMPUTED_VALUE"""),-1.0) -> -1 | V22: =IFERROR(__xludf.DUMMYFUNCTION("""COMPUTED_VALUE"""),10.0) -> 10 | W22: =IFERROR(__xludf.DUMMYFUNCTION("""COMPUTED_VALUE"""),46003.0) -> 46003 | X22: =IFERROR(__xludf.DUMMYFUNCTION("""COMPUTED_VALUE"""),46003.0) -> 46003 | Y22: =IFERROR(__xludf.DUMMYFUNCTION("""COMPUTED_VALUE"""),46008.0) -> 46008 | AF22: =IFERROR(__xludf.DUMMYFUNCTION("""COMPUTED_VALUE"""),"裾まつり直し") -> 裾まつり直し | AG22: =IFERROR(__xludf.DUMMYFUNCTION("""COMPUTED_VALUE"""),"縫製/依頼シートをつけてTB出荷") -> 縫製/依頼シートをつけてTB出荷 | AT22: =IFERROR(__xludf.DUMMYFUNCTION("""COMPUTED_VALUE"""),4.0) -> 4 | AU22: =IFERROR(__xludf.DUMMYFUNCTION("""COMPUTED_VALUE"""),45995.0) -> 45995 | BB22: =IFERROR(__xludf.DUMMYFUNCTION("""COMPUTED_VALUE"""),"なめらかで極細の糸から創り上げた、着心地抜群のストレッチ新素材") -> なめらかで極細の糸から創り上げた、着心地抜群のストレッチ新素材 | BC22: =IFERROR(__xludf.DUMMYFUNCTION("""COMPUTED_VALUE"""),"W240001~W240003") -> W240001~W240003 | BD22: =IFERROR(__xludf.DUMMYFUNCTION("""COMPUTED_VALUE"""),"出しNG（再製作）ジャケット・スラックス") -> 出しNG（再製作）ジャケット・スラックス
D23: =IFERROR(__xludf.DUMMYFUNCTION("""COMPUTED_VALUE"""),"鎌浅") -> 鎌浅 | E23: =IFERROR(__xludf.DUMMYFUNCTION("""COMPUTED_VALUE"""),"※逆補正を含む、補正が入っていない時のみ、お直し可") -> ※逆補正を含む、補正が入っていない時のみ、お直し可 | O23: =IFERROR(__xludf.DUMMYFUNCTION("""COMPUTED_VALUE"""),-1.0) -> -1 | V23: =IFERROR(__xludf.DUMMYFUNCTION("""COMPUTED_VALUE"""),10.0) -> 10 | W23: =IFERROR(__xludf.DUMMYFUNCTION("""COMPUTED_VALUE"""),46003.0) -> 46003 | X23: =IFERROR(__xludf.DUMMYFUNCTION("""COMPUTED_VALUE"""),46003.0) -> 46003 | Y23: =IFERROR(__xludf.DUMMYFUNCTION("""COMPUTED_VALUE"""),46008.0) -> 46008 | AF23: =IFERROR(__xludf.DUMMYFUNCTION("""COMPUTED_VALUE"""),"裏地ほつれ補修（膝裏地裾部分のみ）") -> 裏地ほつれ補修（膝裏地裾部分のみ） | AG23: =IFERROR(__xludf.DUMMYFUNCTION("""COMPUTED_VALUE"""),"縫製/依頼シートをつけてTB出荷") -> 縫製/依頼シートをつけてTB出荷 | AT23: =IFERROR(__xludf.DUMMYFUNCTION("""COMPUTED_VALUE"""),4.0) -> 4 | AU23: =IFERROR(__xludf.DUMMYFUNCTION("""COMPUTED_VALUE"""),45995.0) -> 45995 | BB23: =IFERROR(__xludf.DUMMYFUNCTION("""COMPUTED_VALUE"""),"Silky Drape Satin ") -> Silky Drape Satin | BC23: =IFERROR(__xludf.DUMMYFUNCTION("""COMPUTED_VALUE"""),"F250001~F250003 ") -> F250001~F250003 | BD23: =IFERROR(__xludf.DUMMYFUNCTION("""COMPUTED_VALUE"""),"出しNG（再製作）ジャケット・スラックス。スカート") -> 出しNG（再製作）ジャケット・スラックス。スカート
AF24: =IFERROR(__xludf.DUMMYFUNCTION("""COMPUTED_VALUE"""),"緩くなったボタンの付け直し") -> 緩くなったボタンの付け直し | AG24: =IFERROR(__xludf.DUMMYFUNCTION("""COMPUTED_VALUE"""),"縫製/依頼シートをつけてTB出荷") -> 縫製/依頼シートをつけてTB出荷 | AT24: =IFERROR(__xludf.DUMMYFUNCTION("""COMPUTED_VALUE"""),4.0) -> 4 | AU24: =IFERROR(__xludf.DUMMYFUNCTION("""COMPUTED_VALUE"""),45995.0) -> 45995 | BB24: =IFERROR(__xludf.DUMMYFUNCTION("""COMPUTED_VALUE"""),"TECH CORDUROY JERSEY ") -> TECH CORDUROY JERSEY | BC24: =IFERROR(__xludf.DUMMYFUNCTION("""COMPUTED_VALUE"""),"C250070〜C250074") -> C250070〜C250074 | BD24: =IFERROR(__xludf.DUMMYFUNCTION("""COMPUTED_VALUE"""),"出しNG（再製作）ジャケット・スラックス") -> 出しNG（再製作）ジャケット・スラックス
B25: =IFERROR(__xludf.DUMMYFUNCTION("""COMPUTED_VALUE"""),"ベスト") -> ベスト | C25: =IFERROR(__xludf.DUMMYFUNCTION("""COMPUTED_VALUE"""),"サイズ") -> サイズ | D25: =IFERROR(__xludf.DUMMYFUNCTION("""COMPUTED_VALUE"""),"バスト") -> バスト | F25: =IFERROR(__xludf.DUMMYFUNCTION("""COMPUTED_VALUE"""),-10.0) -> -10 | G25: =IFERROR(__xludf.DUMMYFUNCTION("""COMPUTED_VALUE"""),-9.0) -> -9 | H25: =IFERROR(__xludf.DUMMYFUNCTION("""COMPUTED_VALUE"""),-8.0) -> -8 | I25: =IFERROR(__xludf.DUMMYFUNCTION("""COMPUTED_VALUE"""),-7.0) -> -7 | J25: =IFERROR(__xludf.DUMMYFUNCTION("""COMPUTED_VALUE"""),-6.0) -> -6 | K25: =IFERROR(__xludf.DUMMYFUNCTION("""COMPUTED_VALUE"""),-5.0) -> -5 | L25: =IFERROR(__xludf.DUMMYFUNCTION("""COMPUTED_VALUE"""),-4.0) -> -4 | M25: =IFERROR(__xludf.DUMMYFUNCTION("""COMPUTED_VALUE"""),-3.0) -> -3 | N25: =IFERROR(__xludf.DUMMYFUNCTION("""COMPUTED_VALUE"""),-2.0) -> -2 | O25: =IFERROR(__xludf.DUMMYFUNCTION("""COMPUTED_VALUE"""),-1.0) -> -1 | P25: =IFERROR(__xludf.DUMMYFUNCTION("""COMPUTED_VALUE"""),0.0) -> 0 | Q25: =IFERROR(__xludf.DUMMYFUNCTION("""COMPUTED_VALUE"""),1.0) -> 1 | R25: =IFERROR(__xludf.DUMMYFUNCTION("""COMPUTED_VALUE"""),2.0) -> 2 | S25: =IFERROR(__xludf.DUMMYFUNCTION("""COMPUTED_VALUE"""),3.0) -> 3 | T25: =IFERROR(__xludf.DUMMYFUNCTION("""COMPUTED_VALUE"""),4.0) -> 4 | U25: =IFERROR(__xludf.DUMMYFUNCTION("""COMPUTED_VALUE"""),5.0) -> 5 | V25: =IFERROR(__xludf.DUMMYFUNCTION("""COMPUTED_VALUE"""),7.0) -> 7 | W25: =IFERROR(__xludf.DUMMYFUNCTION("""COMPUTED_VALUE"""),46000.0) -> 46000 | X25: =IFERROR(__xludf.DUMMYFUNCTION("""COMPUTED_VALUE"""),46003.0) -> 46003 | Y25: =IFERROR(__xludf.DUMMYFUNCTION("""COMPUTED_VALUE"""),46008.0) -> 46008 | AF25: =IFERROR(__xludf.DUMMYFUNCTION("""COMPUTED_VALUE"""),"パンク") -> パンク | AG25: =IFERROR(__xludf.DUMMYFUNCTION("""COMPUTED_VALUE"""),"縫製/依頼シートをつけてTB出荷") -> 縫製/依頼シートをつけてTB出荷 | AT25: =IFERROR(__xludf.DUMMYFUNCTION("""COMPUTED_VALUE"""),4.0) -> 4 | AU25: =IFERROR(__xludf.DUMMYFUNCTION("""COMPUTED_VALUE"""),45995.0) -> 45995
D26: =IFERROR(__xludf.DUMMYFUNCTION("""COMPUTED_VALUE"""),"ウエスト") -> ウエスト | F26: =IFERROR(__xludf.DUMMYFUNCTION("""COMPUTED_VALUE"""),-10.0) -> -10 | G26: =IFERROR(__xludf.DUMMYFUNCTION("""COMPUTED_VALUE"""),-9.0) -> -9 | H26: =IFERROR(__xludf.DUMMYFUNCTION("""COMPUTED_VALUE"""),-8.0) -> -8 | I26: =IFERROR(__xludf.DUMMYFUNCTION("""COMPUTED_VALUE"""),-7.0) -> -7 | J26: =IFERROR(__xludf.DUMMYFUNCTION("""COMPUTED_VALUE"""),-6.0) -> -6 | K26: =IFERROR(__xludf.DUMMYFUNCTION("""COMPUTED_VALUE"""),-5.0) -> -5 | L26: =IFERROR(__xludf.DUMMYFUNCTION("""COMPUTED_VALUE"""),-4.0) -> -4 | M26: =IFERROR(__xludf.DUMMYFUNCTION("""COMPUTED_VALUE"""),-3.0) -> -3 | N26: =IFERROR(__xludf.DUMMYFUNCTION("""COMPUTED_VALUE"""),-2.0) -> -2 | O26: =IFERROR(__xludf.DUMMYFUNCTION("""COMPUTED_VALUE"""),-1.0) -> -1 | P26: =IFERROR(__xludf.DUMMYFUNCTION("""COMPUTED_VALUE"""),0.0) -> 0 | Q26: =IFERROR(__xludf.DUMMYFUNCTION("""COMPUTED_VALUE"""),1.0) -> 1 | R26: =IFERROR(__xludf.DUMMYFUNCTION("""COMPUTED_VALUE"""),2.0) -> 2 | S26: =IFERROR(__xludf.DUMMYFUNCTION("""COMPUTED_VALUE"""),3.0) -> 3 | T26: =IFERROR(__xludf.DUMMYFUNCTION("""COMPUTED_VALUE"""),4.0) -> 4 | U26: =IFERROR(__xludf.DUMMYFUNCTION("""COMPUTED_VALUE"""),5.0) -> 5 | V26: =IFERROR(__xludf.DUMMYFUNCTION("""COMPUTED_VALUE"""),7.0) -> 7 | W26: =IFERROR(__xludf.DUMMYFUNCTION("""COMPUTED_VALUE"""),46000.0) -> 46000 | X26: =IFERROR(__xludf.DUMMYFUNCTION("""COMPUTED_VALUE"""),46003.0) -> 46003 | Y26: =IFERROR(__xludf.DUMMYFUNCTION("""COMPUTED_VALUE"""),46008.0) -> 46008 | AF26: =IFERROR(__xludf.DUMMYFUNCTION("""COMPUTED_VALUE"""),"たたきお直し") -> たたきお直し | AG26: =IFERROR(__xludf.DUMMYFUNCTION("""COMPUTED_VALUE"""),"縫製/依頼シートをつけてTB出荷") -> 縫製/依頼シートをつけてTB出荷 | AT26: =IFERROR(__xludf.DUMMYFUNCTION("""COMPUTED_VALUE"""),7.0) -> 7 | AU26: =IFERROR(__xludf.DUMMYFUNCTION("""COMPUTED_VALUE"""),46000.0) -> 46000
D27: =IFERROR(__xludf.DUMMYFUNCTION("""COMPUTED_VALUE"""),"着丈") -> 着丈 | F27: =IFERROR(__xludf.DUMMYFUNCTION("""COMPUTED_VALUE"""),-10.0) -> -10 | G27: =IFERROR(__xludf.DUMMYFUNCTION("""COMPUTED_VALUE"""),-9.0) -> -9 | H27: =IFERROR(__xludf.DUMMYFUNCTION("""COMPUTED_VALUE"""),-8.0) -> -8 | I27: =IFERROR(__xludf.DUMMYFUNCTION("""COMPUTED_VALUE"""),-7.0) -> -7 | J27: =IFERROR(__xludf.DUMMYFUNCTION("""COMPUTED_VALUE"""),-6.0) -> -6 | K27: =IFERROR(__xludf.DUMMYFUNCTION("""COMPUTED_VALUE"""),-5.0) -> -5 | L27: =IFERROR(__xludf.DUMMYFUNCTION("""COMPUTED_VALUE"""),-4.0) -> -4 | M27: =IFERROR(__xludf.DUMMYFUNCTION("""COMPUTED_VALUE"""),-3.0) -> -3 | N27: =IFERROR(__xludf.DUMMYFUNCTION("""COMPUTED_VALUE"""),-2.0) -> -2 | O27: =IFERROR(__xludf.DUMMYFUNCTION("""COMPUTED_VALUE"""),-1.0) -> -1 | P27: =IFERROR(__xludf.DUMMYFUNCTION("""COMPUTED_VALUE"""),0.0) -> 0 | Q27: =IFERROR(__xludf.DUMMYFUNCTION("""COMPUTED_VALUE"""),0.5) -> 0.5 | R27: =IFERROR(__xludf.DUMMYFUNCTION("""COMPUTED_VALUE"""),2.0) -> 2 | S27: =IFERROR(__xludf.DUMMYFUNCTION("""COMPUTED_VALUE"""),3.0) -> 3 | T27: =IFERROR(__xludf.DUMMYFUNCTION("""COMPUTED_VALUE"""),4.0) -> 4 | U27: =IFERROR(__xludf.DUMMYFUNCTION("""COMPUTED_VALUE"""),5.0) -> 5 | V27: =IFERROR(__xludf.DUMMYFUNCTION("""COMPUTED_VALUE"""),7.0) -> 7 | W27: =IFERROR(__xludf.DUMMYFUNCTION("""COMPUTED_VALUE"""),46000.0) -> 46000 | X27: =IFERROR(__xludf.DUMMYFUNCTION("""COMPUTED_VALUE"""),46003.0) -> 46003 | Y27: =IFERROR(__xludf.DUMMYFUNCTION("""COMPUTED_VALUE"""),46008.0) -> 46008
C28: =IFERROR(__xludf.DUMMYFUNCTION("""COMPUTED_VALUE"""),"縫製") -> 縫製 | D28: =IFERROR(__xludf.DUMMYFUNCTION("""COMPUTED_VALUE"""),"バスト") -> バスト | E28: =IFERROR(__xludf.DUMMYFUNCTION("""COMPUTED_VALUE"""),"ベルトループ交換") -> ベルトループ交換 | V28: =IFERROR(__xludf.DUMMYFUNCTION("""COMPUTED_VALUE"""),4.0) -> 4 | W28: =IFERROR(__xludf.DUMMYFUNCTION("""COMPUTED_VALUE"""),45995.0) -> 45995 | X28: =IFERROR(__xludf.DUMMYFUNCTION("""COMPUTED_VALUE"""),46003.0) -> 46003 | Y28: =IFERROR(__xludf.DUMMYFUNCTION("""COMPUTED_VALUE"""),46008.0) -> 46008 | AD28: =IFERROR(__xludf.DUMMYFUNCTION("""COMPUTED_VALUE"""),"チノ") -> チノ | AE28: =IFERROR(__xludf.DUMMYFUNCTION("""COMPUTED_VALUE"""),"サイズ") -> サイズ | AF28: =IFERROR(__xludf.DUMMYFUNCTION("""COMPUTED_VALUE"""),"ウエスト") -> ウエスト | AH28: =IFERROR(__xludf.DUMMYFUNCTION("""COMPUTED_VALUE"""),-6.0) -> -6 | AI28: =IFERROR(__xludf.DUMMYFUNCTION("""COMPUTED_VALUE"""),-5.0) -> -5 | AJ28: =IFERROR(__xludf.DUMMYFUNCTION("""COMPUTED_VALUE"""),-4.0) -> -4 | AK28: =IFERROR(__xludf.DUMMYFUNCTION("""COMPUTED_VALUE"""),-3.0) -> -3 | AL28: =IFERROR(__xludf.DUMMYFUNCTION("""COMPUTED_VALUE"""),-2.0) -> -2 | AM28: =IFERROR(__xludf.DUMMYFUNCTION("""COMPUTED_VALUE"""),-1.0) -> -1 | AN28: =IFERROR(__xludf.DUMMYFUNCTION("""COMPUTED_VALUE"""),0.0) -> 0 | AO28: =IFERROR(__xludf.DUMMYFUNCTION("""COMPUTED_VALUE"""),1.0) -> 1 | AP28: =IFERROR(__xludf.DUMMYFUNCTION("""COMPUTED_VALUE"""),2.0) -> 2 | AQ28: =IFERROR(__xludf.DUMMYFUNCTION("""COMPUTED_VALUE"""),3.0) -> 3 | AR28: =IFERROR(__xludf.DUMMYFUNCTION("""COMPUTED_VALUE"""),4.0) -> 4 | AS28: =IFERROR(__xludf.DUMMYFUNCTION("""COMPUTED_VALUE"""),5.0) -> 5 | AT28: =IFERROR(__xludf.DUMMYFUNCTION("""COMPUTED_VALUE"""),5.0) -> 5 | AU28: =IFERROR(__xludf.DUMMYFUNCTION("""COMPUTED_VALUE"""),45996.0) -> 45996 | AV28: =IFERROR(__xludf.DUMMYFUNCTION("""COMPUTED_VALUE"""),46002.0) -> 46002 | AW28: =IFERROR(__xludf.DUMMYFUNCTION("""COMPUTED_VALUE"""),46007.0) -> 46007
D29: =IFERROR(__xludf.DUMMYFUNCTION("""COMPUTED_VALUE"""),"ウエスト") -> ウエスト | E29: =IFERROR(__xludf.DUMMYFUNCTION("""COMPUTED_VALUE"""),"ボタン付け替え") -> ボタン付け替え | V29: =IFERROR(__xludf.DUMMYFUNCTION("""COMPUTED_VALUE"""),4.0) -> 4 | W29: =IFERROR(__xludf.DUMMYFUNCTION("""COMPUTED_VALUE"""),45995.0) -> 45995 | X29: =IFERROR(__xludf.DUMMYFUNCTION("""COMPUTED_VALUE"""),46003.0) -> 46003 | Y29: =IFERROR(__xludf.DUMMYFUNCTION("""COMPUTED_VALUE"""),46008.0) -> 46008 | AF29: =IFERROR(__xludf.DUMMYFUNCTION("""COMPUTED_VALUE"""),"股上") -> 股上 | AH29: =IFERROR(__xludf.DUMMYFUNCTION("""COMPUTED_VALUE"""),-6.0) -> -6 | AI29: =IFERROR(__xludf.DUMMYFUNCTION("""COMPUTED_VALUE"""),-5.0) -> -5 | AJ29: =IFERROR(__xludf.DUMMYFUNCTION("""COMPUTED_VALUE"""),-3.0) -> -3 | AK29: =IFERROR(__xludf.DUMMYFUNCTION("""COMPUTED_VALUE"""),-2.0) -> -2 | AL29: =IFERROR(__xludf.DUMMYFUNCTION("""COMPUTED_VALUE"""),-1.0) -> -1 | AM29: =IFERROR(__xludf.DUMMYFUNCTION("""COMPUTED_VALUE"""),-0.5) -> -0.5 | AN29: =IFERROR(__xludf.DUMMYFUNCTION("""COMPUTED_VALUE"""),0.0) -> 0 | AO29: =IFERROR(__xludf.DUMMYFUNCTION("""COMPUTED_VALUE"""),1.0) -> 1 | AP29: =IFERROR(__xludf.DUMMYFUNCTION("""COMPUTED_VALUE"""),2.0) -> 2 | AQ29: =IFERROR(__xludf.DUMMYFUNCTION("""COMPUTED_VALUE"""),3.0) -> 3 | AR29: =IFERROR(__xludf.DUMMYFUNCTION("""COMPUTED_VALUE"""),4.0) -> 4 | AS29: =IFERROR(__xludf.DUMMYFUNCTION("""COMPUTED_VALUE"""),5.0) -> 5 | AT29: =IFERROR(__xludf.DUMMYFUNCTION("""COMPUTED_VALUE"""),7.0) -> 7 | AU29: =IFERROR(__xludf.DUMMYFUNCTION("""COMPUTED_VALUE"""),46000.0) -> 46000 | AV29: =IFERROR(__xludf.DUMMYFUNCTION("""COMPUTED_VALUE"""),46002.0) -> 46002 | AW29: =IFERROR(__xludf.DUMMYFUNCTION("""COMPUTED_VALUE"""),46007.0) -> 46007
D30: =IFERROR(__xludf.DUMMYFUNCTION("""COMPUTED_VALUE"""),"着丈") -> 着丈 | E30: =IFERROR(__xludf.DUMMYFUNCTION("""COMPUTED_VALUE"""),"裏地ほつれ補修（裾）") -> 裏地ほつれ補修（裾） | V30: =IFERROR(__xludf.DUMMYFUNCTION("""COMPUTED_VALUE"""),4.0) -> 4 | W30: =IFERROR(__xludf.DUMMYFUNCTION("""COMPUTED_VALUE"""),45995.0) -> 45995 | X30: =IFERROR(__xludf.DUMMYFUNCTION("""COMPUTED_VALUE"""),46003.0) -> 46003 | Y30: =IFERROR(__xludf.DUMMYFUNCTION("""COMPUTED_VALUE"""),46008.0) -> 46008 | AF30: =IFERROR(__xludf.DUMMYFUNCTION("""COMPUTED_VALUE"""),"股下") -> 股下 | AG30: =IFERROR(__xludf.DUMMYFUNCTION("""COMPUTED_VALUE"""),"シングル") -> シングル | AH30: =IFERROR(__xludf.DUMMYFUNCTION("""COMPUTED_VALUE"""),-6.0) -> -6 | AI30: =IFERROR(__xludf.DUMMYFUNCTION("""COMPUTED_VALUE"""),-5.0) -> -5 | AJ30: =IFERROR(__xludf.DUMMYFUNCTION("""COMPUTED_VALUE"""),-4.0) -> -4 | AK30: =IFERROR(__xludf.DUMMYFUNCTION("""COMPUTED_VALUE"""),-3.0) -> -3 | AL30: =IFERROR(__xludf.DUMMYFUNCTION("""COMPUTED_VALUE"""),-2.0) -> -2 | AM30: =IFERROR(__xludf.DUMMYFUNCTION("""COMPUTED_VALUE"""),-1.0) -> -1 | AN30: =IFERROR(__xludf.DUMMYFUNCTION("""COMPUTED_VALUE"""),0.0) -> 0 | AO30: =IFERROR(__xludf.DUMMYFUNCTION("""COMPUTED_VALUE"""),1.0) -> 1 | AP30: =IFERROR(__xludf.DUMMYFUNCTION("""COMPUTED_VALUE"""),2.0) -> 2 | AQ30: =IFERROR(__xludf.DUMMYFUNCTION("""COMPUTED_VALUE"""),3.0) -> 3 | AR30: =IFERROR(__xludf.DUMMYFUNCTION("""COMPUTED_VALUE"""),4.0) -> 4 | AS30: =IFERROR(__xludf.DUMMYFUNCTION("""COMPUTED_VALUE"""),5.0) -> 5 | AT30: =IFERROR(__xludf.DUMMYFUNCTION("""COMPUTED_VALUE"""),5.0) -> 5 | AU30: =IFERROR(__xludf.DUMMYFUNCTION("""COMPUTED_VALUE"""),45996.0) -> 45996 | AV30: =IFERROR(__xludf.DUMMYFUNCTION("""COMPUTED_VALUE"""),46002.0) -> 46002 | AW30: =IFERROR(__xludf.DUMMYFUNCTION("""COMPUTED_VALUE"""),46007.0) -> 46007
AG31: =IFERROR(__xludf.DUMMYFUNCTION("""COMPUTED_VALUE"""),"ダブル") -> ダブル | AH31: =IFERROR(__xludf.DUMMYFUNCTION("""COMPUTED_VALUE"""),-6.0) -> -6 | AI31: =IFERROR(__xludf.DUMMYFUNCTION("""COMPUTED_VALUE"""),-5.0) -> -5 | AJ31: =IFERROR(__xludf.DUMMYFUNCTION("""COMPUTED_VALUE"""),-4.0) -> -4 | AK31: =IFERROR(__xludf.DUMMYFUNCTION("""COMPUTED_VALUE"""),-3.0) -> -3 | AL31: =IFERROR(__xludf.DUMMYFUNCTION("""COMPUTED_VALUE"""),-2.0) -> -2 | AM31: =IFERROR(__xludf.DUMMYFUNCTION("""COMPUTED_VALUE"""),-1.0) -> -1 | AN31: =IFERROR(__xludf.DUMMYFUNCTION("""COMPUTED_VALUE"""),0.0) -> 0 | AO31: =IFERROR(__xludf.DUMMYFUNCTION("""COMPUTED_VALUE"""),1.0) -> 1 | AP31: =IFERROR(__xludf.DUMMYFUNCTION("""COMPUTED_VALUE"""),2.0) -> 2 | AQ31: =IFERROR(__xludf.DUMMYFUNCTION("""COMPUTED_VALUE"""),3.0) -> 3 | AR31: =IFERROR(__xludf.DUMMYFUNCTION("""COMPUTED_VALUE"""),4.0) -> 4 | AS31: =IFERROR(__xludf.DUMMYFUNCTION("""COMPUTED_VALUE"""),5.0) -> 5 | AT31: =IFERROR(__xludf.DUMMYFUNCTION("""COMPUTED_VALUE"""),"-") -> - | AU31: =IFERROR(__xludf.DUMMYFUNCTION("""COMPUTED_VALUE"""),"-") -> - | AV31: =IFERROR(__xludf.DUMMYFUNCTION("""COMPUTED_VALUE"""),46002.0) -> 46002 | AW31: =IFERROR(__xludf.DUMMYFUNCTION("""COMPUTED_VALUE"""),46007.0) -> 46007
AG32: =IFERROR(__xludf.DUMMYFUNCTION("""COMPUTED_VALUE"""),"ステッチ") -> ステッチ | AH32: =IFERROR(__xludf.DUMMYFUNCTION("""COMPUTED_VALUE"""),-6.0) -> -6 | AI32: =IFERROR(__xludf.DUMMYFUNCTION("""COMPUTED_VALUE"""),-5.0) -> -5 | AJ32: =IFERROR(__xludf.DUMMYFUNCTION("""COMPUTED_VALUE"""),-4.0) -> -4 | AK32: =IFERROR(__xludf.DUMMYFUNCTION("""COMPUTED_VALUE"""),-3.0) -> -3 | AL32: =IFERROR(__xludf.DUMMYFUNCTION("""COMPUTED_VALUE"""),-2.0) -> -2 | AM32: =IFERROR(__xludf.DUMMYFUNCTION("""COMPUTED_VALUE"""),-1.0) -> -1 | AN32: =IFERROR(__xludf.DUMMYFUNCTION("""COMPUTED_VALUE"""),0.0) -> 0 | AO32: =IFERROR(__xludf.DUMMYFUNCTION("""COMPUTED_VALUE"""),1.0) -> 1 | AP32: =IFERROR(__xludf.DUMMYFUNCTION("""COMPUTED_VALUE"""),2.0) -> 2 | AQ32: =IFERROR(__xludf.DUMMYFUNCTION("""COMPUTED_VALUE"""),3.0) -> 3 | AR32: =IFERROR(__xludf.DUMMYFUNCTION("""COMPUTED_VALUE"""),4.0) -> 4 | AS32: =IFERROR(__xludf.DUMMYFUNCTION("""COMPUTED_VALUE"""),5.0) -> 5 | AT32: =IFERROR(__xludf.DUMMYFUNCTION("""COMPUTED_VALUE"""),"-") -> - | AU32: =IFERROR(__xludf.DUMMYFUNCTION("""COMPUTED_VALUE"""),"-") -> - | AV32: =IFERROR(__xludf.DUMMYFUNCTION("""COMPUTED_VALUE"""),46002.0) -> 46002 | AW32: =IFERROR(__xludf.DUMMYFUNCTION("""COMPUTED_VALUE"""),46007.0) -> 46007
B33: =IFERROR(__xludf.DUMMYFUNCTION("""COMPUTED_VALUE""")," シャツ長袖 タックアウト長袖") -> シャツ長袖 タックアウト長袖 | C33: =IFERROR(__xludf.DUMMYFUNCTION("""COMPUTED_VALUE"""),"サイズ") -> サイズ | D33: =IFERROR(__xludf.DUMMYFUNCTION("""COMPUTED_VALUE"""),"裄丈") -> 裄丈 | F33: =IFERROR(__xludf.DUMMYFUNCTION("""COMPUTED_VALUE"""),-10.0) -> -10 | G33: =IFERROR(__xludf.DUMMYFUNCTION("""COMPUTED_VALUE"""),-9.0) -> -9 | H33: =IFERROR(__xludf.DUMMYFUNCTION("""COMPUTED_VALUE"""),-8.0) -> -8 | I33: =IFERROR(__xludf.DUMMYFUNCTION("""COMPUTED_VALUE"""),-7.0) -> -7 | J33: =IFERROR(__xludf.DUMMYFUNCTION("""COMPUTED_VALUE"""),-6.0) -> -6 | K33: =IFERROR(__xludf.DUMMYFUNCTION("""COMPUTED_VALUE"""),-5.0) -> -5 | L33: =IFERROR(__xludf.DUMMYFUNCTION("""COMPUTED_VALUE"""),-4.0) -> -4 | M33: =IFERROR(__xludf.DUMMYFUNCTION("""COMPUTED_VALUE"""),-3.0) -> -3 | N33: =IFERROR(__xludf.DUMMYFUNCTION("""COMPUTED_VALUE"""),-2.0) -> -2 | O33: =IFERROR(__xludf.DUMMYFUNCTION("""COMPUTED_VALUE"""),-1.0) -> -1 | P33: =IFERROR(__xludf.DUMMYFUNCTION("""COMPUTED_VALUE"""),0.0) -> 0 | Q33: =IFERROR(__xludf.DUMMYFUNCTION("""COMPUTED_VALUE"""),1.0) -> 1 | R33: =IFERROR(__xludf.DUMMYFUNCTION("""COMPUTED_VALUE"""),2.0) -> 2 | S33: =IFERROR(__xludf.DUMMYFUNCTION("""COMPUTED_VALUE"""),3.0) -> 3 | T33: =IFERROR(__xludf.DUMMYFUNCTION("""COMPUTED_VALUE"""),4.0) -> 4 | U33: =IFERROR(__xludf.DUMMYFUNCTION("""COMPUTED_VALUE"""),5.0) -> 5 | V33: =IFERROR(__xludf.DUMMYFUNCTION("""COMPUTED_VALUE"""),7.0) -> 7 | W33: =IFERROR(__xludf.DUMMYFUNCTION("""COMPUTED_VALUE"""),46000.0) -> 46000 | X33: =IFERROR(__xludf.DUMMYFUNCTION("""COMPUTED_VALUE"""),46003.0) -> 46003 | Y33: =IFERROR(__xludf.DUMMYFUNCTION("""COMPUTED_VALUE"""),46008.0) -> 46008 | AF33: =IFERROR(__xludf.DUMMYFUNCTION("""COMPUTED_VALUE"""),"ワタリ巾（半寸）") -> ワタリ巾（半寸） | AH33: =IFERROR(__xludf.DUMMYFUNCTION("""COMPUTED_VALUE"""),-6.0) -> -6 | AI33: =IFERROR(__xludf.DUMMYFUNCTION("""COMPUTED_VALUE"""),-5.0) -> -5 | AJ33: =IFERROR(__xludf.DUMMYFUNCTION("""COMPUTED_VALUE"""),-4.0) -> -4 | AK33: =IFERROR(__xludf.DUMMYFUNCTION("""COMPUTED_VALUE"""),-3.0) -> -3 | AL33: =IFERROR(__xludf.DUMMYFUNCTION("""COMPUTED_VALUE"""),-2.0) -> -2 | AM33: =IFERROR(__xludf.DUMMYFUNCTION("""COMPUTED_VALUE"""),-1.0) -> -1 | AN33: =IFERROR(__xludf.DUMMYFUNCTION("""COMPUTED_VALUE"""),0.0) -> 0 | AO33: =IFERROR(__xludf.DUMMYFUNCTION("""COMPUTED_VALUE"""),1.0) -> 1 | AP33: =IFERROR(__xludf.DUMMYFUNCTION("""COMPUTED_VALUE"""),2.0) -> 2 | AQ33: =IFERROR(__xludf.DUMMYFUNCTION("""COMPUTED_VALUE"""),3.0) -> 3 | AR33: =IFERROR(__xludf.DUMMYFUNCTION("""COMPUTED_VALUE"""),4.0) -> 4 | AS33: =IFERROR(__xludf.DUMMYFUNCTION("""COMPUTED_VALUE"""),5.0) -> 5 | AT33: =IFERROR(__xludf.DUMMYFUNCTION("""COMPUTED_VALUE"""),5.0) -> 5 | AU33: =IFERROR(__xludf.DUMMYFUNCTION("""COMPUTED_VALUE"""),45996.0) -> 45996 | AV33: =IFERROR(__xludf.DUMMYFUNCTION("""COMPUTED_VALUE"""),46002.0) -> 46002 | AW33: =IFERROR(__xludf.DUMMYFUNCTION("""COMPUTED_VALUE"""),46007.0) -> 46007 | BB33: =IFERROR(__xludf.DUMMYFUNCTION("""COMPUTED_VALUE"""),"White Friday 一覧") -> White Friday 一覧
D34: =IFERROR(__xludf.DUMMYFUNCTION("""COMPUTED_VALUE"""),"襟") -> 襟 | F34: =IFERROR(__xludf.DUMMYFUNCTION("""COMPUTED_VALUE"""),-10.0) -> -10 | G34: =IFERROR(__xludf.DUMMYFUNCTION("""COMPUTED_VALUE"""),-9.0) -> -9 | H34: =IFERROR(__xludf.DUMMYFUNCTION("""COMPUTED_VALUE"""),-8.0) -> -8 | I34: =IFERROR(__xludf.DUMMYFUNCTION("""COMPUTED_VALUE"""),-7.0) -> -7 | J34: =IFERROR(__xludf.DUMMYFUNCTION("""COMPUTED_VALUE"""),-6.0) -> -6 | K34: =IFERROR(__xludf.DUMMYFUNCTION("""COMPUTED_VALUE"""),-5.0) -> -5 | L34: =IFERROR(__xludf.DUMMYFUNCTION("""COMPUTED_VALUE"""),-4.0) -> -4 | M34: =IFERROR(__xludf.DUMMYFUNCTION("""COMPUTED_VALUE"""),-3.0) -> -3 | N34: =IFERROR(__xludf.DUMMYFUNCTION("""COMPUTED_VALUE"""),-2.0) -> -2 | O34: =IFERROR(__xludf.DUMMYFUNCTION("""COMPUTED_VALUE"""),-1.0) -> -1 | P34: =IFERROR(__xludf.DUMMYFUNCTION("""COMPUTED_VALUE"""),0.0) -> 0 | Q34: =IFERROR(__xludf.DUMMYFUNCTION("""COMPUTED_VALUE"""),1.0) -> 1 | R34: =IFERROR(__xludf.DUMMYFUNCTION("""COMPUTED_VALUE"""),2.0) -> 2 | S34: =IFERROR(__xludf.DUMMYFUNCTION("""COMPUTED_VALUE"""),3.0) -> 3 | T34: =IFERROR(__xludf.DUMMYFUNCTION("""COMPUTED_VALUE"""),4.0) -> 4 | U34: =IFERROR(__xludf.DUMMYFUNCTION("""COMPUTED_VALUE"""),5.0) -> 5 | V34: =IFERROR(__xludf.DUMMYFUNCTION("""COMPUTED_VALUE"""),"-") -> - | W34: =IFERROR(__xludf.DUMMYFUNCTION("""COMPUTED_VALUE"""),"-") -> - | X34: =IFERROR(__xludf.DUMMYFUNCTION("""COMPUTED_VALUE"""),"-") -> - | Y34: =IFERROR(__xludf.DUMMYFUNCTION("""COMPUTED_VALUE"""),"-") -> - | AF34: =IFERROR(__xludf.DUMMYFUNCTION("""COMPUTED_VALUE"""),"ヒザ巾（半寸）") -> ヒザ巾（半寸） | AH34: =IFERROR(__xludf.DUMMYFUNCTION("""COMPUTED_VALUE"""),-6.0) -> -6 | AI34: =IFERROR(__xludf.DUMMYFUNCTION("""COMPUTED_VALUE"""),-5.0) -> -5 | AJ34: =IFERROR(__xludf.DUMMYFUNCTION("""COMPUTED_VALUE"""),-4.0) -> -4 | AK34: =IFERROR(__xludf.DUMMYFUNCTION("""COMPUTED_VALUE"""),-3.0) -> -3 | AL34: =IFERROR(__xludf.DUMMYFUNCTION("""COMPUTED_VALUE"""),-2.0) -> -2 | AM34: =IFERROR(__xludf.DUMMYFUNCTION("""COMPUTED_VALUE"""),-1.0) -> -1 | AN34: =IFERROR(__xludf.DUMMYFUNCTION("""COMPUTED_VALUE"""),0.0) -> 0 | AO34: =IFERROR(__xludf.DUMMYFUNCTION("""COMPUTED_VALUE"""),1.0) -> 1 | AP34: =IFERROR(__xludf.DUMMYFUNCTION("""COMPUTED_VALUE"""),2.0) -> 2 | AQ34: =IFERROR(__xludf.DUMMYFUNCTION("""COMPUTED_VALUE"""),3.0) -> 3 | AR34: =IFERROR(__xludf.DUMMYFUNCTION("""COMPUTED_VALUE"""),4.0) -> 4 | AS34: =IFERROR(__xludf.DUMMYFUNCTION("""COMPUTED_VALUE"""),5.0) -> 5 | AT34: =IFERROR(__xludf.DUMMYFUNCTION("""COMPUTED_VALUE"""),5.0) -> 5 | AU34: =IFERROR(__xludf.DUMMYFUNCTION("""COMPUTED_VALUE"""),45996.0) -> 45996 | AV34: =IFERROR(__xludf.DUMMYFUNCTION("""COMPUTED_VALUE"""),46002.0) -> 46002 | AW34: =IFERROR(__xludf.DUMMYFUNCTION("""COMPUTED_VALUE"""),46007.0) -> 46007 | BB34: =IFERROR(__xludf.DUMMYFUNCTION("""COMPUTED_VALUE"""),"なめらかで極細の糸から創り上げた、着心地抜群のストレッチ新素材") -> なめらかで極細の糸から創り上げた、着心地抜群のストレッチ新素材 | BC34: =IFERROR(__xludf.DUMMYFUNCTION("""COMPUTED_VALUE"""),"W240001") -> W240001 | BD34: =IFERROR(__xludf.DUMMYFUNCTION("""COMPUTED_VALUE"""),"出しNG（再製作）ジャケット・スラックス") -> 出しNG（再製作）ジャケット・スラックス
D35: =IFERROR(__xludf.DUMMYFUNCTION("""COMPUTED_VALUE"""),"カフス") -> カフス | F35: =IFERROR(__xludf.DUMMYFUNCTION("""COMPUTED_VALUE"""),-10.0) -> -10 | G35: =IFERROR(__xludf.DUMMYFUNCTION("""COMPUTED_VALUE"""),-9.0) -> -9 | H35: =IFERROR(__xludf.DUMMYFUNCTION("""COMPUTED_VALUE"""),-8.0) -> -8 | I35: =IFERROR(__xludf.DUMMYFUNCTION("""COMPUTED_VALUE"""),-7.0) -> -7 | J35: =IFERROR(__xludf.DUMMYFUNCTION("""COMPUTED_VALUE"""),-6.0) -> -6 | K35: =IFERROR(__xludf.DUMMYFUNCTION("""COMPUTED_VALUE"""),-5.0) -> -5 | L35: =IFERROR(__xludf.DUMMYFUNCTION("""COMPUTED_VALUE"""),-4.0) -> -4 | M35: =IFERROR(__xludf.DUMMYFUNCTION("""COMPUTED_VALUE"""),-3.0) -> -3 | N35: =IFERROR(__xludf.DUMMYFUNCTION("""COMPUTED_VALUE"""),-2.0) -> -2 | O35: =IFERROR(__xludf.DUMMYFUNCTION("""COMPUTED_VALUE"""),-1.0) -> -1 | P35: =IFERROR(__xludf.DUMMYFUNCTION("""COMPUTED_VALUE"""),0.0) -> 0 | Q35: =IFERROR(__xludf.DUMMYFUNCTION("""COMPUTED_VALUE"""),1.0) -> 1 | R35: =IFERROR(__xludf.DUMMYFUNCTION("""COMPUTED_VALUE"""),2.0) -> 2 | S35: =IFERROR(__xludf.DUMMYFUNCTION("""COMPUTED_VALUE"""),3.0) -> 3 | T35: =IFERROR(__xludf.DUMMYFUNCTION("""COMPUTED_VALUE"""),4.0) -> 4 | U35: =IFERROR(__xludf.DUMMYFUNCTION("""COMPUTED_VALUE"""),5.0) -> 5 | V35: =IFERROR(__xludf.DUMMYFUNCTION("""COMPUTED_VALUE"""),"-") -> - | W35: =IFERROR(__xludf.DUMMYFUNCTION("""COMPUTED_VALUE"""),"-") -> - | X35: =IFERROR(__xludf.DUMMYFUNCTION("""COMPUTED_VALUE"""),"-") -> - | Y35: =IFERROR(__xludf.DUMMYFUNCTION("""COMPUTED_VALUE"""),"-") -> - | AF35: =IFERROR(__xludf.DUMMYFUNCTION("""COMPUTED_VALUE"""),"裾口巾（半寸）") -> 裾口巾（半寸） | AH35: =IFERROR(__xludf.DUMMYFUNCTION("""COMPUTED_VALUE"""),-6.0) -> -6 | AI35: =IFERROR(__xludf.DUMMYFUNCTION("""COMPUTED_VALUE"""),-5.0) -> -5 | AJ35: =IFERROR(__xludf.DUMMYFUNCTION("""COMPUTED_VALUE"""),-4.0) -> -4 | AK35: =IFERROR(__xludf.DUMMYFUNCTION("""COMPUTED_VALUE"""),-3.0) -> -3 | AL35: =IFERROR(__xludf.DUMMYFUNCTION("""COMPUTED_VALUE"""),-2.0) -> -2 | AM35: =IFERROR(__xludf.DUMMYFUNCTION("""COMPUTED_VALUE"""),-1.0) -> -1 | AN35: =IFERROR(__xludf.DUMMYFUNCTION("""COMPUTED_VALUE"""),0.0) -> 0 | AO35: =IFERROR(__xludf.DUMMYFUNCTION("""COMPUTED_VALUE"""),1.0) -> 1 | AP35: =IFERROR(__xludf.DUMMYFUNCTION("""COMPUTED_VALUE"""),2.0) -> 2 | AQ35: =IFERROR(__xludf.DUMMYFUNCTION("""COMPUTED_VALUE"""),3.0) -> 3 | AR35: =IFERROR(__xludf.DUMMYFUNCTION("""COMPUTED_VALUE"""),4.0) -> 4 | AS35: =IFERROR(__xludf.DUMMYFUNCTION("""COMPUTED_VALUE"""),5.0) -> 5 | AT35: =IFERROR(__xludf.DUMMYFUNCTION("""COMPUTED_VALUE"""),5.0) -> 5 | AU35: =IFERROR(__xludf.DUMMYFUNCTION("""COMPUTED_VALUE"""),45996.0) -> 45996 | AV35: =IFERROR(__xludf.DUMMYFUNCTION("""COMPUTED_VALUE"""),46002.0) -> 46002 | AW35: =IFERROR(__xludf.DUMMYFUNCTION("""COMPUTED_VALUE"""),46007.0) -> 46007 | BB35: =IFERROR(__xludf.DUMMYFUNCTION("""COMPUTED_VALUE"""),"なめらかで極細の糸から創り上げた、着心地抜群のストレッチ新素材") -> なめらかで極細の糸から創り上げた、着心地抜群のストレッチ新素材 | BC35: =IFERROR(__xludf.DUMMYFUNCTION("""COMPUTED_VALUE"""),"W240002") -> W240002 | BD35: =IFERROR(__xludf.DUMMYFUNCTION("""COMPUTED_VALUE"""),"出しNG（再製作）ジャケット・スラックス") -> 出しNG（再製作）ジャケット・スラックス
D36: =IFERROR(__xludf.DUMMYFUNCTION("""COMPUTED_VALUE"""),"バスト") -> バスト | F36: =IFERROR(__xludf.DUMMYFUNCTION("""COMPUTED_VALUE"""),-10.0) -> -10 | G36: =IFERROR(__xludf.DUMMYFUNCTION("""COMPUTED_VALUE"""),-9.0) -> -9 | H36: =IFERROR(__xludf.DUMMYFUNCTION("""COMPUTED_VALUE"""),-8.0) -> -8 | I36: =IFERROR(__xludf.DUMMYFUNCTION("""COMPUTED_VALUE"""),-7.0) -> -7 | J36: =IFERROR(__xludf.DUMMYFUNCTION("""COMPUTED_VALUE"""),-6.0) -> -6 | K36: =IFERROR(__xludf.DUMMYFUNCTION("""COMPUTED_VALUE"""),-5.0) -> -5 | L36: =IFERROR(__xludf.DUMMYFUNCTION("""COMPUTED_VALUE"""),-4.0) -> -4 | M36: =IFERROR(__xludf.DUMMYFUNCTION("""COMPUTED_VALUE"""),-3.0) -> -3 | N36: =IFERROR(__xludf.DUMMYFUNCTION("""COMPUTED_VALUE"""),-2.0) -> -2 | O36: =IFERROR(__xludf.DUMMYFUNCTION("""COMPUTED_VALUE"""),-1.0) -> -1 | P36: =IFERROR(__xludf.DUMMYFUNCTION("""COMPUTED_VALUE"""),0.0) -> 0 | Q36: =IFERROR(__xludf.DUMMYFUNCTION("""COMPUTED_VALUE"""),1.0) -> 1 | R36: =IFERROR(__xludf.DUMMYFUNCTION("""COMPUTED_VALUE"""),2.0) -> 2 | S36: =IFERROR(__xludf.DUMMYFUNCTION("""COMPUTED_VALUE"""),3.0) -> 3 | T36: =IFERROR(__xludf.DUMMYFUNCTION("""COMPUTED_VALUE"""),4.0) -> 4 | U36: =IFERROR(__xludf.DUMMYFUNCTION("""COMPUTED_VALUE"""),5.0) -> 5 | V36: =IFERROR(__xludf.DUMMYFUNCTION("""COMPUTED_VALUE"""),7.0) -> 7 | W36: =IFERROR(__xludf.DUMMYFUNCTION("""COMPUTED_VALUE"""),46000.0) -> 46000 | X36: =IFERROR(__xludf.DUMMYFUNCTION("""COMPUTED_VALUE"""),46003.0) -> 46003 | Y36: =IFERROR(__xludf.DUMMYFUNCTION("""COMPUTED_VALUE"""),46008.0) -> 46008 | AE36: =IFERROR(__xludf.DUMMYFUNCTION("""COMPUTED_VALUE"""),"縫製") -> 縫製 | AF36: =IFERROR(__xludf.DUMMYFUNCTION("""COMPUTED_VALUE"""),"ベルトループ付け直し") -> ベルトループ付け直し | AG36: =IFERROR(__xludf.DUMMYFUNCTION("""COMPUTED_VALUE"""),"縫製/依頼シートをつけてTB出荷") -> 縫製/依頼シートをつけてTB出荷 | AT36: =IFERROR(__xludf.DUMMYFUNCTION("""COMPUTED_VALUE"""),4.0) -> 4 | AU36: =IFERROR(__xludf.DUMMYFUNCTION("""COMPUTED_VALUE"""),45995.0) -> 45995 | BB36: =IFERROR(__xludf.DUMMYFUNCTION("""COMPUTED_VALUE"""),"なめらかで極細の糸から創り上げた、着心地抜群のストレッチ新素材") -> なめらかで極細の糸から創り上げた、着心地抜群のストレッチ新素材 | BC36: =IFERROR(__xludf.DUMMYFUNCTION("""COMPUTED_VALUE"""),"W240003") -> W240003 | BD36: =IFERROR(__xludf.DUMMYFUNCTION("""COMPUTED_VALUE"""),"出しNG（再製作）ジャケット・スラックス") -> 出しNG（再製作）ジャケット・スラックス
D37: =IFERROR(__xludf.DUMMYFUNCTION("""COMPUTED_VALUE"""),"アームホール") -> アームホール | E37: =IFERROR(__xludf.DUMMYFUNCTION("""COMPUTED_VALUE"""),"※バストと連動。 数値指定は再製作") -> ※バストと連動。 数値指定は再製作 | F37: =IFERROR(__xludf.DUMMYFUNCTION("""COMPUTED_VALUE"""),-10.0) -> -10 | G37: =IFERROR(__xludf.DUMMYFUNCTION("""COMPUTED_VALUE"""),-9.0) -> -9 | H37: =IFERROR(__xludf.DUMMYFUNCTION("""COMPUTED_VALUE"""),-8.0) -> -8 | I37: =IFERROR(__xludf.DUMMYFUNCTION("""COMPUTED_VALUE"""),-7.0) -> -7 | J37: =IFERROR(__xludf.DUMMYFUNCTION("""COMPUTED_VALUE"""),-6.0) -> -6 | K37: =IFERROR(__xludf.DUMMYFUNCTION("""COMPUTED_VALUE"""),-5.0) -> -5 | L37: =IFERROR(__xludf.DUMMYFUNCTION("""COMPUTED_VALUE"""),-4.0) -> -4 | M37: =IFERROR(__xludf.DUMMYFUNCTION("""COMPUTED_VALUE"""),-3.0) -> -3 | N37: =IFERROR(__xludf.DUMMYFUNCTION("""COMPUTED_VALUE"""),-2.0) -> -2 | O37: =IFERROR(__xludf.DUMMYFUNCTION("""COMPUTED_VALUE"""),-1.0) -> -1 | P37: =IFERROR(__xludf.DUMMYFUNCTION("""COMPUTED_VALUE"""),0.0) -> 0 | Q37: =IFERROR(__xludf.DUMMYFUNCTION("""COMPUTED_VALUE"""),1.0) -> 1 | R37: =IFERROR(__xludf.DUMMYFUNCTION("""COMPUTED_VALUE"""),2.0) -> 2 | S37: =IFERROR(__xludf.DUMMYFUNCTION("""COMPUTED_VALUE"""),3.0) -> 3 | T37: =IFERROR(__xludf.DUMMYFUNCTION("""COMPUTED_VALUE"""),4.0) -> 4 | U37: =IFERROR(__xludf.DUMMYFUNCTION("""COMPUTED_VALUE"""),5.0) -> 5 | V37: =IFERROR(__xludf.DUMMYFUNCTION("""COMPUTED_VALUE"""),7.0) -> 7 | W37: =IFERROR(__xludf.DUMMYFUNCTION("""COMPUTED_VALUE"""),46000.0) -> 46000 | X37: =IFERROR(__xludf.DUMMYFUNCTION("""COMPUTED_VALUE"""),46003.0) -> 46003 | Y37: =IFERROR(__xludf.DUMMYFUNCTION("""COMPUTED_VALUE"""),46008.0) -> 46008 | AF37: =IFERROR(__xludf.DUMMYFUNCTION("""COMPUTED_VALUE"""),"裾まつり直し") -> 裾まつり直し | AG37: =IFERROR(__xludf.DUMMYFUNCTION("""COMPUTED_VALUE"""),"縫製/依頼シートをつけてTB出荷") -> 縫製/依頼シートをつけてTB出荷 | AT37: =IFERROR(__xludf.DUMMYFUNCTION("""COMPUTED_VALUE"""),4.0) -> 4 | AU37: =IFERROR(__xludf.DUMMYFUNCTION("""COMPUTED_VALUE"""),45995.0) -> 45995 | BB37: =IFERROR(__xludf.DUMMYFUNCTION("""COMPUTED_VALUE"""),"史上最軽量、KAJIFの技術が詰まったリサイクルファブリック") -> 史上最軽量、KAJIFの技術が詰まったリサイクルファブリック | BC37: =IFERROR(__xludf.DUMMYFUNCTION("""COMPUTED_VALUE"""),"W240004") -> W240004 | BD37: =IFERROR(__xludf.DUMMYFUNCTION("""COMPUTED_VALUE"""),"問題なし") -> 問題なし
D38: =IFERROR(__xludf.DUMMYFUNCTION("""COMPUTED_VALUE"""),"ウエスト") -> ウエスト | F38: =IFERROR(__xludf.DUMMYFUNCTION("""COMPUTED_VALUE"""),-10.0) -> -10 | G38: =IFERROR(__xludf.DUMMYFUNCTION("""COMPUTED_VALUE"""),-9.0) -> -9 | H38: =IFERROR(__xludf.DUMMYFUNCTION("""COMPUTED_VALUE"""),-8.0) -> -8 | I38: =IFERROR(__xludf.DUMMYFUNCTION("""COMPUTED_VALUE"""),-7.0) -> -7 | J38: =IFERROR(__xludf.DUMMYFUNCTION("""COMPUTED_VALUE"""),-6.0) -> -6 | K38: =IFERROR(__xludf.DUMMYFUNCTION("""COMPUTED_VALUE"""),-5.0) -> -5 | L38: =IFERROR(__xludf.DUMMYFUNCTION("""COMPUTED_VALUE"""),-4.0) -> -4 | M38: =IFERROR(__xludf.DUMMYFUNCTION("""COMPUTED_VALUE"""),-3.0) -> -3 | N38: =IFERROR(__xludf.DUMMYFUNCTION("""COMPUTED_VALUE"""),-2.0) -> -2 | O38: =IFERROR(__xludf.DUMMYFUNCTION("""COMPUTED_VALUE"""),-1.0) -> -1 | P38: =IFERROR(__xludf.DUMMYFUNCTION("""COMPUTED_VALUE"""),0.0) -> 0 | Q38: =IFERROR(__xludf.DUMMYFUNCTION("""COMPUTED_VALUE"""),1.0) -> 1 | R38: =IFERROR(__xludf.DUMMYFUNCTION("""COMPUTED_VALUE"""),2.0) -> 2 | S38: =IFERROR(__xludf.DUMMYFUNCTION("""COMPUTED_VALUE"""),3.0) -> 3 | T38: =IFERROR(__xludf.DUMMYFUNCTION("""COMPUTED_VALUE"""),4.0) -> 4 | U38: =IFERROR(__xludf.DUMMYFUNCTION("""COMPUTED_VALUE"""),5.0) -> 5 | V38: =IFERROR(__xludf.DUMMYFUNCTION("""COMPUTED_VALUE"""),7.0) -> 7 | W38: =IFERROR(__xludf.DUMMYFUNCTION("""COMPUTED_VALUE"""),46000.0) -> 46000 | X38: =IFERROR(__xludf.DUMMYFUNCTION("""COMPUTED_VALUE"""),46003.0) -> 46003 | Y38: =IFERROR(__xludf.DUMMYFUNCTION("""COMPUTED_VALUE"""),46008.0) -> 46008 | AF38: =IFERROR(__xludf.DUMMYFUNCTION("""COMPUTED_VALUE"""),"緩くなったボタンの付け直し") -> 緩くなったボタンの付け直し | AG38: =IFERROR(__xludf.DUMMYFUNCTION("""COMPUTED_VALUE"""),"縫製/依頼シートをつけてTB出荷") -> 縫製/依頼シートをつけてTB出荷 | AT38: =IFERROR(__xludf.DUMMYFUNCTION("""COMPUTED_VALUE"""),4.0) -> 4 | AU38: =IFERROR(__xludf.DUMMYFUNCTION("""COMPUTED_VALUE"""),45995.0) -> 45995 | AX38: =IFERROR(__xludf.DUMMYFUNCTION("""COMPUTED_VALUE"""),"120/個数") -> 120/個数 | AY38: =IFERROR(__xludf.DUMMYFUNCTION("""COMPUTED_VALUE"""),"180/個数") -> 180/個数 | BB38: =IFERROR(__xludf.DUMMYFUNCTION("""COMPUTED_VALUE"""),"史上最軽量、KAJIFの技術が詰まったリサイクルファブリック") -> 史上最軽量、KAJIFの技術が詰まったリサイクルファブリック | BC38: =IFERROR(__xludf.DUMMYFUNCTION("""COMPUTED_VALUE"""),"W240005") -> W240005 | BD38: =IFERROR(__xludf.DUMMYFUNCTION("""COMPUTED_VALUE"""),"問題なし") -> 問題なし
D39: =IFERROR(__xludf.DUMMYFUNCTION("""COMPUTED_VALUE"""),"着丈") -> 着丈 | F39: =IFERROR(__xludf.DUMMYFUNCTION("""COMPUTED_VALUE"""),-10.0) -> -10 | G39: =IFERROR(__xludf.DUMMYFUNCTION("""COMPUTED_VALUE"""),-9.0) -> -9 | H39: =IFERROR(__xludf.DUMMYFUNCTION("""COMPUTED_VALUE"""),-8.0) -> -8 | I39: =IFERROR(__xludf.DUMMYFUNCTION("""COMPUTED_VALUE"""),-7.0) -> -7 | J39: =IFERROR(__xludf.DUMMYFUNCTION("""COMPUTED_VALUE"""),-6.0) -> -6 | K39: =IFERROR(__xludf.DUMMYFUNCTION("""COMPUTED_VALUE"""),-5.0) -> -5 | L39: =IFERROR(__xludf.DUMMYFUNCTION("""COMPUTED_VALUE"""),-4.0) -> -4 | M39: =IFERROR(__xludf.DUMMYFUNCTION("""COMPUTED_VALUE"""),-3.0) -> -3 | N39: =IFERROR(__xludf.DUMMYFUNCTION("""COMPUTED_VALUE"""),-2.0) -> -2 | O39: =IFERROR(__xludf.DUMMYFUNCTION("""COMPUTED_VALUE"""),-1.0) -> -1 | P39: =IFERROR(__xludf.DUMMYFUNCTION("""COMPUTED_VALUE"""),0.0) -> 0 | Q39: =IFERROR(__xludf.DUMMYFUNCTION("""COMPUTED_VALUE"""),1.0) -> 1 | R39: =IFERROR(__xludf.DUMMYFUNCTION("""COMPUTED_VALUE"""),2.0) -> 2 | S39: =IFERROR(__xludf.DUMMYFUNCTION("""COMPUTED_VALUE"""),3.0) -> 3 | T39: =IFERROR(__xludf.DUMMYFUNCTION("""COMPUTED_VALUE"""),4.0) -> 4 | U39: =IFERROR(__xludf.DUMMYFUNCTION("""COMPUTED_VALUE"""),5.0) -> 5 | V39: =IFERROR(__xludf.DUMMYFUNCTION("""COMPUTED_VALUE"""),7.0) -> 7 | W39: =IFERROR(__xludf.DUMMYFUNCTION("""COMPUTED_VALUE"""),46000.0) -> 46000 | X39: =IFERROR(__xludf.DUMMYFUNCTION("""COMPUTED_VALUE"""),46003.0) -> 46003 | Y39: =IFERROR(__xludf.DUMMYFUNCTION("""COMPUTED_VALUE"""),46008.0) -> 46008 | AF39: =IFERROR(__xludf.DUMMYFUNCTION("""COMPUTED_VALUE"""),"再プレス") -> 再プレス | AG39: =IFERROR(__xludf.DUMMYFUNCTION("""COMPUTED_VALUE"""),"縫製/依頼シートをつけてTB出荷") -> 縫製/依頼シートをつけてTB出荷 | AT39: =IFERROR(__xludf.DUMMYFUNCTION("""COMPUTED_VALUE"""),4.0) -> 4 | AU39: =IFERROR(__xludf.DUMMYFUNCTION("""COMPUTED_VALUE"""),45995.0) -> 45995 | AX39: =IFERROR(__xludf.DUMMYFUNCTION("""COMPUTED_VALUE"""),580.0) -> 580 | BB39: =IFERROR(__xludf.DUMMYFUNCTION("""COMPUTED_VALUE"""),"史上最軽量、KAJIFの技術が詰まったリサイクルファブリック") -> 史上最軽量、KAJIFの技術が詰まったリサイクルファブリック | BC39: =IFERROR(__xludf.DUMMYFUNCTION("""COMPUTED_VALUE"""),"W240006") -> W240006 | BD39: =IFERROR(__xludf.DUMMYFUNCTION("""COMPUTED_VALUE"""),"問題なし") -> 問題なし
D40: =IFERROR(__xludf.DUMMYFUNCTION("""COMPUTED_VALUE"""),"肩巾") -> 肩巾 | F40: =IFERROR(__xludf.DUMMYFUNCTION("""COMPUTED_VALUE"""),-10.0) -> -10 | G40: =IFERROR(__xludf.DUMMYFUNCTION("""COMPUTED_VALUE"""),-9.0) -> -9 | H40: =IFERROR(__xludf.DUMMYFUNCTION("""COMPUTED_VALUE"""),-8.0) -> -8 | I40: =IFERROR(__xludf.DUMMYFUNCTION("""COMPUTED_VALUE"""),-7.0) -> -7 | J40: =IFERROR(__xludf.DUMMYFUNCTION("""COMPUTED_VALUE"""),-6.0) -> -6 | K40: =IFERROR(__xludf.DUMMYFUNCTION("""COMPUTED_VALUE"""),-5.0) -> -5 | L40: =IFERROR(__xludf.DUMMYFUNCTION("""COMPUTED_VALUE"""),-4.0) -> -4 | M40: =IFERROR(__xludf.DUMMYFUNCTION("""COMPUTED_VALUE"""),-3.0) -> -3 | N40: =IFERROR(__xludf.DUMMYFUNCTION("""COMPUTED_VALUE"""),-2.0) -> -2 | O40: =IFERROR(__xludf.DUMMYFUNCTION("""COMPUTED_VALUE"""),-1.0) -> -1 | P40: =IFERROR(__xludf.DUMMYFUNCTION("""COMPUTED_VALUE"""),0.0) -> 0 | Q40: =IFERROR(__xludf.DUMMYFUNCTION("""COMPUTED_VALUE"""),1.0) -> 1 | R40: =IFERROR(__xludf.DUMMYFUNCTION("""COMPUTED_VALUE"""),2.0) -> 2 | S40: =IFERROR(__xludf.DUMMYFUNCTION("""COMPUTED_VALUE"""),3.0) -> 3 | T40: =IFERROR(__xludf.DUMMYFUNCTION("""COMPUTED_VALUE"""),4.0) -> 4 | U40: =IFERROR(__xludf.DUMMYFUNCTION("""COMPUTED_VALUE"""),5.0) -> 5 | V40: =IFERROR(__xludf.DUMMYFUNCTION("""COMPUTED_VALUE"""),7.0) -> 7 | W40: =IFERROR(__xludf.DUMMYFUNCTION("""COMPUTED_VALUE"""),46000.0) -> 46000 | X40: =IFERROR(__xludf.DUMMYFUNCTION("""COMPUTED_VALUE"""),46003.0) -> 46003 | Y40: =IFERROR(__xludf.DUMMYFUNCTION("""COMPUTED_VALUE"""),46008.0) -> 46008 | BB40: =IFERROR(__xludf.DUMMYFUNCTION("""COMPUTED_VALUE"""),"史上最軽量、KAJIFの技術が詰まったリサイクルファブリック") -> 史上最軽量、KAJIFの技術が詰まったリサイクルファブリック | BC40: =IFERROR(__xludf.DUMMYFUNCTION("""COMPUTED_VALUE"""),"W240007") -> W240007 | BD40: =IFERROR(__xludf.DUMMYFUNCTION("""COMPUTED_VALUE"""),"問題なし") -> 問題なし
D41: =IFERROR(__xludf.DUMMYFUNCTION("""COMPUTED_VALUE"""),"ヒップ") -> ヒップ | F41: =IFERROR(__xludf.DUMMYFUNCTION("""COMPUTED_VALUE"""),-10.0) -> -10 | G41: =IFERROR(__xludf.DUMMYFUNCTION("""COMPUTED_VALUE"""),-9.0) -> -9 | H41: =IFERROR(__xludf.DUMMYFUNCTION("""COMPUTED_VALUE"""),-8.0) -> -8 | I41: =IFERROR(__xludf.DUMMYFUNCTION("""COMPUTED_VALUE"""),-7.0) -> -7 | J41: =IFERROR(__xludf.DUMMYFUNCTION("""COMPUTED_VALUE"""),-6.0) -> -6 | K41: =IFERROR(__xludf.DUMMYFUNCTION("""COMPUTED_VALUE"""),-5.0) -> -5 | L41: =IFERROR(__xludf.DUMMYFUNCTION("""COMPUTED_VALUE"""),-4.0) -> -4 | M41: =IFERROR(__xludf.DUMMYFUNCTION("""COMPUTED_VALUE"""),-3.0) -> -3 | N41: =IFERROR(__xludf.DUMMYFUNCTION("""COMPUTED_VALUE"""),-2.0) -> -2 | O41: =IFERROR(__xludf.DUMMYFUNCTION("""COMPUTED_VALUE"""),-1.0) -> -1 | P41: =IFERROR(__xludf.DUMMYFUNCTION("""COMPUTED_VALUE"""),0.0) -> 0 | Q41: =IFERROR(__xludf.DUMMYFUNCTION("""COMPUTED_VALUE"""),1.0) -> 1 | R41: =IFERROR(__xludf.DUMMYFUNCTION("""COMPUTED_VALUE"""),2.0) -> 2 | S41: =IFERROR(__xludf.DUMMYFUNCTION("""COMPUTED_VALUE"""),3.0) -> 3 | T41: =IFERROR(__xludf.DUMMYFUNCTION("""COMPUTED_VALUE"""),4.0) -> 4 | U41: =IFERROR(__xludf.DUMMYFUNCTION("""COMPUTED_VALUE"""),5.0) -> 5 | V41: =IFERROR(__xludf.DUMMYFUNCTION("""COMPUTED_VALUE"""),7.0) -> 7 | W41: =IFERROR(__xludf.DUMMYFUNCTION("""COMPUTED_VALUE"""),46000.0) -> 46000 | X41: =IFERROR(__xludf.DUMMYFUNCTION("""COMPUTED_VALUE"""),46003.0) -> 46003 | Y41: =IFERROR(__xludf.DUMMYFUNCTION("""COMPUTED_VALUE"""),46008.0) -> 46008 | AD41: =IFERROR(__xludf.DUMMYFUNCTION("""COMPUTED_VALUE"""),"サポ内 縫製生地不良 到着して間もなく、弊社瑕疵の可能性のあるもの 縫製・汚れ対応依頼シートで記入") -> サポ内 縫製生地不良 到着して間もなく、弊社瑕疵の可能性のあるもの 縫製・汚れ対応依頼シートで記入 | BB41: =IFERROR(__xludf.DUMMYFUNCTION("""COMPUTED_VALUE"""),"世界に挑む技術、テック×テーラードで魅せる新感覚シボレザー") -> 世界に挑む技術、テック×テーラードで魅せる新感覚シボレザー | BC41: =IFERROR(__xludf.DUMMYFUNCTION("""COMPUTED_VALUE"""),"W240009") -> W240009 | BD41: =IFERROR(__xludf.DUMMYFUNCTION("""COMPUTED_VALUE"""),"出しNG（再製作）ジャケット・スラックス") -> 出しNG（再製作）ジャケット・スラックス
AD42: =IFERROR(__xludf.DUMMYFUNCTION("""COMPUTED_VALUE"""),"アイテム") -> アイテム | AE42: =IFERROR(__xludf.DUMMYFUNCTION("""COMPUTED_VALUE"""),"ジャンル") -> ジャンル | AF42: =IFERROR(__xludf.DUMMYFUNCTION("""COMPUTED_VALUE"""),"事象") -> 事象 | AG42: =IFERROR(__xludf.DUMMYFUNCTION("""COMPUTED_VALUE"""),"対応条件 お直し内容が確定できず、不明な場合は cs確認依頼_縫製関連へ") -> 対応条件 お直し内容が確定できず、不明な場合は cs確認依頼_縫製関連へ | AN42: =IFERROR(__xludf.DUMMYFUNCTION("""COMPUTED_VALUE"""),"マニュアルリンク") -> マニュアルリンク | AT42: =IFERROR(__xludf.DUMMYFUNCTION("""COMPUTED_VALUE"""),"営業日") -> 営業日 | AU42: =IFERROR(__xludf.DUMMYFUNCTION("""COMPUTED_VALUE"""),"1箇所納期") -> 1箇所納期 | AV42: =IFERROR(__xludf.DUMMYFUNCTION("""COMPUTED_VALUE"""),"2箇所納期") -> 2箇所納期 | AW42: =IFERROR(__xludf.DUMMYFUNCTION("""COMPUTED_VALUE"""),"縫製・汚れ対応依頼シート ") -> 縫製・汚れ対応依頼シート | AX42: =IFERROR(__xludf.DUMMYFUNCTION("""COMPUTED_VALUE"""),"CS確認依頼する必要") -> CS確認依頼する必要 | BB42: =IFERROR(__xludf.DUMMYFUNCTION("""COMPUTED_VALUE"""),"世界に挑む技術、テック×テーラードで魅せる新感覚シボレザー") -> 世界に挑む技術、テック×テーラードで魅せる新感覚シボレザー | BC42: =IFERROR(__xludf.DUMMYFUNCTION("""COMPUTED_VALUE"""),"W240010") -> W240010 | BD42: =IFERROR(__xludf.DUMMYFUNCTION("""COMPUTED_VALUE"""),"出しNG（再製作）ジャケット・スラックス") -> 出しNG（再製作）ジャケット・スラックス
B43: =IFERROR(__xludf.DUMMYFUNCTION("""COMPUTED_VALUE""")," シャツ半袖 タックアウト半袖") -> シャツ半袖 タックアウト半袖 | C43: =IFERROR(__xludf.DUMMYFUNCTION("""COMPUTED_VALUE"""),"サイズ") -> サイズ | D43: =IFERROR(__xludf.DUMMYFUNCTION("""COMPUTED_VALUE"""),"裄丈") -> 裄丈 | F43: =IFERROR(__xludf.DUMMYFUNCTION("""COMPUTED_VALUE"""),-10.0) -> -10 | G43: =IFERROR(__xludf.DUMMYFUNCTION("""COMPUTED_VALUE"""),-9.0) -> -9 | H43: =IFERROR(__xludf.DUMMYFUNCTION("""COMPUTED_VALUE"""),-8.0) -> -8 | I43: =IFERROR(__xludf.DUMMYFUNCTION("""COMPUTED_VALUE"""),-7.0) -> -7 | J43: =IFERROR(__xludf.DUMMYFUNCTION("""COMPUTED_VALUE"""),-6.0) -> -6 | K43: =IFERROR(__xludf.DUMMYFUNCTION("""COMPUTED_VALUE"""),-5.0) -> -5 | L43: =IFERROR(__xludf.DUMMYFUNCTION("""COMPUTED_VALUE"""),-4.0) -> -4 | M43: =IFERROR(__xludf.DUMMYFUNCTION("""COMPUTED_VALUE"""),-3.0) -> -3 | N43: =IFERROR(__xludf.DUMMYFUNCTION("""COMPUTED_VALUE"""),-2.0) -> -2 | O43: =IFERROR(__xludf.DUMMYFUNCTION("""COMPUTED_VALUE"""),-1.0) -> -1 | P43: =IFERROR(__xludf.DUMMYFUNCTION("""COMPUTED_VALUE"""),0.0) -> 0 | Q43: =IFERROR(__xludf.DUMMYFUNCTION("""COMPUTED_VALUE"""),1.0) -> 1 | R43: =IFERROR(__xludf.DUMMYFUNCTION("""COMPUTED_VALUE"""),2.0) -> 2 | S43: =IFERROR(__xludf.DUMMYFUNCTION("""COMPUTED_VALUE"""),3.0) -> 3 | T43: =IFERROR(__xludf.DUMMYFUNCTION("""COMPUTED_VALUE"""),4.0) -> 4 | U43: =IFERROR(__xludf.DUMMYFUNCTION("""COMPUTED_VALUE"""),5.0) -> 5 | V43: =IFERROR(__xludf.DUMMYFUNCTION("""COMPUTED_VALUE"""),"-") -> - | W43: =IFERROR(__xludf.DUMMYFUNCTION("""COMPUTED_VALUE"""),"-") -> - | X43: =IFERROR(__xludf.DUMMYFUNCTION("""COMPUTED_VALUE"""),"-") -> - | Y43: =IFERROR(__xludf.DUMMYFUNCTION("""COMPUTED_VALUE"""),"-") -> - | AD43: =IFERROR(__xludf.DUMMYFUNCTION("""COMPUTED_VALUE"""),"全アイテム") -> 全アイテム | AE43: =IFERROR(__xludf.DUMMYFUNCTION("""COMPUTED_VALUE"""),"縫製") -> 縫製 | AF43: =IFERROR(__xludf.DUMMYFUNCTION("""COMPUTED_VALUE"""),"各種ほつれ") -> 各種ほつれ | AG43: =IFERROR(__xludf.DUMMYFUNCTION("""COMPUTED_VALUE"""),"縫製/依頼シートをつけてTB出荷 対応可否についてはマニュアル参照 ") -> 縫製/依頼シートをつけてTB出荷 対応可否についてはマニュアル参照 | AN43: =IFERROR(__xludf.DUMMYFUNCTION("""COMPUTED_VALUE"""),"https://www.notion.so/fabric-tokyo/10-0913b4c011c346c0b37737686571aaa1") -> https://www.notion.so/fabric-tokyo/10-0913b4c011c346c0b37737686571aaa1 | AT43: =IFERROR(__xludf.DUMMYFUNCTION("""COMPUTED_VALUE"""),7.0) -> 7 | AU43: =IFERROR(__xludf.DUMMYFUNCTION("""COMPUTED_VALUE"""),46000.0) -> 46000 | AV43: =IFERROR(__xludf.DUMMYFUNCTION("""COMPUTED_VALUE"""),46009.0) -> 46009 | AW43: =IFERROR(__xludf.DUMMYFUNCTION("""COMPUTED_VALUE"""),"必要") -> 必要 | AX43: =IFERROR(__xludf.DUMMYFUNCTION("""COMPUTED_VALUE"""),"確認不要") -> 確認不要 | BB43: =IFERROR(__xludf.DUMMYFUNCTION("""COMPUTED_VALUE"""),"世界に挑む技術、レザーを超える艶レザー調テックサテン") -> 世界に挑む技術、レザーを超える艶レザー調テックサテン | BC43: =IFERROR(__xludf.DUMMYFUNCTION("""COMPUTED_VALUE"""),"W240011") -> W240011 | BD43: =IFERROR(__xludf.DUMMYFUNCTION("""COMPUTED_VALUE"""),"出しNG（再製作）ジャケット・スラックス") -> 出しNG（再製作）ジャケット・スラックス
D44: =IFERROR(__xludf.DUMMYFUNCTION("""COMPUTED_VALUE"""),"襟") -> 襟 | F44: =IFERROR(__xludf.DUMMYFUNCTION("""COMPUTED_VALUE"""),-10.0) -> -10 | G44: =IFERROR(__xludf.DUMMYFUNCTION("""COMPUTED_VALUE"""),-9.0) -> -9 | H44: =IFERROR(__xludf.DUMMYFUNCTION("""COMPUTED_VALUE"""),-8.0) -> -8 | I44: =IFERROR(__xludf.DUMMYFUNCTION("""COMPUTED_VALUE"""),-7.0) -> -7 | J44: =IFERROR(__xludf.DUMMYFUNCTION("""COMPUTED_VALUE"""),-6.0) -> -6 | K44: =IFERROR(__xludf.DUMMYFUNCTION("""COMPUTED_VALUE"""),-5.0) -> -5 | L44: =IFERROR(__xludf.DUMMYFUNCTION("""COMPUTED_VALUE"""),-4.0) -> -4 | M44: =IFERROR(__xludf.DUMMYFUNCTION("""COMPUTED_VALUE"""),-3.0) -> -3 | N44: =IFERROR(__xludf.DUMMYFUNCTION("""COMPUTED_VALUE"""),-2.0) -> -2 | O44: =IFERROR(__xludf.DUMMYFUNCTION("""COMPUTED_VALUE"""),-1.0) -> -1 | P44: =IFERROR(__xludf.DUMMYFUNCTION("""COMPUTED_VALUE"""),0.0) -> 0 | Q44: =IFERROR(__xludf.DUMMYFUNCTION("""COMPUTED_VALUE"""),1.0) -> 1 | R44: =IFERROR(__xludf.DUMMYFUNCTION("""COMPUTED_VALUE"""),2.0) -> 2 | S44: =IFERROR(__xludf.DUMMYFUNCTION("""COMPUTED_VALUE"""),3.0) -> 3 | T44: =IFERROR(__xludf.DUMMYFUNCTION("""COMPUTED_VALUE"""),4.0) -> 4 | U44: =IFERROR(__xludf.DUMMYFUNCTION("""COMPUTED_VALUE"""),5.0) -> 5 | V44: =IFERROR(__xludf.DUMMYFUNCTION("""COMPUTED_VALUE"""),"-") -> - | W44: =IFERROR(__xludf.DUMMYFUNCTION("""COMPUTED_VALUE"""),"-") -> - | X44: =IFERROR(__xludf.DUMMYFUNCTION("""COMPUTED_VALUE"""),"-") -> - | Y44: =IFERROR(__xludf.DUMMYFUNCTION("""COMPUTED_VALUE"""),"-") -> - | AD44: =IFERROR(__xludf.DUMMYFUNCTION("""COMPUTED_VALUE"""),"全アイテム") -> 全アイテム | AE44: =IFERROR(__xludf.DUMMYFUNCTION("""COMPUTED_VALUE"""),"縫製") -> 縫製 | AF44: =IFERROR(__xludf.DUMMYFUNCTION("""COMPUTED_VALUE"""),"糸飛び") -> 糸飛び | AG44: =IFERROR(__xludf.DUMMYFUNCTION("""COMPUTED_VALUE"""),"縫製/依頼シートをつけてTB出荷 対応可否についてはマニュアル参照 ") -> 縫製/依頼シートをつけてTB出荷 対応可否についてはマニュアル参照 | AN44: =IFERROR(__xludf.DUMMYFUNCTION("""COMPUTED_VALUE"""),"https://www.notion.so/fabric-tokyo/10-20-27d49967a235803aa6a6cb4a27095ff6") -> https://www.notion.so/fabric-tokyo/10-20-27d49967a235803aa6a6cb4a27095ff6 | AT44: =IFERROR(__xludf.DUMMYFUNCTION("""COMPUTED_VALUE"""),7.0) -> 7 | AU44: =IFERROR(__xludf.DUMMYFUNCTION("""COMPUTED_VALUE"""),46000.0) -> 46000 | AV44: =IFERROR(__xludf.DUMMYFUNCTION("""COMPUTED_VALUE"""),46009.0) -> 46009 | AW44: =IFERROR(__xludf.DUMMYFUNCTION("""COMPUTED_VALUE"""),"必要") -> 必要 | AX44: =IFERROR(__xludf.DUMMYFUNCTION("""COMPUTED_VALUE"""),"確認不要") -> 確認不要 | BB44: =IFERROR(__xludf.DUMMYFUNCTION("""COMPUTED_VALUE"""),"世界に挑む技術、テック×テーラードで魅せる新感覚シボレザー") -> 世界に挑む技術、テック×テーラードで魅せる新感覚シボレザー | BC44: =IFERROR(__xludf.DUMMYFUNCTION("""COMPUTED_VALUE"""),"W240012") -> W240012 | BD44: =IFERROR(__xludf.DUMMYFUNCTION("""COMPUTED_VALUE"""),"出しNG（再製作）ジャケット・スラックス") -> 出しNG（再製作）ジャケット・スラックス
D45: =IFERROR(__xludf.DUMMYFUNCTION("""COMPUTED_VALUE"""),"カフス") -> カフス | F45: =IFERROR(__xludf.DUMMYFUNCTION("""COMPUTED_VALUE"""),-10.0) -> -10 | G45: =IFERROR(__xludf.DUMMYFUNCTION("""COMPUTED_VALUE"""),-9.0) -> -9 | H45: =IFERROR(__xludf.DUMMYFUNCTION("""COMPUTED_VALUE"""),-8.0) -> -8 | I45: =IFERROR(__xludf.DUMMYFUNCTION("""COMPUTED_VALUE"""),-7.0) -> -7 | J45: =IFERROR(__xludf.DUMMYFUNCTION("""COMPUTED_VALUE"""),-6.0) -> -6 | K45: =IFERROR(__xludf.DUMMYFUNCTION("""COMPUTED_VALUE"""),-5.0) -> -5 | L45: =IFERROR(__xludf.DUMMYFUNCTION("""COMPUTED_VALUE"""),-4.0) -> -4 | M45: =IFERROR(__xludf.DUMMYFUNCTION("""COMPUTED_VALUE"""),-3.0) -> -3 | N45: =IFERROR(__xludf.DUMMYFUNCTION("""COMPUTED_VALUE"""),-2.0) -> -2 | O45: =IFERROR(__xludf.DUMMYFUNCTION("""COMPUTED_VALUE"""),-1.0) -> -1 | P45: =IFERROR(__xludf.DUMMYFUNCTION("""COMPUTED_VALUE"""),0.0) -> 0 | Q45: =IFERROR(__xludf.DUMMYFUNCTION("""COMPUTED_VALUE"""),1.0) -> 1 | R45: =IFERROR(__xludf.DUMMYFUNCTION("""COMPUTED_VALUE"""),2.0) -> 2 | S45: =IFERROR(__xludf.DUMMYFUNCTION("""COMPUTED_VALUE"""),3.0) -> 3 | T45: =IFERROR(__xludf.DUMMYFUNCTION("""COMPUTED_VALUE"""),4.0) -> 4 | U45: =IFERROR(__xludf.DUMMYFUNCTION("""COMPUTED_VALUE"""),5.0) -> 5 | V45: =IFERROR(__xludf.DUMMYFUNCTION("""COMPUTED_VALUE"""),"-") -> - | W45: =IFERROR(__xludf.DUMMYFUNCTION("""COMPUTED_VALUE"""),"-") -> - | X45: =IFERROR(__xludf.DUMMYFUNCTION("""COMPUTED_VALUE"""),"-") -> - | Y45: =IFERROR(__xludf.DUMMYFUNCTION("""COMPUTED_VALUE"""),"-") -> - | AD45: =IFERROR(__xludf.DUMMYFUNCTION("""COMPUTED_VALUE"""),"全アイテム") -> 全アイテム | AE45: =IFERROR(__xludf.DUMMYFUNCTION("""COMPUTED_VALUE"""),"生地不良") -> 生地不良 | AF45: =IFERROR(__xludf.DUMMYFUNCTION("""COMPUTED_VALUE"""),"生地のネップ") -> 生地のネップ | AG45: =IFERROR(__xludf.DUMMYFUNCTION("""COMPUTED_VALUE"""),"縫製/依頼シートをつけてTB出荷 対応可否についてはマニュアル参照 ") -> 縫製/依頼シートをつけてTB出荷 対応可否についてはマニュアル参照 | AN45: =IFERROR(__xludf.DUMMYFUNCTION("""COMPUTED_VALUE"""),"https://www.notion.so/fabric-tokyo/10-21-27d49967a2358001a3b5f0b7164773ac") -> https://www.notion.so/fabric-tokyo/10-21-27d49967a2358001a3b5f0b7164773ac | AT45: =IFERROR(__xludf.DUMMYFUNCTION("""COMPUTED_VALUE"""),7.0) -> 7 | AU45: =IFERROR(__xludf.DUMMYFUNCTION("""COMPUTED_VALUE"""),46000.0) -> 46000 | AV45: =IFERROR(__xludf.DUMMYFUNCTION("""COMPUTED_VALUE"""),46009.0) -> 46009 | AW45: =IFERROR(__xludf.DUMMYFUNCTION("""COMPUTED_VALUE"""),"必要") -> 必要 | AX45: =IFERROR(__xludf.DUMMYFUNCTION("""COMPUTED_VALUE"""),"確認不要") -> 確認不要 | BB45: =IFERROR(__xludf.DUMMYFUNCTION("""COMPUTED_VALUE"""),"天然の消臭抗菌、和紙から作った風通しのいいデニム") -> 天然の消臭抗菌、和紙から作った風通しのいいデニム | BC45: =IFERROR(__xludf.DUMMYFUNCTION("""COMPUTED_VALUE"""),"W240013") -> W240013 | BD45: =IFERROR(__xludf.DUMMYFUNCTION("""COMPUTED_VALUE"""),"出しNG（再製作）ジャケット・スラックス") -> 出しNG（再製作）ジャケット・スラックス
D46: =IFERROR(__xludf.DUMMYFUNCTION("""COMPUTED_VALUE"""),"バスト") -> バスト | F46: =IFERROR(__xludf.DUMMYFUNCTION("""COMPUTED_VALUE"""),-10.0) -> -10 | G46: =IFERROR(__xludf.DUMMYFUNCTION("""COMPUTED_VALUE"""),-9.0) -> -9 | H46: =IFERROR(__xludf.DUMMYFUNCTION("""COMPUTED_VALUE"""),-8.0) -> -8 | I46: =IFERROR(__xludf.DUMMYFUNCTION("""COMPUTED_VALUE"""),-7.0) -> -7 | J46: =IFERROR(__xludf.DUMMYFUNCTION("""COMPUTED_VALUE"""),-6.0) -> -6 | K46: =IFERROR(__xludf.DUMMYFUNCTION("""COMPUTED_VALUE"""),-5.0) -> -5 | L46: =IFERROR(__xludf.DUMMYFUNCTION("""COMPUTED_VALUE"""),-4.0) -> -4 | M46: =IFERROR(__xludf.DUMMYFUNCTION("""COMPUTED_VALUE"""),-3.0) -> -3 | N46: =IFERROR(__xludf.DUMMYFUNCTION("""COMPUTED_VALUE"""),-2.0) -> -2 | O46: =IFERROR(__xludf.DUMMYFUNCTION("""COMPUTED_VALUE"""),-1.0) -> -1 | P46: =IFERROR(__xludf.DUMMYFUNCTION("""COMPUTED_VALUE"""),0.0) -> 0 | Q46: =IFERROR(__xludf.DUMMYFUNCTION("""COMPUTED_VALUE"""),1.0) -> 1 | R46: =IFERROR(__xludf.DUMMYFUNCTION("""COMPUTED_VALUE"""),2.0) -> 2 | S46: =IFERROR(__xludf.DUMMYFUNCTION("""COMPUTED_VALUE"""),3.0) -> 3 | T46: =IFERROR(__xludf.DUMMYFUNCTION("""COMPUTED_VALUE"""),4.0) -> 4 | U46: =IFERROR(__xludf.DUMMYFUNCTION("""COMPUTED_VALUE"""),5.0) -> 5 | V46: =IFERROR(__xludf.DUMMYFUNCTION("""COMPUTED_VALUE"""),7.0) -> 7 | W46: =IFERROR(__xludf.DUMMYFUNCTION("""COMPUTED_VALUE"""),46000.0) -> 46000 | X46: =IFERROR(__xludf.DUMMYFUNCTION("""COMPUTED_VALUE"""),46003.0) -> 46003 | Y46: =IFERROR(__xludf.DUMMYFUNCTION("""COMPUTED_VALUE"""),46008.0) -> 46008 | AD46: =IFERROR(__xludf.DUMMYFUNCTION("""COMPUTED_VALUE"""),"スラックス・チノ") -> スラックス・チノ | AE46: =IFERROR(__xludf.DUMMYFUNCTION("""COMPUTED_VALUE"""),"縫製") -> 縫製 | AF46: =IFERROR(__xludf.DUMMYFUNCTION("""COMPUTED_VALUE"""),"ファスナー破損交換") -> ファスナー破損交換 | AG46: =IFERROR(__xludf.DUMMYFUNCTION("""COMPUTED_VALUE"""),"縫製/依頼シートをつけてTB出荷 対応可否についてはマニュアル参照 ") -> 縫製/依頼シートをつけてTB出荷 対応可否についてはマニュアル参照 | AN46: =IFERROR(__xludf.DUMMYFUNCTION("""COMPUTED_VALUE"""),"https://www.notion.so/fabric-tokyo/10-15-6fd0369bf9524f398f3379c18f7b3fdf") -> https://www.notion.so/fabric-tokyo/10-15-6fd0369bf9524f398f3379c18f7b3fdf | AT46: =IFERROR(__xludf.DUMMYFUNCTION("""COMPUTED_VALUE"""),7.0) -> 7 | AU46: =IFERROR(__xludf.DUMMYFUNCTION("""COMPUTED_VALUE"""),46000.0) -> 46000 | AV46: =IFERROR(__xludf.DUMMYFUNCTION("""COMPUTED_VALUE"""),"-") -> - | AW46: =IFERROR(__xludf.DUMMYFUNCTION("""COMPUTED_VALUE"""),"必要") -> 必要 | AX46: =IFERROR(__xludf.DUMMYFUNCTION("""COMPUTED_VALUE"""),"確認不要") -> 確認不要 | BB46: =IFERROR(__xludf.DUMMYFUNCTION("""COMPUTED_VALUE"""),"北陸の柔軟さが実現させた、高密度でなめらかなリッチブラックサテン") -> 北陸の柔軟さが実現させた、高密度でなめらかなリッチブラックサテン | BC46: =IFERROR(__xludf.DUMMYFUNCTION("""COMPUTED_VALUE"""),"W240014") -> W240014 | BD46: =IFERROR(__xludf.DUMMYFUNCTION("""COMPUTED_VALUE"""),"出しNG（再製作）ジャケット・スラックス") -> 出しNG（再製作）ジャケット・スラックス
D47: =IFERROR(__xludf.DUMMYFUNCTION("""COMPUTED_VALUE"""),"アームホール") -> アームホール | E47: =IFERROR(__xludf.DUMMYFUNCTION("""COMPUTED_VALUE"""),"※バストと連動。 数値指定は再製作") -> ※バストと連動。 数値指定は再製作 | F47: =IFERROR(__xludf.DUMMYFUNCTION("""COMPUTED_VALUE"""),-10.0) -> -10 | G47: =IFERROR(__xludf.DUMMYFUNCTION("""COMPUTED_VALUE"""),-9.0) -> -9 | H47: =IFERROR(__xludf.DUMMYFUNCTION("""COMPUTED_VALUE"""),-8.0) -> -8 | I47: =IFERROR(__xludf.DUMMYFUNCTION("""COMPUTED_VALUE"""),-7.0) -> -7 | J47: =IFERROR(__xludf.DUMMYFUNCTION("""COMPUTED_VALUE"""),-6.0) -> -6 | K47: =IFERROR(__xludf.DUMMYFUNCTION("""COMPUTED_VALUE"""),-5.0) -> -5 | L47: =IFERROR(__xludf.DUMMYFUNCTION("""COMPUTED_VALUE"""),-4.0) -> -4 | M47: =IFERROR(__xludf.DUMMYFUNCTION("""COMPUTED_VALUE"""),-3.0) -> -3 | N47: =IFERROR(__xludf.DUMMYFUNCTION("""COMPUTED_VALUE"""),-2.0) -> -2 | O47: =IFERROR(__xludf.DUMMYFUNCTION("""COMPUTED_VALUE"""),-1.0) -> -1 | P47: =IFERROR(__xludf.DUMMYFUNCTION("""COMPUTED_VALUE"""),0.0) -> 0 | Q47: =IFERROR(__xludf.DUMMYFUNCTION("""COMPUTED_VALUE"""),1.0) -> 1 | R47: =IFERROR(__xludf.DUMMYFUNCTION("""COMPUTED_VALUE"""),2.0) -> 2 | S47: =IFERROR(__xludf.DUMMYFUNCTION("""COMPUTED_VALUE"""),3.0) -> 3 | T47: =IFERROR(__xludf.DUMMYFUNCTION("""COMPUTED_VALUE"""),4.0) -> 4 | U47: =IFERROR(__xludf.DUMMYFUNCTION("""COMPUTED_VALUE"""),5.0) -> 5 | V47: =IFERROR(__xludf.DUMMYFUNCTION("""COMPUTED_VALUE"""),7.0) -> 7 | W47: =IFERROR(__xludf.DUMMYFUNCTION("""COMPUTED_VALUE"""),46000.0) -> 46000 | X47: =IFERROR(__xludf.DUMMYFUNCTION("""COMPUTED_VALUE"""),46003.0) -> 46003 | Y47: =IFERROR(__xludf.DUMMYFUNCTION("""COMPUTED_VALUE"""),46008.0) -> 46008 | AD47: =IFERROR(__xludf.DUMMYFUNCTION("""COMPUTED_VALUE"""),"シャツ") -> シャツ | AE47: =IFERROR(__xludf.DUMMYFUNCTION("""COMPUTED_VALUE"""),"カスタマイズ") -> カスタマイズ | AF47: =IFERROR(__xludf.DUMMYFUNCTION("""COMPUTED_VALUE"""),"胸ポケットつけ忘れ") -> 胸ポケットつけ忘れ | AG47: =IFERROR(__xludf.DUMMYFUNCTION("""COMPUTED_VALUE"""),"弊社瑕疵、胸ポケットのカスタマイズ指示がされているが、ついていない場合 国内工場製作分でのみ対応可") -> 弊社瑕疵、胸ポケットのカスタマイズ指示がされているが、ついていない場合 国内工場製作分でのみ対応可 | AT47: =IFERROR(__xludf.DUMMYFUNCTION("""COMPUTED_VALUE"""),10.0) -> 10 | AU47: =IFERROR(__xludf.DUMMYFUNCTION("""COMPUTED_VALUE"""),46003.0) -> 46003 | AV47: =IFERROR(__xludf.DUMMYFUNCTION("""COMPUTED_VALUE"""),"-") -> - | AW47: =IFERROR(__xludf.DUMMYFUNCTION("""COMPUTED_VALUE"""),"必要") -> 必要 | AX47: =IFERROR(__xludf.DUMMYFUNCTION("""COMPUTED_VALUE"""),"確認必要") -> 確認必要 | BB47: =IFERROR(__xludf.DUMMYFUNCTION("""COMPUTED_VALUE"""),"織物のような美しい光沢感と発色で、北陸と尾州を旅したラグジュアリージャージー") -> 織物のような美しい光沢感と発色で、北陸と尾州を旅したラグジュアリージャージー | BC47: =IFERROR(__xludf.DUMMYFUNCTION("""COMPUTED_VALUE"""),"W240015") -> W240015 | BD47: =IFERROR(__xludf.DUMMYFUNCTION("""COMPUTED_VALUE"""),"出しNG（再製作）ジャケット・スラックス") -> 出しNG（再製作）ジャケット・スラックス
D48: =IFERROR(__xludf.DUMMYFUNCTION("""COMPUTED_VALUE"""),"ウエスト") -> ウエスト | F48: =IFERROR(__xludf.DUMMYFUNCTION("""COMPUTED_VALUE"""),-10.0) -> -10 | G48: =IFERROR(__xludf.DUMMYFUNCTION("""COMPUTED_VALUE"""),-9.0) -> -9 | H48: =IFERROR(__xludf.DUMMYFUNCTION("""COMPUTED_VALUE"""),-8.0) -> -8 | I48: =IFERROR(__xludf.DUMMYFUNCTION("""COMPUTED_VALUE"""),-7.0) -> -7 | J48: =IFERROR(__xludf.DUMMYFUNCTION("""COMPUTED_VALUE"""),-6.0) -> -6 | K48: =IFERROR(__xludf.DUMMYFUNCTION("""COMPUTED_VALUE"""),-5.0) -> -5 | L48: =IFERROR(__xludf.DUMMYFUNCTION("""COMPUTED_VALUE"""),-4.0) -> -4 | M48: =IFERROR(__xludf.DUMMYFUNCTION("""COMPUTED_VALUE"""),-3.0) -> -3 | N48: =IFERROR(__xludf.DUMMYFUNCTION("""COMPUTED_VALUE"""),-2.0) -> -2 | O48: =IFERROR(__xludf.DUMMYFUNCTION("""COMPUTED_VALUE"""),-1.0) -> -1 | P48: =IFERROR(__xludf.DUMMYFUNCTION("""COMPUTED_VALUE"""),0.0) -> 0 | Q48: =IFERROR(__xludf.DUMMYFUNCTION("""COMPUTED_VALUE"""),1.0) -> 1 | R48: =IFERROR(__xludf.DUMMYFUNCTION("""COMPUTED_VALUE"""),2.0) -> 2 | S48: =IFERROR(__xludf.DUMMYFUNCTION("""COMPUTED_VALUE"""),3.0) -> 3 | T48: =IFERROR(__xludf.DUMMYFUNCTION("""COMPUTED_VALUE"""),4.0) -> 4 | U48: =IFERROR(__xludf.DUMMYFUNCTION("""COMPUTED_VALUE"""),5.0) -> 5 | V48: =IFERROR(__xludf.DUMMYFUNCTION("""COMPUTED_VALUE"""),7.0) -> 7 | W48: =IFERROR(__xludf.DUMMYFUNCTION("""COMPUTED_VALUE"""),46000.0) -> 46000 | X48: =IFERROR(__xludf.DUMMYFUNCTION("""COMPUTED_VALUE"""),46003.0) -> 46003 | Y48: =IFERROR(__xludf.DUMMYFUNCTION("""COMPUTED_VALUE"""),46008.0) -> 46008 | AD48: =IFERROR(__xludf.DUMMYFUNCTION("""COMPUTED_VALUE"""),"スラックス・チノ") -> スラックス・チノ | AE48: =IFERROR(__xludf.DUMMYFUNCTION("""COMPUTED_VALUE"""),"縫製") -> 縫製 | AF48: =IFERROR(__xludf.DUMMYFUNCTION("""COMPUTED_VALUE"""),"クリースステッチ") -> クリースステッチ | AG48: =IFERROR(__xludf.DUMMYFUNCTION("""COMPUTED_VALUE"""),"クリースの糸のみが切れている場合に限り対応可能") -> クリースの糸のみが切れている場合に限り対応可能 | AN48: =IFERROR(__xludf.DUMMYFUNCTION("""COMPUTED_VALUE"""),"https://www.notion.so/fabric-tokyo/10-16-4c1fa9072e024588b94a67997bf1af95") -> https://www.notion.so/fabric-tokyo/10-16-4c1fa9072e024588b94a67997bf1af95 | AT48: =IFERROR(__xludf.DUMMYFUNCTION("""COMPUTED_VALUE"""),12.0) -> 12 | AU48: =IFERROR(__xludf.DUMMYFUNCTION("""COMPUTED_VALUE"""),46007.0) -> 46007 | AV48: =IFERROR(__xludf.DUMMYFUNCTION("""COMPUTED_VALUE"""),46037.0) -> 46037 | AW48: =IFERROR(__xludf.DUMMYFUNCTION("""COMPUTED_VALUE"""),"必要") -> 必要 | AX48: =IFERROR(__xludf.DUMMYFUNCTION("""COMPUTED_VALUE"""),"確認不要") -> 確認不要 | BB48: =IFERROR(__xludf.DUMMYFUNCTION("""COMPUTED_VALUE"""),"織物のような美しい光沢感と発色で、北陸と尾州を旅したラグジュアリージャージー") -> 織物のような美しい光沢感と発色で、北陸と尾州を旅したラグジュアリージャージー | BC48: =IFERROR(__xludf.DUMMYFUNCTION("""COMPUTED_VALUE"""),"W240016") -> W240016 | BD48: =IFERROR(__xludf.DUMMYFUNCTION("""COMPUTED_VALUE"""),"出しNG（再製作）ジャケット・スラックス") -> 出しNG（再製作）ジャケット・スラックス
D49: =IFERROR(__xludf.DUMMYFUNCTION("""COMPUTED_VALUE"""),"着丈") -> 着丈 | F49: =IFERROR(__xludf.DUMMYFUNCTION("""COMPUTED_VALUE"""),-10.0) -> -10 | G49: =IFERROR(__xludf.DUMMYFUNCTION("""COMPUTED_VALUE"""),-9.0) -> -9 | H49: =IFERROR(__xludf.DUMMYFUNCTION("""COMPUTED_VALUE"""),-8.0) -> -8 | I49: =IFERROR(__xludf.DUMMYFUNCTION("""COMPUTED_VALUE"""),-7.0) -> -7 | J49: =IFERROR(__xludf.DUMMYFUNCTION("""COMPUTED_VALUE"""),-6.0) -> -6 | K49: =IFERROR(__xludf.DUMMYFUNCTION("""COMPUTED_VALUE"""),-5.0) -> -5 | L49: =IFERROR(__xludf.DUMMYFUNCTION("""COMPUTED_VALUE"""),-4.0) -> -4 | M49: =IFERROR(__xludf.DUMMYFUNCTION("""COMPUTED_VALUE"""),-3.0) -> -3 | N49: =IFERROR(__xludf.DUMMYFUNCTION("""COMPUTED_VALUE"""),-2.0) -> -2 | O49: =IFERROR(__xludf.DUMMYFUNCTION("""COMPUTED_VALUE"""),-1.0) -> -1 | P49: =IFERROR(__xludf.DUMMYFUNCTION("""COMPUTED_VALUE"""),0.0) -> 0 | Q49: =IFERROR(__xludf.DUMMYFUNCTION("""COMPUTED_VALUE"""),1.0) -> 1 | R49: =IFERROR(__xludf.DUMMYFUNCTION("""COMPUTED_VALUE"""),2.0) -> 2 | S49: =IFERROR(__xludf.DUMMYFUNCTION("""COMPUTED_VALUE"""),3.0) -> 3 | T49: =IFERROR(__xludf.DUMMYFUNCTION("""COMPUTED_VALUE"""),4.0) -> 4 | U49: =IFERROR(__xludf.DUMMYFUNCTION("""COMPUTED_VALUE"""),5.0) -> 5 | V49: =IFERROR(__xludf.DUMMYFUNCTION("""COMPUTED_VALUE"""),7.0) -> 7 | W49: =IFERROR(__xludf.DUMMYFUNCTION("""COMPUTED_VALUE"""),46000.0) -> 46000 | X49: =IFERROR(__xludf.DUMMYFUNCTION("""COMPUTED_VALUE"""),46003.0) -> 46003 | Y49: =IFERROR(__xludf.DUMMYFUNCTION("""COMPUTED_VALUE"""),46008.0) -> 46008 | BB49: =IFERROR(__xludf.DUMMYFUNCTION("""COMPUTED_VALUE"""),"やわらかい上品さに包みこまれる、北陸素材で作った世界初の近江晒シャツ") -> やわらかい上品さに包みこまれる、北陸素材で作った世界初の近江晒シャツ | BC49: =IFERROR(__xludf.DUMMYFUNCTION("""COMPUTED_VALUE"""),"W240017") -> W240017 | BD49: =IFERROR(__xludf.DUMMYFUNCTION("""COMPUTED_VALUE"""),"出しNG（再製作）ジャケット・スラックス") -> 出しNG（再製作）ジャケット・スラックス
D50: =IFERROR(__xludf.DUMMYFUNCTION("""COMPUTED_VALUE"""),"肩巾") -> 肩巾 | F50: =IFERROR(__xludf.DUMMYFUNCTION("""COMPUTED_VALUE"""),-10.0) -> -10 | G50: =IFERROR(__xludf.DUMMYFUNCTION("""COMPUTED_VALUE"""),-9.0) -> -9 | H50: =IFERROR(__xludf.DUMMYFUNCTION("""COMPUTED_VALUE"""),-8.0) -> -8 | I50: =IFERROR(__xludf.DUMMYFUNCTION("""COMPUTED_VALUE"""),-7.0) -> -7 | J50: =IFERROR(__xludf.DUMMYFUNCTION("""COMPUTED_VALUE"""),-6.0) -> -6 | K50: =IFERROR(__xludf.DUMMYFUNCTION("""COMPUTED_VALUE"""),-5.0) -> -5 | L50: =IFERROR(__xludf.DUMMYFUNCTION("""COMPUTED_VALUE"""),-4.0) -> -4 | M50: =IFERROR(__xludf.DUMMYFUNCTION("""COMPUTED_VALUE"""),-3.0) -> -3 | N50: =IFERROR(__xludf.DUMMYFUNCTION("""COMPUTED_VALUE"""),-2.0) -> -2 | O50: =IFERROR(__xludf.DUMMYFUNCTION("""COMPUTED_VALUE"""),-1.0) -> -1 | P50: =IFERROR(__xludf.DUMMYFUNCTION("""COMPUTED_VALUE"""),0.0) -> 0 | Q50: =IFERROR(__xludf.DUMMYFUNCTION("""COMPUTED_VALUE"""),1.0) -> 1 | R50: =IFERROR(__xludf.DUMMYFUNCTION("""COMPUTED_VALUE"""),2.0) -> 2 | S50: =IFERROR(__xludf.DUMMYFUNCTION("""COMPUTED_VALUE"""),3.0) -> 3 | T50: =IFERROR(__xludf.DUMMYFUNCTION("""COMPUTED_VALUE"""),4.0) -> 4 | U50: =IFERROR(__xludf.DUMMYFUNCTION("""COMPUTED_VALUE"""),5.0) -> 5 | V50: =IFERROR(__xludf.DUMMYFUNCTION("""COMPUTED_VALUE"""),"-") -> - | W50: =IFERROR(__xludf.DUMMYFUNCTION("""COMPUTED_VALUE"""),"-") -> - | X50: =IFERROR(__xludf.DUMMYFUNCTION("""COMPUTED_VALUE"""),"-") -> - | Y50: =IFERROR(__xludf.DUMMYFUNCTION("""COMPUTED_VALUE"""),"-") -> - | BB50: =IFERROR(__xludf.DUMMYFUNCTION("""COMPUTED_VALUE"""),"保温性・軽さ・イージーケアを実現させた、福井県産のオールラウンダーコート") -> 保温性・軽さ・イージーケアを実現させた、福井県産のオールラウンダーコート | BC50: =IFERROR(__xludf.DUMMYFUNCTION("""COMPUTED_VALUE"""),"W240018") -> W240018 | BD50: =IFERROR(__xludf.DUMMYFUNCTION("""COMPUTED_VALUE"""),"出しNG（再製作）ジャケット・スラックス") -> 出しNG（再製作）ジャケット・スラックス
D51: =IFERROR(__xludf.DUMMYFUNCTION("""COMPUTED_VALUE"""),"ヒップ") -> ヒップ | F51: =IFERROR(__xludf.DUMMYFUNCTION("""COMPUTED_VALUE"""),-10.0) -> -10 | G51: =IFERROR(__xludf.DUMMYFUNCTION("""COMPUTED_VALUE"""),-9.0) -> -9 | H51: =IFERROR(__xludf.DUMMYFUNCTION("""COMPUTED_VALUE"""),-8.0) -> -8 | I51: =IFERROR(__xludf.DUMMYFUNCTION("""COMPUTED_VALUE"""),-7.0) -> -7 | J51: =IFERROR(__xludf.DUMMYFUNCTION("""COMPUTED_VALUE"""),-6.0) -> -6 | K51: =IFERROR(__xludf.DUMMYFUNCTION("""COMPUTED_VALUE"""),-5.0) -> -5 | L51: =IFERROR(__xludf.DUMMYFUNCTION("""COMPUTED_VALUE"""),-4.0) -> -4 | M51: =IFERROR(__xludf.DUMMYFUNCTION("""COMPUTED_VALUE"""),-3.0) -> -3 | N51: =IFERROR(__xludf.DUMMYFUNCTION("""COMPUTED_VALUE"""),-2.0) -> -2 | O51: =IFERROR(__xludf.DUMMYFUNCTION("""COMPUTED_VALUE"""),-1.0) -> -1 | P51: =IFERROR(__xludf.DUMMYFUNCTION("""COMPUTED_VALUE"""),0.0) -> 0 | Q51: =IFERROR(__xludf.DUMMYFUNCTION("""COMPUTED_VALUE"""),1.0) -> 1 | R51: =IFERROR(__xludf.DUMMYFUNCTION("""COMPUTED_VALUE"""),2.0) -> 2 | S51: =IFERROR(__xludf.DUMMYFUNCTION("""COMPUTED_VALUE"""),3.0) -> 3 | T51: =IFERROR(__xludf.DUMMYFUNCTION("""COMPUTED_VALUE"""),4.0) -> 4 | U51: =IFERROR(__xludf.DUMMYFUNCTION("""COMPUTED_VALUE"""),5.0) -> 5 | V51: =IFERROR(__xludf.DUMMYFUNCTION("""COMPUTED_VALUE"""),7.0) -> 7 | W51: =IFERROR(__xludf.DUMMYFUNCTION("""COMPUTED_VALUE"""),46000.0) -> 46000 | X51: =IFERROR(__xludf.DUMMYFUNCTION("""COMPUTED_VALUE"""),46003.0) -> 46003 | Y51: =IFERROR(__xludf.DUMMYFUNCTION("""COMPUTED_VALUE"""),46008.0) -> 46008 | BB51: =IFERROR(__xludf.DUMMYFUNCTION("""COMPUTED_VALUE"""),"保温性・軽さ・イージーケアを実現させた、福井県産のオールラウンダーコート") -> 保温性・軽さ・イージーケアを実現させた、福井県産のオールラウンダーコート | BC51: =IFERROR(__xludf.DUMMYFUNCTION("""COMPUTED_VALUE"""),"W240019") -> W240019 | BD51: =IFERROR(__xludf.DUMMYFUNCTION("""COMPUTED_VALUE"""),"出しNG（再製作）ジャケット・スラックス") -> 出しNG（再製作）ジャケット・スラックス
BB52: =IFERROR(__xludf.DUMMYFUNCTION("""COMPUTED_VALUE"""),"保温性・軽さ・イージーケアを実現させた、福井県産のオールラウンダーコート") -> 保温性・軽さ・イージーケアを実現させた、福井県産のオールラウンダーコート | BC52: =IFERROR(__xludf.DUMMYFUNCTION("""COMPUTED_VALUE"""),"W240020") -> W240020 | BD52: =IFERROR(__xludf.DUMMYFUNCTION("""COMPUTED_VALUE"""),"出しNG（再製作）ジャケット・スラックス") -> 出しNG（再製作）ジャケット・スラックス
B53: =IFERROR(__xludf.DUMMYFUNCTION("""COMPUTED_VALUE""")," オーダーポロ 半袖") -> オーダーポロ 半袖 | C53: =IFERROR(__xludf.DUMMYFUNCTION("""COMPUTED_VALUE"""),"サイズ") -> サイズ | D53: =IFERROR(__xludf.DUMMYFUNCTION("""COMPUTED_VALUE"""),"裄丈") -> 裄丈 | F53: =IFERROR(__xludf.DUMMYFUNCTION("""COMPUTED_VALUE"""),-10.0) -> -10 | G53: =IFERROR(__xludf.DUMMYFUNCTION("""COMPUTED_VALUE"""),-9.0) -> -9 | H53: =IFERROR(__xludf.DUMMYFUNCTION("""COMPUTED_VALUE"""),-8.0) -> -8 | I53: =IFERROR(__xludf.DUMMYFUNCTION("""COMPUTED_VALUE"""),-7.0) -> -7 | J53: =IFERROR(__xludf.DUMMYFUNCTION("""COMPUTED_VALUE"""),-6.0) -> -6 | K53: =IFERROR(__xludf.DUMMYFUNCTION("""COMPUTED_VALUE"""),-5.0) -> -5 | L53: =IFERROR(__xludf.DUMMYFUNCTION("""COMPUTED_VALUE"""),-4.0) -> -4 | M53: =IFERROR(__xludf.DUMMYFUNCTION("""COMPUTED_VALUE"""),-3.0) -> -3 | N53: =IFERROR(__xludf.DUMMYFUNCTION("""COMPUTED_VALUE"""),-2.0) -> -2 | O53: =IFERROR(__xludf.DUMMYFUNCTION("""COMPUTED_VALUE"""),-1.0) -> -1 | P53: =IFERROR(__xludf.DUMMYFUNCTION("""COMPUTED_VALUE"""),0.0) -> 0 | Q53: =IFERROR(__xludf.DUMMYFUNCTION("""COMPUTED_VALUE"""),1.0) -> 1 | R53: =IFERROR(__xludf.DUMMYFUNCTION("""COMPUTED_VALUE"""),2.0) -> 2 | S53: =IFERROR(__xludf.DUMMYFUNCTION("""COMPUTED_VALUE"""),3.0) -> 3 | T53: =IFERROR(__xludf.DUMMYFUNCTION("""COMPUTED_VALUE"""),4.0) -> 4 | U53: =IFERROR(__xludf.DUMMYFUNCTION("""COMPUTED_VALUE"""),5.0) -> 5 | V53: =IFERROR(__xludf.DUMMYFUNCTION("""COMPUTED_VALUE"""),"-") -> - | W53: =IFERROR(__xludf.DUMMYFUNCTION("""COMPUTED_VALUE"""),"-") -> - | X53: =IFERROR(__xludf.DUMMYFUNCTION("""COMPUTED_VALUE"""),"-") -> - | Y53: =IFERROR(__xludf.DUMMYFUNCTION("""COMPUTED_VALUE"""),"-") -> - | BB53: =IFERROR(__xludf.DUMMYFUNCTION("""COMPUTED_VALUE"""),"極上の着心地とハリ感が調和する、ウルトラハイゲージジャージーシャツ") -> 極上の着心地とハリ感が調和する、ウルトラハイゲージジャージーシャツ | BC53: =IFERROR(__xludf.DUMMYFUNCTION("""COMPUTED_VALUE"""),"W240021") -> W240021 | BD53: =IFERROR(__xludf.DUMMYFUNCTION("""COMPUTED_VALUE"""),"出しNG（再製作）ジャケット・スラックス") -> 出しNG（再製作）ジャケット・スラックス
D54: =IFERROR(__xludf.DUMMYFUNCTION("""COMPUTED_VALUE"""),"襟") -> 襟 | F54: =IFERROR(__xludf.DUMMYFUNCTION("""COMPUTED_VALUE"""),-10.0) -> -10 | G54: =IFERROR(__xludf.DUMMYFUNCTION("""COMPUTED_VALUE"""),-9.0) -> -9 | H54: =IFERROR(__xludf.DUMMYFUNCTION("""COMPUTED_VALUE"""),-8.0) -> -8 | I54: =IFERROR(__xludf.DUMMYFUNCTION("""COMPUTED_VALUE"""),-7.0) -> -7 | J54: =IFERROR(__xludf.DUMMYFUNCTION("""COMPUTED_VALUE"""),-6.0) -> -6 | K54: =IFERROR(__xludf.DUMMYFUNCTION("""COMPUTED_VALUE"""),-5.0) -> -5 | L54: =IFERROR(__xludf.DUMMYFUNCTION("""COMPUTED_VALUE"""),-4.0) -> -4 | M54: =IFERROR(__xludf.DUMMYFUNCTION("""COMPUTED_VALUE"""),-3.0) -> -3 | N54: =IFERROR(__xludf.DUMMYFUNCTION("""COMPUTED_VALUE"""),-2.0) -> -2 | O54: =IFERROR(__xludf.DUMMYFUNCTION("""COMPUTED_VALUE"""),-1.0) -> -1 | P54: =IFERROR(__xludf.DUMMYFUNCTION("""COMPUTED_VALUE"""),0.0) -> 0 | Q54: =IFERROR(__xludf.DUMMYFUNCTION("""COMPUTED_VALUE"""),1.0) -> 1 | R54: =IFERROR(__xludf.DUMMYFUNCTION("""COMPUTED_VALUE"""),2.0) -> 2 | S54: =IFERROR(__xludf.DUMMYFUNCTION("""COMPUTED_VALUE"""),3.0) -> 3 | T54: =IFERROR(__xludf.DUMMYFUNCTION("""COMPUTED_VALUE"""),4.0) -> 4 | U54: =IFERROR(__xludf.DUMMYFUNCTION("""COMPUTED_VALUE"""),5.0) -> 5 | V54: =IFERROR(__xludf.DUMMYFUNCTION("""COMPUTED_VALUE"""),"-") -> - | W54: =IFERROR(__xludf.DUMMYFUNCTION("""COMPUTED_VALUE"""),"-") -> - | X54: =IFERROR(__xludf.DUMMYFUNCTION("""COMPUTED_VALUE"""),"-") -> - | Y54: =IFERROR(__xludf.DUMMYFUNCTION("""COMPUTED_VALUE"""),"-") -> - | BB54: =IFERROR(__xludf.DUMMYFUNCTION("""COMPUTED_VALUE"""),"極上の着心地とハリ感が調和する、ウルトラハイゲージジャージーシャツ") -> 極上の着心地とハリ感が調和する、ウルトラハイゲージジャージーシャツ | BC54: =IFERROR(__xludf.DUMMYFUNCTION("""COMPUTED_VALUE"""),"W240022") -> W240022 | BD54: =IFERROR(__xludf.DUMMYFUNCTION("""COMPUTED_VALUE"""),"出しNG（再製作）ジャケット・スラックス") -> 出しNG（再製作）ジャケット・スラックス
D55: =IFERROR(__xludf.DUMMYFUNCTION("""COMPUTED_VALUE"""),"カフス") -> カフス | F55: =IFERROR(__xludf.DUMMYFUNCTION("""COMPUTED_VALUE"""),-10.0) -> -10 | G55: =IFERROR(__xludf.DUMMYFUNCTION("""COMPUTED_VALUE"""),-9.0) -> -9 | H55: =IFERROR(__xludf.DUMMYFUNCTION("""COMPUTED_VALUE"""),-8.0) -> -8 | I55: =IFERROR(__xludf.DUMMYFUNCTION("""COMPUTED_VALUE"""),-7.0) -> -7 | J55: =IFERROR(__xludf.DUMMYFUNCTION("""COMPUTED_VALUE"""),-6.0) -> -6 | K55: =IFERROR(__xludf.DUMMYFUNCTION("""COMPUTED_VALUE"""),-5.0) -> -5 | L55: =IFERROR(__xludf.DUMMYFUNCTION("""COMPUTED_VALUE"""),-4.0) -> -4 | M55: =IFERROR(__xludf.DUMMYFUNCTION("""COMPUTED_VALUE"""),-3.0) -> -3 | N55: =IFERROR(__xludf.DUMMYFUNCTION("""COMPUTED_VALUE"""),-2.0) -> -2 | O55: =IFERROR(__xludf.DUMMYFUNCTION("""COMPUTED_VALUE"""),-1.0) -> -1 | P55: =IFERROR(__xludf.DUMMYFUNCTION("""COMPUTED_VALUE"""),0.0) -> 0 | Q55: =IFERROR(__xludf.DUMMYFUNCTION("""COMPUTED_VALUE"""),1.0) -> 1 | R55: =IFERROR(__xludf.DUMMYFUNCTION("""COMPUTED_VALUE"""),2.0) -> 2 | S55: =IFERROR(__xludf.DUMMYFUNCTION("""COMPUTED_VALUE"""),3.0) -> 3 | T55: =IFERROR(__xludf.DUMMYFUNCTION("""COMPUTED_VALUE"""),4.0) -> 4 | U55: =IFERROR(__xludf.DUMMYFUNCTION("""COMPUTED_VALUE"""),5.0) -> 5 | V55: =IFERROR(__xludf.DUMMYFUNCTION("""COMPUTED_VALUE"""),"-") -> - | W55: =IFERROR(__xludf.DUMMYFUNCTION("""COMPUTED_VALUE"""),"-") -> - | X55: =IFERROR(__xludf.DUMMYFUNCTION("""COMPUTED_VALUE"""),"-") -> - | Y55: =IFERROR(__xludf.DUMMYFUNCTION("""COMPUTED_VALUE"""),"-") -> - | BB55: =IFERROR(__xludf.DUMMYFUNCTION("""COMPUTED_VALUE"""),"極上の着心地とハリ感が調和する、ウルトラハイゲージジャージーシャツ") -> 極上の着心地とハリ感が調和する、ウルトラハイゲージジャージーシャツ | BC55: =IFERROR(__xludf.DUMMYFUNCTION("""COMPUTED_VALUE"""),"W240023") -> W240023 | BD55: =IFERROR(__xludf.DUMMYFUNCTION("""COMPUTED_VALUE"""),"出しNG（再製作）ジャケット・スラックス") -> 出しNG（再製作）ジャケット・スラックス
D56: =IFERROR(__xludf.DUMMYFUNCTION("""COMPUTED_VALUE"""),"バスト") -> バスト | F56: =IFERROR(__xludf.DUMMYFUNCTION("""COMPUTED_VALUE"""),-10.0) -> -10 | G56: =IFERROR(__xludf.DUMMYFUNCTION("""COMPUTED_VALUE"""),-9.0) -> -9 | H56: =IFERROR(__xludf.DUMMYFUNCTION("""COMPUTED_VALUE"""),-8.0) -> -8 | I56: =IFERROR(__xludf.DUMMYFUNCTION("""COMPUTED_VALUE"""),-7.0) -> -7 | J56: =IFERROR(__xludf.DUMMYFUNCTION("""COMPUTED_VALUE"""),-6.0) -> -6 | K56: =IFERROR(__xludf.DUMMYFUNCTION("""COMPUTED_VALUE"""),-5.0) -> -5 | L56: =IFERROR(__xludf.DUMMYFUNCTION("""COMPUTED_VALUE"""),-4.0) -> -4 | M56: =IFERROR(__xludf.DUMMYFUNCTION("""COMPUTED_VALUE"""),-3.0) -> -3 | N56: =IFERROR(__xludf.DUMMYFUNCTION("""COMPUTED_VALUE"""),-2.0) -> -2 | O56: =IFERROR(__xludf.DUMMYFUNCTION("""COMPUTED_VALUE"""),-1.0) -> -1 | P56: =IFERROR(__xludf.DUMMYFUNCTION("""COMPUTED_VALUE"""),0.0) -> 0 | Q56: =IFERROR(__xludf.DUMMYFUNCTION("""COMPUTED_VALUE"""),1.0) -> 1 | R56: =IFERROR(__xludf.DUMMYFUNCTION("""COMPUTED_VALUE"""),2.0) -> 2 | S56: =IFERROR(__xludf.DUMMYFUNCTION("""COMPUTED_VALUE"""),3.0) -> 3 | T56: =IFERROR(__xludf.DUMMYFUNCTION("""COMPUTED_VALUE"""),4.0) -> 4 | U56: =IFERROR(__xludf.DUMMYFUNCTION("""COMPUTED_VALUE"""),5.0) -> 5 | V56: =IFERROR(__xludf.DUMMYFUNCTION("""COMPUTED_VALUE"""),7.0) -> 7 | W56: =IFERROR(__xludf.DUMMYFUNCTION("""COMPUTED_VALUE"""),46000.0) -> 46000 | X56: =IFERROR(__xludf.DUMMYFUNCTION("""COMPUTED_VALUE"""),46003.0) -> 46003 | Y56: =IFERROR(__xludf.DUMMYFUNCTION("""COMPUTED_VALUE"""),46008.0) -> 46008 | BB56: =IFERROR(__xludf.DUMMYFUNCTION("""COMPUTED_VALUE"""),"極上の着心地とハリ感が調和する、ウルトラハイゲージジャージーシャツ") -> 極上の着心地とハリ感が調和する、ウルトラハイゲージジャージーシャツ | BC56: =IFERROR(__xludf.DUMMYFUNCTION("""COMPUTED_VALUE"""),"W240026") -> W240026 | BD56: =IFERROR(__xludf.DUMMYFUNCTION("""COMPUTED_VALUE"""),"出しNG（再製作）ジャケット・スラックス") -> 出しNG（再製作）ジャケット・スラックス
D57: =IFERROR(__xludf.DUMMYFUNCTION("""COMPUTED_VALUE"""),"アームホール") -> アームホール | E57: =IFERROR(__xludf.DUMMYFUNCTION("""COMPUTED_VALUE"""),"※バストと連動。 数値指定は再製作") -> ※バストと連動。 数値指定は再製作 | F57: =IFERROR(__xludf.DUMMYFUNCTION("""COMPUTED_VALUE"""),-10.0) -> -10 | G57: =IFERROR(__xludf.DUMMYFUNCTION("""COMPUTED_VALUE"""),-9.0) -> -9 | H57: =IFERROR(__xludf.DUMMYFUNCTION("""COMPUTED_VALUE"""),-8.0) -> -8 | I57: =IFERROR(__xludf.DUMMYFUNCTION("""COMPUTED_VALUE"""),-7.0) -> -7 | J57: =IFERROR(__xludf.DUMMYFUNCTION("""COMPUTED_VALUE"""),-6.0) -> -6 | K57: =IFERROR(__xludf.DUMMYFUNCTION("""COMPUTED_VALUE"""),-5.0) -> -5 | L57: =IFERROR(__xludf.DUMMYFUNCTION("""COMPUTED_VALUE"""),-4.0) -> -4 | M57: =IFERROR(__xludf.DUMMYFUNCTION("""COMPUTED_VALUE"""),-3.0) -> -3 | N57: =IFERROR(__xludf.DUMMYFUNCTION("""COMPUTED_VALUE"""),-2.0) -> -2 | O57: =IFERROR(__xludf.DUMMYFUNCTION("""COMPUTED_VALUE"""),-1.0) -> -1 | P57: =IFERROR(__xludf.DUMMYFUNCTION("""COMPUTED_VALUE"""),0.0) -> 0 | Q57: =IFERROR(__xludf.DUMMYFUNCTION("""COMPUTED_VALUE"""),1.0) -> 1 | R57: =IFERROR(__xludf.DUMMYFUNCTION("""COMPUTED_VALUE"""),2.0) -> 2 | S57: =IFERROR(__xludf.DUMMYFUNCTION("""COMPUTED_VALUE"""),3.0) -> 3 | T57: =IFERROR(__xludf.DUMMYFUNCTION("""COMPUTED_VALUE"""),4.0) -> 4 | U57: =IFERROR(__xludf.DUMMYFUNCTION("""COMPUTED_VALUE"""),5.0) -> 5 | V57: =IFERROR(__xludf.DUMMYFUNCTION("""COMPUTED_VALUE"""),7.0) -> 7 | W57: =IFERROR(__xludf.DUMMYFUNCTION("""COMPUTED_VALUE"""),46000.0) -> 46000 | X57: =IFERROR(__xludf.DUMMYFUNCTION("""COMPUTED_VALUE"""),46003.0) -> 46003 | Y57: =IFERROR(__xludf.DUMMYFUNCTION("""COMPUTED_VALUE"""),46008.0) -> 46008 | BB57: =IFERROR(__xludf.DUMMYFUNCTION("""COMPUTED_VALUE"""),"極上の着心地とハリ感が調和する、ウルトラハイゲージジャージーシャツ") -> 極上の着心地とハリ感が調和する、ウルトラハイゲージジャージーシャツ | BC57: =IFERROR(__xludf.DUMMYFUNCTION("""COMPUTED_VALUE"""),"W240027") -> W240027 | BD57: =IFERROR(__xludf.DUMMYFUNCTION("""COMPUTED_VALUE"""),"出しNG（再製作）ジャケット・スラックス") -> 出しNG（再製作）ジャケット・スラックス
D58: =IFERROR(__xludf.DUMMYFUNCTION("""COMPUTED_VALUE"""),"ウエスト") -> ウエスト | F58: =IFERROR(__xludf.DUMMYFUNCTION("""COMPUTED_VALUE"""),-10.0) -> -10 | G58: =IFERROR(__xludf.DUMMYFUNCTION("""COMPUTED_VALUE"""),-9.0) -> -9 | H58: =IFERROR(__xludf.DUMMYFUNCTION("""COMPUTED_VALUE"""),-8.0) -> -8 | I58: =IFERROR(__xludf.DUMMYFUNCTION("""COMPUTED_VALUE"""),-7.0) -> -7 | J58: =IFERROR(__xludf.DUMMYFUNCTION("""COMPUTED_VALUE"""),-6.0) -> -6 | K58: =IFERROR(__xludf.DUMMYFUNCTION("""COMPUTED_VALUE"""),-5.0) -> -5 | L58: =IFERROR(__xludf.DUMMYFUNCTION("""COMPUTED_VALUE"""),-4.0) -> -4 | M58: =IFERROR(__xludf.DUMMYFUNCTION("""COMPUTED_VALUE"""),-3.0) -> -3 | N58: =IFERROR(__xludf.DUMMYFUNCTION("""COMPUTED_VALUE"""),-2.0) -> -2 | O58: =IFERROR(__xludf.DUMMYFUNCTION("""COMPUTED_VALUE"""),-1.0) -> -1 | P58: =IFERROR(__xludf.DUMMYFUNCTION("""COMPUTED_VALUE"""),0.0) -> 0 | Q58: =IFERROR(__xludf.DUMMYFUNCTION("""COMPUTED_VALUE"""),1.0) -> 1 | R58: =IFERROR(__xludf.DUMMYFUNCTION("""COMPUTED_VALUE"""),2.0) -> 2 | S58: =IFERROR(__xludf.DUMMYFUNCTION("""COMPUTED_VALUE"""),3.0) -> 3 | T58: =IFERROR(__xludf.DUMMYFUNCTION("""COMPUTED_VALUE"""),4.0) -> 4 | U58: =IFERROR(__xludf.DUMMYFUNCTION("""COMPUTED_VALUE"""),5.0) -> 5 | V58: =IFERROR(__xludf.DUMMYFUNCTION("""COMPUTED_VALUE"""),7.0) -> 7 | W58: =IFERROR(__xludf.DUMMYFUNCTION("""COMPUTED_VALUE"""),46000.0) -> 46000 | X58: =IFERROR(__xludf.DUMMYFUNCTION("""COMPUTED_VALUE"""),46003.0) -> 46003 | Y58: =IFERROR(__xludf.DUMMYFUNCTION("""COMPUTED_VALUE"""),46008.0) -> 46008
D59: =IFERROR(__xludf.DUMMYFUNCTION("""COMPUTED_VALUE"""),"着丈") -> 着丈 | E59: =IFERROR(__xludf.DUMMYFUNCTION("""COMPUTED_VALUE"""),"※スリット移動の為、かんぬきの後が残る ステッチ幅(2.5cm)以下の詰めの場合、素材により修理跡が残ります。") -> ※スリット移動の為、かんぬきの後が残る ステッチ幅(2.5cm)以下の詰めの場合、素材により修理跡が残ります。 | F59: =IFERROR(__xludf.DUMMYFUNCTION("""COMPUTED_VALUE"""),-10.0) -> -10 | G59: =IFERROR(__xludf.DUMMYFUNCTION("""COMPUTED_VALUE"""),-9.0) -> -9 | H59: =IFERROR(__xludf.DUMMYFUNCTION("""COMPUTED_VALUE"""),-8.0) -> -8 | I59: =IFERROR(__xludf.DUMMYFUNCTION("""COMPUTED_VALUE"""),-7.0) -> -7 | J59: =IFERROR(__xludf.DUMMYFUNCTION("""COMPUTED_VALUE"""),-6.0) -> -6 | K59: =IFERROR(__xludf.DUMMYFUNCTION("""COMPUTED_VALUE"""),-5.0) -> -5 | L59: =IFERROR(__xludf.DUMMYFUNCTION("""COMPUTED_VALUE"""),-4.0) -> -4 | M59: =IFERROR(__xludf.DUMMYFUNCTION("""COMPUTED_VALUE"""),-3.0) -> -3 | N59: =IFERROR(__xludf.DUMMYFUNCTION("""COMPUTED_VALUE"""),-2.0) -> -2 | O59: =IFERROR(__xludf.DUMMYFUNCTION("""COMPUTED_VALUE"""),-1.0) -> -1 | P59: =IFERROR(__xludf.DUMMYFUNCTION("""COMPUTED_VALUE"""),0.0) -> 0 | Q59: =IFERROR(__xludf.DUMMYFUNCTION("""COMPUTED_VALUE"""),1.0) -> 1 | R59: =IFERROR(__xludf.DUMMYFUNCTION("""COMPUTED_VALUE"""),2.0) -> 2 | S59: =IFERROR(__xludf.DUMMYFUNCTION("""COMPUTED_VALUE"""),3.0) -> 3 | T59: =IFERROR(__xludf.DUMMYFUNCTION("""COMPUTED_VALUE"""),4.0) -> 4 | U59: =IFERROR(__xludf.DUMMYFUNCTION("""COMPUTED_VALUE"""),5.0) -> 5 | V59: =IFERROR(__xludf.DUMMYFUNCTION("""COMPUTED_VALUE"""),7.0) -> 7 | W59: =IFERROR(__xludf.DUMMYFUNCTION("""COMPUTED_VALUE"""),46000.0) -> 46000 | X59: =IFERROR(__xludf.DUMMYFUNCTION("""COMPUTED_VALUE"""),46003.0) -> 46003 | Y59: =IFERROR(__xludf.DUMMYFUNCTION("""COMPUTED_VALUE"""),46008.0) -> 46008
D60: =IFERROR(__xludf.DUMMYFUNCTION("""COMPUTED_VALUE"""),"肩巾") -> 肩巾 | F60: =IFERROR(__xludf.DUMMYFUNCTION("""COMPUTED_VALUE"""),-10.0) -> -10 | G60: =IFERROR(__xludf.DUMMYFUNCTION("""COMPUTED_VALUE"""),-9.0) -> -9 | H60: =IFERROR(__xludf.DUMMYFUNCTION("""COMPUTED_VALUE"""),-8.0) -> -8 | I60: =IFERROR(__xludf.DUMMYFUNCTION("""COMPUTED_VALUE"""),-7.0) -> -7 | J60: =IFERROR(__xludf.DUMMYFUNCTION("""COMPUTED_VALUE"""),-6.0) -> -6 | K60: =IFERROR(__xludf.DUMMYFUNCTION("""COMPUTED_VALUE"""),-5.0) -> -5 | L60: =IFERROR(__xludf.DUMMYFUNCTION("""COMPUTED_VALUE"""),-4.0) -> -4 | M60: =IFERROR(__xludf.DUMMYFUNCTION("""COMPUTED_VALUE"""),-3.0) -> -3 | N60: =IFERROR(__xludf.DUMMYFUNCTION("""COMPUTED_VALUE"""),-2.0) -> -2 | O60: =IFERROR(__xludf.DUMMYFUNCTION("""COMPUTED_VALUE"""),-1.0) -> -1 | P60: =IFERROR(__xludf.DUMMYFUNCTION("""COMPUTED_VALUE"""),0.0) -> 0 | Q60: =IFERROR(__xludf.DUMMYFUNCTION("""COMPUTED_VALUE"""),1.0) -> 1 | R60: =IFERROR(__xludf.DUMMYFUNCTION("""COMPUTED_VALUE"""),2.0) -> 2 | S60: =IFERROR(__xludf.DUMMYFUNCTION("""COMPUTED_VALUE"""),3.0) -> 3 | T60: =IFERROR(__xludf.DUMMYFUNCTION("""COMPUTED_VALUE"""),4.0) -> 4 | U60: =IFERROR(__xludf.DUMMYFUNCTION("""COMPUTED_VALUE"""),5.0) -> 5 | V60: =IFERROR(__xludf.DUMMYFUNCTION("""COMPUTED_VALUE"""),"-") -> - | W60: =IFERROR(__xludf.DUMMYFUNCTION("""COMPUTED_VALUE"""),"-") -> - | X60: =IFERROR(__xludf.DUMMYFUNCTION("""COMPUTED_VALUE"""),"-") -> - | Y60: =IFERROR(__xludf.DUMMYFUNCTION("""COMPUTED_VALUE"""),"-") -> -
D61: =IFERROR(__xludf.DUMMYFUNCTION("""COMPUTED_VALUE"""),"ヒップ") -> ヒップ | F61: =IFERROR(__xludf.DUMMYFUNCTION("""COMPUTED_VALUE"""),-10.0) -> -10 | G61: =IFERROR(__xludf.DUMMYFUNCTION("""COMPUTED_VALUE"""),-9.0) -> -9 | H61: =IFERROR(__xludf.DUMMYFUNCTION("""COMPUTED_VALUE"""),-8.0) -> -8 | I61: =IFERROR(__xludf.DUMMYFUNCTION("""COMPUTED_VALUE"""),-7.0) -> -7 | J61: =IFERROR(__xludf.DUMMYFUNCTION("""COMPUTED_VALUE"""),-6.0) -> -6 | K61: =IFERROR(__xludf.DUMMYFUNCTION("""COMPUTED_VALUE"""),-5.0) -> -5 | L61: =IFERROR(__xludf.DUMMYFUNCTION("""COMPUTED_VALUE"""),-4.0) -> -4 | M61: =IFERROR(__xludf.DUMMYFUNCTION("""COMPUTED_VALUE"""),-3.0) -> -3 | N61: =IFERROR(__xludf.DUMMYFUNCTION("""COMPUTED_VALUE"""),-2.0) -> -2 | O61: =IFERROR(__xludf.DUMMYFUNCTION("""COMPUTED_VALUE"""),-1.0) -> -1 | P61: =IFERROR(__xludf.DUMMYFUNCTION("""COMPUTED_VALUE"""),0.0) -> 0 | Q61: =IFERROR(__xludf.DUMMYFUNCTION("""COMPUTED_VALUE"""),1.0) -> 1 | R61: =IFERROR(__xludf.DUMMYFUNCTION("""COMPUTED_VALUE"""),2.0) -> 2 | S61: =IFERROR(__xludf.DUMMYFUNCTION("""COMPUTED_VALUE"""),3.0) -> 3 | T61: =IFERROR(__xludf.DUMMYFUNCTION("""COMPUTED_VALUE"""),4.0) -> 4 | U61: =IFERROR(__xludf.DUMMYFUNCTION("""COMPUTED_VALUE"""),5.0) -> 5 | V61: =IFERROR(__xludf.DUMMYFUNCTION("""COMPUTED_VALUE"""),"-") -> - | W61: =IFERROR(__xludf.DUMMYFUNCTION("""COMPUTED_VALUE"""),"-") -> - | X61: =IFERROR(__xludf.DUMMYFUNCTION("""COMPUTED_VALUE"""),"-") -> - | Y61: =IFERROR(__xludf.DUMMYFUNCTION("""COMPUTED_VALUE"""),"-") -> -
B63: =IFERROR(__xludf.DUMMYFUNCTION("""COMPUTED_VALUE""")," オーダーポロ 長袖") -> オーダーポロ 長袖 | C63: =IFERROR(__xludf.DUMMYFUNCTION("""COMPUTED_VALUE"""),"サイズ") -> サイズ | D63: =IFERROR(__xludf.DUMMYFUNCTION("""COMPUTED_VALUE"""),"裄丈") -> 裄丈 | E63: =IFERROR(__xludf.DUMMYFUNCTION("""COMPUTED_VALUE"""),"カフスあり") -> カフスあり | F63: =IFERROR(__xludf.DUMMYFUNCTION("""COMPUTED_VALUE"""),-10.0) -> -10 | G63: =IFERROR(__xludf.DUMMYFUNCTION("""COMPUTED_VALUE"""),-9.0) -> -9 | H63: =IFERROR(__xludf.DUMMYFUNCTION("""COMPUTED_VALUE"""),-8.0) -> -8 | I63: =IFERROR(__xludf.DUMMYFUNCTION("""COMPUTED_VALUE"""),-7.0) -> -7 | J63: =IFERROR(__xludf.DUMMYFUNCTION("""COMPUTED_VALUE"""),-6.0) -> -6 | K63: =IFERROR(__xludf.DUMMYFUNCTION("""COMPUTED_VALUE"""),-5.0) -> -5 | L63: =IFERROR(__xludf.DUMMYFUNCTION("""COMPUTED_VALUE"""),-4.0) -> -4 | M63: =IFERROR(__xludf.DUMMYFUNCTION("""COMPUTED_VALUE"""),-3.0) -> -3 | N63: =IFERROR(__xludf.DUMMYFUNCTION("""COMPUTED_VALUE"""),-2.0) -> -2 | O63: =IFERROR(__xludf.DUMMYFUNCTION("""COMPUTED_VALUE"""),-1.0) -> -1 | P63: =IFERROR(__xludf.DUMMYFUNCTION("""COMPUTED_VALUE"""),0.0) -> 0 | Q63: =IFERROR(__xludf.DUMMYFUNCTION("""COMPUTED_VALUE"""),1.0) -> 1 | R63: =IFERROR(__xludf.DUMMYFUNCTION("""COMPUTED_VALUE"""),2.0) -> 2 | S63: =IFERROR(__xludf.DUMMYFUNCTION("""COMPUTED_VALUE"""),3.0) -> 3 | T63: =IFERROR(__xludf.DUMMYFUNCTION("""COMPUTED_VALUE"""),4.0) -> 4 | U63: =IFERROR(__xludf.DUMMYFUNCTION("""COMPUTED_VALUE"""),5.0) -> 5 | V63: =IFERROR(__xludf.DUMMYFUNCTION("""COMPUTED_VALUE"""),7.0) -> 7 | W63: =IFERROR(__xludf.DUMMYFUNCTION("""COMPUTED_VALUE"""),46000.0) -> 46000 | X63: =IFERROR(__xludf.DUMMYFUNCTION("""COMPUTED_VALUE"""),46003.0) -> 46003 | Y63: =IFERROR(__xludf.DUMMYFUNCTION("""COMPUTED_VALUE"""),46008.0) -> 46008
D64: =IFERROR(__xludf.DUMMYFUNCTION("""COMPUTED_VALUE"""),"裄丈") -> 裄丈 | E64: =IFERROR(__xludf.DUMMYFUNCTION("""COMPUTED_VALUE"""),"カフスなし") -> カフスなし | F64: =IFERROR(__xludf.DUMMYFUNCTION("""COMPUTED_VALUE"""),-10.0) -> -10 | G64: =IFERROR(__xludf.DUMMYFUNCTION("""COMPUTED_VALUE"""),-9.0) -> -9 | H64: =IFERROR(__xludf.DUMMYFUNCTION("""COMPUTED_VALUE"""),-8.0) -> -8 | I64: =IFERROR(__xludf.DUMMYFUNCTION("""COMPUTED_VALUE"""),-7.0) -> -7 | J64: =IFERROR(__xludf.DUMMYFUNCTION("""COMPUTED_VALUE"""),-6.0) -> -6 | K64: =IFERROR(__xludf.DUMMYFUNCTION("""COMPUTED_VALUE"""),-5.0) -> -5 | L64: =IFERROR(__xludf.DUMMYFUNCTION("""COMPUTED_VALUE"""),-4.0) -> -4 | M64: =IFERROR(__xludf.DUMMYFUNCTION("""COMPUTED_VALUE"""),-3.0) -> -3 | N64: =IFERROR(__xludf.DUMMYFUNCTION("""COMPUTED_VALUE"""),-2.0) -> -2 | O64: =IFERROR(__xludf.DUMMYFUNCTION("""COMPUTED_VALUE"""),-1.0) -> -1 | P64: =IFERROR(__xludf.DUMMYFUNCTION("""COMPUTED_VALUE"""),0.0) -> 0 | Q64: =IFERROR(__xludf.DUMMYFUNCTION("""COMPUTED_VALUE"""),1.0) -> 1 | R64: =IFERROR(__xludf.DUMMYFUNCTION("""COMPUTED_VALUE"""),2.0) -> 2 | S64: =IFERROR(__xludf.DUMMYFUNCTION("""COMPUTED_VALUE"""),3.0) -> 3 | T64: =IFERROR(__xludf.DUMMYFUNCTION("""COMPUTED_VALUE"""),4.0) -> 4 | U64: =IFERROR(__xludf.DUMMYFUNCTION("""COMPUTED_VALUE"""),5.0) -> 5 | V64: =IFERROR(__xludf.DUMMYFUNCTION("""COMPUTED_VALUE"""),7.0) -> 7 | W64: =IFERROR(__xludf.DUMMYFUNCTION("""COMPUTED_VALUE"""),46000.0) -> 46000 | X64: =IFERROR(__xludf.DUMMYFUNCTION("""COMPUTED_VALUE"""),46003.0) -> 46003 | Y64: =IFERROR(__xludf.DUMMYFUNCTION("""COMPUTED_VALUE"""),46008.0) -> 46008
D65: =IFERROR(__xludf.DUMMYFUNCTION("""COMPUTED_VALUE"""),"襟") -> 襟 | F65: =IFERROR(__xludf.DUMMYFUNCTION("""COMPUTED_VALUE"""),-10.0) -> -10 | G65: =IFERROR(__xludf.DUMMYFUNCTION("""COMPUTED_VALUE"""),-9.0) -> -9 | H65: =IFERROR(__xludf.DUMMYFUNCTION("""COMPUTED_VALUE"""),-8.0) -> -8 | I65: =IFERROR(__xludf.DUMMYFUNCTION("""COMPUTED_VALUE"""),-7.0) -> -7 | J65: =IFERROR(__xludf.DUMMYFUNCTION("""COMPUTED_VALUE"""),-6.0) -> -6 | K65: =IFERROR(__xludf.DUMMYFUNCTION("""COMPUTED_VALUE"""),-5.0) -> -5 | L65: =IFERROR(__xludf.DUMMYFUNCTION("""COMPUTED_VALUE"""),-4.0) -> -4 | M65: =IFERROR(__xludf.DUMMYFUNCTION("""COMPUTED_VALUE"""),-3.0) -> -3 | N65: =IFERROR(__xludf.DUMMYFUNCTION("""COMPUTED_VALUE"""),-2.0) -> -2 | O65: =IFERROR(__xludf.DUMMYFUNCTION("""COMPUTED_VALUE"""),-1.0) -> -1 | P65: =IFERROR(__xludf.DUMMYFUNCTION("""COMPUTED_VALUE"""),0.0) -> 0 | Q65: =IFERROR(__xludf.DUMMYFUNCTION("""COMPUTED_VALUE"""),1.0) -> 1 | R65: =IFERROR(__xludf.DUMMYFUNCTION("""COMPUTED_VALUE"""),2.0) -> 2 | S65: =IFERROR(__xludf.DUMMYFUNCTION("""COMPUTED_VALUE"""),3.0) -> 3 | T65: =IFERROR(__xludf.DUMMYFUNCTION("""COMPUTED_VALUE"""),4.0) -> 4 | U65: =IFERROR(__xludf.DUMMYFUNCTION("""COMPUTED_VALUE"""),5.0) -> 5 | V65: =IFERROR(__xludf.DUMMYFUNCTION("""COMPUTED_VALUE"""),"-") -> - | W65: =IFERROR(__xludf.DUMMYFUNCTION("""COMPUTED_VALUE"""),"-") -> - | X65: =IFERROR(__xludf.DUMMYFUNCTION("""COMPUTED_VALUE"""),"-") -> - | Y65: =IFERROR(__xludf.DUMMYFUNCTION("""COMPUTED_VALUE"""),"-") -> -
D66: =IFERROR(__xludf.DUMMYFUNCTION("""COMPUTED_VALUE"""),"カフス") -> カフス | F66: =IFERROR(__xludf.DUMMYFUNCTION("""COMPUTED_VALUE"""),-10.0) -> -10 | G66: =IFERROR(__xludf.DUMMYFUNCTION("""COMPUTED_VALUE"""),-9.0) -> -9 | H66: =IFERROR(__xludf.DUMMYFUNCTION("""COMPUTED_VALUE"""),-8.0) -> -8 | I66: =IFERROR(__xludf.DUMMYFUNCTION("""COMPUTED_VALUE"""),-7.0) -> -7 | J66: =IFERROR(__xludf.DUMMYFUNCTION("""COMPUTED_VALUE"""),-6.0) -> -6 | K66: =IFERROR(__xludf.DUMMYFUNCTION("""COMPUTED_VALUE"""),-5.0) -> -5 | L66: =IFERROR(__xludf.DUMMYFUNCTION("""COMPUTED_VALUE"""),-4.0) -> -4 | M66: =IFERROR(__xludf.DUMMYFUNCTION("""COMPUTED_VALUE"""),-3.0) -> -3 | N66: =IFERROR(__xludf.DUMMYFUNCTION("""COMPUTED_VALUE"""),-2.0) -> -2 | O66: =IFERROR(__xludf.DUMMYFUNCTION("""COMPUTED_VALUE"""),-1.0) -> -1 | P66: =IFERROR(__xludf.DUMMYFUNCTION("""COMPUTED_VALUE"""),0.0) -> 0 | Q66: =IFERROR(__xludf.DUMMYFUNCTION("""COMPUTED_VALUE"""),1.0) -> 1 | R66: =IFERROR(__xludf.DUMMYFUNCTION("""COMPUTED_VALUE"""),2.0) -> 2 | S66: =IFERROR(__xludf.DUMMYFUNCTION("""COMPUTED_VALUE"""),3.0) -> 3 | T66: =IFERROR(__xludf.DUMMYFUNCTION("""COMPUTED_VALUE"""),4.0) -> 4 | U66: =IFERROR(__xludf.DUMMYFUNCTION("""COMPUTED_VALUE"""),5.0) -> 5 | V66: =IFERROR(__xludf.DUMMYFUNCTION("""COMPUTED_VALUE"""),"-") -> - | W66: =IFERROR(__xludf.DUMMYFUNCTION("""COMPUTED_VALUE"""),"-") -> - | X66: =IFERROR(__xludf.DUMMYFUNCTION("""COMPUTED_VALUE"""),"-") -> - | Y66: =IFERROR(__xludf.DUMMYFUNCTION("""COMPUTED_VALUE"""),"-") -> -
D67: =IFERROR(__xludf.DUMMYFUNCTION("""COMPUTED_VALUE"""),"バスト") -> バスト | F67: =IFERROR(__xludf.DUMMYFUNCTION("""COMPUTED_VALUE"""),-10.0) -> -10 | G67: =IFERROR(__xludf.DUMMYFUNCTION("""COMPUTED_VALUE"""),-9.0) -> -9 | H67: =IFERROR(__xludf.DUMMYFUNCTION("""COMPUTED_VALUE"""),-8.0) -> -8 | I67: =IFERROR(__xludf.DUMMYFUNCTION("""COMPUTED_VALUE"""),-7.0) -> -7 | J67: =IFERROR(__xludf.DUMMYFUNCTION("""COMPUTED_VALUE"""),-6.0) -> -6 | K67: =IFERROR(__xludf.DUMMYFUNCTION("""COMPUTED_VALUE"""),-5.0) -> -5 | L67: =IFERROR(__xludf.DUMMYFUNCTION("""COMPUTED_VALUE"""),-4.0) -> -4 | M67: =IFERROR(__xludf.DUMMYFUNCTION("""COMPUTED_VALUE"""),-3.0) -> -3 | N67: =IFERROR(__xludf.DUMMYFUNCTION("""COMPUTED_VALUE"""),-2.0) -> -2 | O67: =IFERROR(__xludf.DUMMYFUNCTION("""COMPUTED_VALUE"""),-1.0) -> -1 | P67: =IFERROR(__xludf.DUMMYFUNCTION("""COMPUTED_VALUE"""),0.0) -> 0 | Q67: =IFERROR(__xludf.DUMMYFUNCTION("""COMPUTED_VALUE"""),1.0) -> 1 | R67: =IFERROR(__xludf.DUMMYFUNCTION("""COMPUTED_VALUE"""),2.0) -> 2 | S67: =IFERROR(__xludf.DUMMYFUNCTION("""COMPUTED_VALUE"""),3.0) -> 3 | T67: =IFERROR(__xludf.DUMMYFUNCTION("""COMPUTED_VALUE"""),4.0) -> 4 | U67: =IFERROR(__xludf.DUMMYFUNCTION("""COMPUTED_VALUE"""),5.0) -> 5 | V67: =IFERROR(__xludf.DUMMYFUNCTION("""COMPUTED_VALUE"""),7.0) -> 7 | W67: =IFERROR(__xludf.DUMMYFUNCTION("""COMPUTED_VALUE"""),46000.0) -> 46000 | X67: =IFERROR(__xludf.DUMMYFUNCTION("""COMPUTED_VALUE"""),46003.0) -> 46003 | Y67: =IFERROR(__xludf.DUMMYFUNCTION("""COMPUTED_VALUE"""),46008.0) -> 46008
D68: =IFERROR(__xludf.DUMMYFUNCTION("""COMPUTED_VALUE"""),"アームホール") -> アームホール | E68: =IFERROR(__xludf.DUMMYFUNCTION("""COMPUTED_VALUE"""),"※バストと連動。 数値指定は再製作") -> ※バストと連動。 数値指定は再製作 | F68: =IFERROR(__xludf.DUMMYFUNCTION("""COMPUTED_VALUE"""),-10.0) -> -10 | G68: =IFERROR(__xludf.DUMMYFUNCTION("""COMPUTED_VALUE"""),-9.0) -> -9 | H68: =IFERROR(__xludf.DUMMYFUNCTION("""COMPUTED_VALUE"""),-8.0) -> -8 | I68: =IFERROR(__xludf.DUMMYFUNCTION("""COMPUTED_VALUE"""),-7.0) -> -7 | J68: =IFERROR(__xludf.DUMMYFUNCTION("""COMPUTED_VALUE"""),-6.0) -> -6 | K68: =IFERROR(__xludf.DUMMYFUNCTION("""COMPUTED_VALUE"""),-5.0) -> -5 | L68: =IFERROR(__xludf.DUMMYFUNCTION("""COMPUTED_VALUE"""),-4.0) -> -4 | M68: =IFERROR(__xludf.DUMMYFUNCTION("""COMPUTED_VALUE"""),-3.0) -> -3 | N68: =IFERROR(__xludf.DUMMYFUNCTION("""COMPUTED_VALUE"""),-2.0) -> -2 | O68: =IFERROR(__xludf.DUMMYFUNCTION("""COMPUTED_VALUE"""),-1.0) -> -1 | P68: =IFERROR(__xludf.DUMMYFUNCTION("""COMPUTED_VALUE"""),0.0) -> 0 | Q68: =IFERROR(__xludf.DUMMYFUNCTION("""COMPUTED_VALUE"""),1.0) -> 1 | R68: =IFERROR(__xludf.DUMMYFUNCTION("""COMPUTED_VALUE"""),2.0) -> 2 | S68: =IFERROR(__xludf.DUMMYFUNCTION("""COMPUTED_VALUE"""),3.0) -> 3 | T68: =IFERROR(__xludf.DUMMYFUNCTION("""COMPUTED_VALUE"""),4.0) -> 4 | U68: =IFERROR(__xludf.DUMMYFUNCTION("""COMPUTED_VALUE"""),5.0) -> 5 | V68: =IFERROR(__xludf.DUMMYFUNCTION("""COMPUTED_VALUE"""),7.0) -> 7 | W68: =IFERROR(__xludf.DUMMYFUNCTION("""COMPUTED_VALUE"""),46000.0) -> 46000 | X68: =IFERROR(__xludf.DUMMYFUNCTION("""COMPUTED_VALUE"""),46003.0) -> 46003 | Y68: =IFERROR(__xludf.DUMMYFUNCTION("""COMPUTED_VALUE"""),46008.0) -> 46008
D69: =IFERROR(__xludf.DUMMYFUNCTION("""COMPUTED_VALUE"""),"ウエスト") -> ウエスト | F69: =IFERROR(__xludf.DUMMYFUNCTION("""COMPUTED_VALUE"""),-10.0) -> -10 | G69: =IFERROR(__xludf.DUMMYFUNCTION("""COMPUTED_VALUE"""),-9.0) -> -9 | H69: =IFERROR(__xludf.DUMMYFUNCTION("""COMPUTED_VALUE"""),-8.0) -> -8 | I69: =IFERROR(__xludf.DUMMYFUNCTION("""COMPUTED_VALUE"""),-7.0) -> -7 | J69: =IFERROR(__xludf.DUMMYFUNCTION("""COMPUTED_VALUE"""),-6.0) -> -6 | K69: =IFERROR(__xludf.DUMMYFUNCTION("""COMPUTED_VALUE"""),-5.0) -> -5 | L69: =IFERROR(__xludf.DUMMYFUNCTION("""COMPUTED_VALUE"""),-4.0) -> -4 | M69: =IFERROR(__xludf.DUMMYFUNCTION("""COMPUTED_VALUE"""),-3.0) -> -3 | N69: =IFERROR(__xludf.DUMMYFUNCTION("""COMPUTED_VALUE"""),-2.0) -> -2 | O69: =IFERROR(__xludf.DUMMYFUNCTION("""COMPUTED_VALUE"""),-1.0) -> -1 | P69: =IFERROR(__xludf.DUMMYFUNCTION("""COMPUTED_VALUE"""),0.0) -> 0 | Q69: =IFERROR(__xludf.DUMMYFUNCTION("""COMPUTED_VALUE"""),1.0) -> 1 | R69: =IFERROR(__xludf.DUMMYFUNCTION("""COMPUTED_VALUE"""),2.0) -> 2 | S69: =IFERROR(__xludf.DUMMYFUNCTION("""COMPUTED_VALUE"""),3.0) -> 3 | T69: =IFERROR(__xludf.DUMMYFUNCTION("""COMPUTED_VALUE"""),4.0) -> 4 | U69: =IFERROR(__xludf.DUMMYFUNCTION("""COMPUTED_VALUE"""),5.0) -> 5 | V69: =IFERROR(__xludf.DUMMYFUNCTION("""COMPUTED_VALUE"""),7.0) -> 7 | W69: =IFERROR(__xludf.DUMMYFUNCTION("""COMPUTED_VALUE"""),46000.0) -> 46000 | X69: =IFERROR(__xludf.DUMMYFUNCTION("""COMPUTED_VALUE"""),46003.0) -> 46003 | Y69: =IFERROR(__xludf.DUMMYFUNCTION("""COMPUTED_VALUE"""),46008.0) -> 46008
D70: =IFERROR(__xludf.DUMMYFUNCTION("""COMPUTED_VALUE"""),"着丈") -> 着丈 | E70: =IFERROR(__xludf.DUMMYFUNCTION("""COMPUTED_VALUE"""),"※スリット移動の為、かんぬきの後が残る ステッチ幅(2.5cm)以下の詰めの場合、素材により修理跡が残ります。") -> ※スリット移動の為、かんぬきの後が残る ステッチ幅(2.5cm)以下の詰めの場合、素材により修理跡が残ります。 | F70: =IFERROR(__xludf.DUMMYFUNCTION("""COMPUTED_VALUE"""),-10.0) -> -10 | G70: =IFERROR(__xludf.DUMMYFUNCTION("""COMPUTED_VALUE"""),-9.0) -> -9 | H70: =IFERROR(__xludf.DUMMYFUNCTION("""COMPUTED_VALUE"""),-8.0) -> -8 | I70: =IFERROR(__xludf.DUMMYFUNCTION("""COMPUTED_VALUE"""),-7.0) -> -7 | J70: =IFERROR(__xludf.DUMMYFUNCTION("""COMPUTED_VALUE"""),-6.0) -> -6 | K70: =IFERROR(__xludf.DUMMYFUNCTION("""COMPUTED_VALUE"""),-5.0) -> -5 | L70: =IFERROR(__xludf.DUMMYFUNCTION("""COMPUTED_VALUE"""),-4.0) -> -4 | M70: =IFERROR(__xludf.DUMMYFUNCTION("""COMPUTED_VALUE"""),-3.0) -> -3 | N70: =IFERROR(__xludf.DUMMYFUNCTION("""COMPUTED_VALUE"""),-2.0) -> -2 | O70: =IFERROR(__xludf.DUMMYFUNCTION("""COMPUTED_VALUE"""),-1.0) -> -1 | P70: =IFERROR(__xludf.DUMMYFUNCTION("""COMPUTED_VALUE"""),0.0) -> 0 | Q70: =IFERROR(__xludf.DUMMYFUNCTION("""COMPUTED_VALUE"""),1.0) -> 1 | R70: =IFERROR(__xludf.DUMMYFUNCTION("""COMPUTED_VALUE"""),2.0) -> 2 | S70: =IFERROR(__xludf.DUMMYFUNCTION("""COMPUTED_VALUE"""),3.0) -> 3 | T70: =IFERROR(__xludf.DUMMYFUNCTION("""COMPUTED_VALUE"""),4.0) -> 4 | U70: =IFERROR(__xludf.DUMMYFUNCTION("""COMPUTED_VALUE"""),5.0) -> 5 | V70: =IFERROR(__xludf.DUMMYFUNCTION("""COMPUTED_VALUE"""),7.0) -> 7 | W70: =IFERROR(__xludf.DUMMYFUNCTION("""COMPUTED_VALUE"""),46000.0) -> 46000 | X70: =IFERROR(__xludf.DUMMYFUNCTION("""COMPUTED_VALUE"""),46003.0) -> 46003 | Y70: =IFERROR(__xludf.DUMMYFUNCTION("""COMPUTED_VALUE"""),46008.0) -> 46008
D71: =IFERROR(__xludf.DUMMYFUNCTION("""COMPUTED_VALUE"""),"肩巾") -> 肩巾 | F71: =IFERROR(__xludf.DUMMYFUNCTION("""COMPUTED_VALUE"""),-10.0) -> -10 | G71: =IFERROR(__xludf.DUMMYFUNCTION("""COMPUTED_VALUE"""),-9.0) -> -9 | H71: =IFERROR(__xludf.DUMMYFUNCTION("""COMPUTED_VALUE"""),-8.0) -> -8 | I71: =IFERROR(__xludf.DUMMYFUNCTION("""COMPUTED_VALUE"""),-7.0) -> -7 | J71: =IFERROR(__xludf.DUMMYFUNCTION("""COMPUTED_VALUE"""),-6.0) -> -6 | K71: =IFERROR(__xludf.DUMMYFUNCTION("""COMPUTED_VALUE"""),-5.0) -> -5 | L71: =IFERROR(__xludf.DUMMYFUNCTION("""COMPUTED_VALUE"""),-4.0) -> -4 | M71: =IFERROR(__xludf.DUMMYFUNCTION("""COMPUTED_VALUE"""),-3.0) -> -3 | N71: =IFERROR(__xludf.DUMMYFUNCTION("""COMPUTED_VALUE"""),-2.0) -> -2 | O71: =IFERROR(__xludf.DUMMYFUNCTION("""COMPUTED_VALUE"""),-1.0) -> -1 | P71: =IFERROR(__xludf.DUMMYFUNCTION("""COMPUTED_VALUE"""),0.0) -> 0 | Q71: =IFERROR(__xludf.DUMMYFUNCTION("""COMPUTED_VALUE"""),1.0) -> 1 | R71: =IFERROR(__xludf.DUMMYFUNCTION("""COMPUTED_VALUE"""),2.0) -> 2 | S71: =IFERROR(__xludf.DUMMYFUNCTION("""COMPUTED_VALUE"""),3.0) -> 3 | T71: =IFERROR(__xludf.DUMMYFUNCTION("""COMPUTED_VALUE"""),4.0) -> 4 | U71: =IFERROR(__xludf.DUMMYFUNCTION("""COMPUTED_VALUE"""),5.0) -> 5 | V71: =IFERROR(__xludf.DUMMYFUNCTION("""COMPUTED_VALUE"""),"-") -> - | W71: =IFERROR(__xludf.DUMMYFUNCTION("""COMPUTED_VALUE"""),"-") -> - | X71: =IFERROR(__xludf.DUMMYFUNCTION("""COMPUTED_VALUE"""),"-") -> - | Y71: =IFERROR(__xludf.DUMMYFUNCTION("""COMPUTED_VALUE"""),"-") -> -
D72: =IFERROR(__xludf.DUMMYFUNCTION("""COMPUTED_VALUE"""),"ヒップ") -> ヒップ | F72: =IFERROR(__xludf.DUMMYFUNCTION("""COMPUTED_VALUE"""),-10.0) -> -10 | G72: =IFERROR(__xludf.DUMMYFUNCTION("""COMPUTED_VALUE"""),-9.0) -> -9 | H72: =IFERROR(__xludf.DUMMYFUNCTION("""COMPUTED_VALUE"""),-8.0) -> -8 | I72: =IFERROR(__xludf.DUMMYFUNCTION("""COMPUTED_VALUE"""),-7.0) -> -7 | J72: =IFERROR(__xludf.DUMMYFUNCTION("""COMPUTED_VALUE"""),-6.0) -> -6 | K72: =IFERROR(__xludf.DUMMYFUNCTION("""COMPUTED_VALUE"""),-5.0) -> -5 | L72: =IFERROR(__xludf.DUMMYFUNCTION("""COMPUTED_VALUE"""),-4.0) -> -4 | M72: =IFERROR(__xludf.DUMMYFUNCTION("""COMPUTED_VALUE"""),-3.0) -> -3 | N72: =IFERROR(__xludf.DUMMYFUNCTION("""COMPUTED_VALUE"""),-2.0) -> -2 | O72: =IFERROR(__xludf.DUMMYFUNCTION("""COMPUTED_VALUE"""),-1.0) -> -1 | P72: =IFERROR(__xludf.DUMMYFUNCTION("""COMPUTED_VALUE"""),0.0) -> 0 | Q72: =IFERROR(__xludf.DUMMYFUNCTION("""COMPUTED_VALUE"""),1.0) -> 1 | R72: =IFERROR(__xludf.DUMMYFUNCTION("""COMPUTED_VALUE"""),2.0) -> 2 | S72: =IFERROR(__xludf.DUMMYFUNCTION("""COMPUTED_VALUE"""),3.0) -> 3 | T72: =IFERROR(__xludf.DUMMYFUNCTION("""COMPUTED_VALUE"""),4.0) -> 4 | U72: =IFERROR(__xludf.DUMMYFUNCTION("""COMPUTED_VALUE"""),5.0) -> 5 | V72: =IFERROR(__xludf.DUMMYFUNCTION("""COMPUTED_VALUE"""),"-") -> - | W72: =IFERROR(__xludf.DUMMYFUNCTION("""COMPUTED_VALUE"""),"-") -> - | X72: =IFERROR(__xludf.DUMMYFUNCTION("""COMPUTED_VALUE"""),"-") -> - | Y72: =IFERROR(__xludf.DUMMYFUNCTION("""COMPUTED_VALUE"""),"-") -> -
B74: =IFERROR(__xludf.DUMMYFUNCTION("""COMPUTED_VALUE""")," チェスター") -> チェスター | C74: =IFERROR(__xludf.DUMMYFUNCTION("""COMPUTED_VALUE"""),"サイズ") -> サイズ | D74: =IFERROR(__xludf.DUMMYFUNCTION("""COMPUTED_VALUE"""),"肩巾") -> 肩巾 | E74: =IFERROR(__xludf.DUMMYFUNCTION("""COMPUTED_VALUE"""),"パターン限界値 -4cm~+6cm") -> パターン限界値 -4cm~+6cm | F74: =IFERROR(__xludf.DUMMYFUNCTION("""COMPUTED_VALUE"""),-10.0) -> -10 | G74: =IFERROR(__xludf.DUMMYFUNCTION("""COMPUTED_VALUE"""),-9.0) -> -9 | H74: =IFERROR(__xludf.DUMMYFUNCTION("""COMPUTED_VALUE"""),-8.0) -> -8 | I74: =IFERROR(__xludf.DUMMYFUNCTION("""COMPUTED_VALUE"""),-7.0) -> -7 | J74: =IFERROR(__xludf.DUMMYFUNCTION("""COMPUTED_VALUE"""),-6.0) -> -6 | K74: =IFERROR(__xludf.DUMMYFUNCTION("""COMPUTED_VALUE"""),-5.0) -> -5 | L74: =IFERROR(__xludf.DUMMYFUNCTION("""COMPUTED_VALUE"""),-4.0) -> -4 | M74: =IFERROR(__xludf.DUMMYFUNCTION("""COMPUTED_VALUE"""),-3.0) -> -3 | N74: =IFERROR(__xludf.DUMMYFUNCTION("""COMPUTED_VALUE"""),-2.0) -> -2 | O74: =IFERROR(__xludf.DUMMYFUNCTION("""COMPUTED_VALUE"""),-1.0) -> -1 | P74: =IFERROR(__xludf.DUMMYFUNCTION("""COMPUTED_VALUE"""),0.0) -> 0 | Q74: =IFERROR(__xludf.DUMMYFUNCTION("""COMPUTED_VALUE"""),1.0) -> 1 | R74: =IFERROR(__xludf.DUMMYFUNCTION("""COMPUTED_VALUE"""),2.0) -> 2 | S74: =IFERROR(__xludf.DUMMYFUNCTION("""COMPUTED_VALUE"""),3.0) -> 3 | T74: =IFERROR(__xludf.DUMMYFUNCTION("""COMPUTED_VALUE"""),4.0) -> 4 | U74: =IFERROR(__xludf.DUMMYFUNCTION("""COMPUTED_VALUE"""),5.0) -> 5 | V74: =IFERROR(__xludf.DUMMYFUNCTION("""COMPUTED_VALUE"""),7.0) -> 7 | W74: =IFERROR(__xludf.DUMMYFUNCTION("""COMPUTED_VALUE"""),46000.0) -> 46000 | X74: =IFERROR(__xludf.DUMMYFUNCTION("""COMPUTED_VALUE"""),46003.0) -> 46003 | Y74: =IFERROR(__xludf.DUMMYFUNCTION("""COMPUTED_VALUE"""),46008.0) -> 46008
D75: =IFERROR(__xludf.DUMMYFUNCTION("""COMPUTED_VALUE"""),"バスト") -> バスト | F75: =IFERROR(__xludf.DUMMYFUNCTION("""COMPUTED_VALUE"""),-10.0) -> -10 | G75: =IFERROR(__xludf.DUMMYFUNCTION("""COMPUTED_VALUE"""),-9.0) -> -9 | H75: =IFERROR(__xludf.DUMMYFUNCTION("""COMPUTED_VALUE"""),-8.0) -> -8 | I75: =IFERROR(__xludf.DUMMYFUNCTION("""COMPUTED_VALUE"""),-7.0) -> -7 | J75: =IFERROR(__xludf.DUMMYFUNCTION("""COMPUTED_VALUE"""),-6.0) -> -6 | K75: =IFERROR(__xludf.DUMMYFUNCTION("""COMPUTED_VALUE"""),-5.0) -> -5 | L75: =IFERROR(__xludf.DUMMYFUNCTION("""COMPUTED_VALUE"""),-4.0) -> -4 | M75: =IFERROR(__xludf.DUMMYFUNCTION("""COMPUTED_VALUE"""),-3.0) -> -3 | N75: =IFERROR(__xludf.DUMMYFUNCTION("""COMPUTED_VALUE"""),-2.0) -> -2 | O75: =IFERROR(__xludf.DUMMYFUNCTION("""COMPUTED_VALUE"""),-1.0) -> -1 | P75: =IFERROR(__xludf.DUMMYFUNCTION("""COMPUTED_VALUE"""),0.0) -> 0 | Q75: =IFERROR(__xludf.DUMMYFUNCTION("""COMPUTED_VALUE"""),1.0) -> 1 | R75: =IFERROR(__xludf.DUMMYFUNCTION("""COMPUTED_VALUE"""),2.0) -> 2 | S75: =IFERROR(__xludf.DUMMYFUNCTION("""COMPUTED_VALUE"""),3.0) -> 3 | T75: =IFERROR(__xludf.DUMMYFUNCTION("""COMPUTED_VALUE"""),4.0) -> 4 | U75: =IFERROR(__xludf.DUMMYFUNCTION("""COMPUTED_VALUE"""),5.0) -> 5 | V75: =IFERROR(__xludf.DUMMYFUNCTION("""COMPUTED_VALUE"""),"-") -> - | W75: =IFERROR(__xludf.DUMMYFUNCTION("""COMPUTED_VALUE"""),"-") -> - | X75: =IFERROR(__xludf.DUMMYFUNCTION("""COMPUTED_VALUE"""),46003.0) -> 46003 | Y75: =IFERROR(__xludf.DUMMYFUNCTION("""COMPUTED_VALUE"""),46008.0) -> 46008
D76: =IFERROR(__xludf.DUMMYFUNCTION("""COMPUTED_VALUE"""),"ウエスト") -> ウエスト | E76: =IFERROR(__xludf.DUMMYFUNCTION("""COMPUTED_VALUE"""),"パターン限界値-4cm~+6cm かつドロップ16cm ") -> パターン限界値-4cm~+6cm かつドロップ16cm | F76: =IFERROR(__xludf.DUMMYFUNCTION("""COMPUTED_VALUE"""),-10.0) -> -10 | G76: =IFERROR(__xludf.DUMMYFUNCTION("""COMPUTED_VALUE"""),-9.0) -> -9 | H76: =IFERROR(__xludf.DUMMYFUNCTION("""COMPUTED_VALUE"""),-8.0) -> -8 | I76: =IFERROR(__xludf.DUMMYFUNCTION("""COMPUTED_VALUE"""),-7.0) -> -7 | J76: =IFERROR(__xludf.DUMMYFUNCTION("""COMPUTED_VALUE"""),-6.0) -> -6 | K76: =IFERROR(__xludf.DUMMYFUNCTION("""COMPUTED_VALUE"""),-5.0) -> -5 | L76: =IFERROR(__xludf.DUMMYFUNCTION("""COMPUTED_VALUE"""),-4.0) -> -4 | M76: =IFERROR(__xludf.DUMMYFUNCTION("""COMPUTED_VALUE"""),-3.0) -> -3 | N76: =IFERROR(__xludf.DUMMYFUNCTION("""COMPUTED_VALUE"""),-2.0) -> -2 | O76: =IFERROR(__xludf.DUMMYFUNCTION("""COMPUTED_VALUE"""),-1.0) -> -1 | P76: =IFERROR(__xludf.DUMMYFUNCTION("""COMPUTED_VALUE"""),0.0) -> 0 | Q76: =IFERROR(__xludf.DUMMYFUNCTION("""COMPUTED_VALUE"""),1.0) -> 1 | R76: =IFERROR(__xludf.DUMMYFUNCTION("""COMPUTED_VALUE"""),2.0) -> 2 | S76: =IFERROR(__xludf.DUMMYFUNCTION("""COMPUTED_VALUE"""),3.0) -> 3 | T76: =IFERROR(__xludf.DUMMYFUNCTION("""COMPUTED_VALUE"""),4.0) -> 4 | U76: =IFERROR(__xludf.DUMMYFUNCTION("""COMPUTED_VALUE"""),5.0) -> 5 | V76: =IFERROR(__xludf.DUMMYFUNCTION("""COMPUTED_VALUE"""),7.0) -> 7 | W76: =IFERROR(__xludf.DUMMYFUNCTION("""COMPUTED_VALUE"""),46000.0) -> 46000 | X76: =IFERROR(__xludf.DUMMYFUNCTION("""COMPUTED_VALUE"""),46003.0) -> 46003 | Y76: =IFERROR(__xludf.DUMMYFUNCTION("""COMPUTED_VALUE"""),46008.0) -> 46008
D77: =IFERROR(__xludf.DUMMYFUNCTION("""COMPUTED_VALUE"""),"袖丈") -> 袖丈 | F77: =IFERROR(__xludf.DUMMYFUNCTION("""COMPUTED_VALUE"""),-10.0) -> -10 | G77: =IFERROR(__xludf.DUMMYFUNCTION("""COMPUTED_VALUE"""),-9.0) -> -9 | H77: =IFERROR(__xludf.DUMMYFUNCTION("""COMPUTED_VALUE"""),-8.0) -> -8 | I77: =IFERROR(__xludf.DUMMYFUNCTION("""COMPUTED_VALUE"""),-7.0) -> -7 | J77: =IFERROR(__xludf.DUMMYFUNCTION("""COMPUTED_VALUE"""),-6.0) -> -6 | K77: =IFERROR(__xludf.DUMMYFUNCTION("""COMPUTED_VALUE"""),-5.0) -> -5 | L77: =IFERROR(__xludf.DUMMYFUNCTION("""COMPUTED_VALUE"""),-4.0) -> -4 | M77: =IFERROR(__xludf.DUMMYFUNCTION("""COMPUTED_VALUE"""),-3.0) -> -3 | N77: =IFERROR(__xludf.DUMMYFUNCTION("""COMPUTED_VALUE"""),-1.5) -> -1.5 | O77: =IFERROR(__xludf.DUMMYFUNCTION("""COMPUTED_VALUE"""),-1.0) -> -1 | P77: =IFERROR(__xludf.DUMMYFUNCTION("""COMPUTED_VALUE"""),0.0) -> 0 | Q77: =IFERROR(__xludf.DUMMYFUNCTION("""COMPUTED_VALUE"""),1.0) -> 1 | R77: =IFERROR(__xludf.DUMMYFUNCTION("""COMPUTED_VALUE"""),2.0) -> 2 | S77: =IFERROR(__xludf.DUMMYFUNCTION("""COMPUTED_VALUE"""),3.0) -> 3 | T77: =IFERROR(__xludf.DUMMYFUNCTION("""COMPUTED_VALUE"""),4.0) -> 4 | U77: =IFERROR(__xludf.DUMMYFUNCTION("""COMPUTED_VALUE"""),5.0) -> 5 | V77: =IFERROR(__xludf.DUMMYFUNCTION("""COMPUTED_VALUE"""),7.0) -> 7 | W77: =IFERROR(__xludf.DUMMYFUNCTION("""COMPUTED_VALUE"""),46000.0) -> 46000 | X77: =IFERROR(__xludf.DUMMYFUNCTION("""COMPUTED_VALUE"""),46003.0) -> 46003 | Y77: =IFERROR(__xludf.DUMMYFUNCTION("""COMPUTED_VALUE"""),46008.0) -> 46008
D78: =IFERROR(__xludf.DUMMYFUNCTION("""COMPUTED_VALUE"""),"着丈") -> 着丈 | E78: =IFERROR(__xludf.DUMMYFUNCTION("""COMPUTED_VALUE"""),"パターン限界値±20cm") -> パターン限界値±20cm | F78: =IFERROR(__xludf.DUMMYFUNCTION("""COMPUTED_VALUE"""),-10.0) -> -10 | G78: =IFERROR(__xludf.DUMMYFUNCTION("""COMPUTED_VALUE"""),-9.0) -> -9 | H78: =IFERROR(__xludf.DUMMYFUNCTION("""COMPUTED_VALUE"""),-8.0) -> -8 | I78: =IFERROR(__xludf.DUMMYFUNCTION("""COMPUTED_VALUE"""),-7.0) -> -7 | J78: =IFERROR(__xludf.DUMMYFUNCTION("""COMPUTED_VALUE"""),-6.0) -> -6 | K78: =IFERROR(__xludf.DUMMYFUNCTION("""COMPUTED_VALUE"""),-5.0) -> -5 | L78: =IFERROR(__xludf.DUMMYFUNCTION("""COMPUTED_VALUE"""),-4.0) -> -4 | M78: =IFERROR(__xludf.DUMMYFUNCTION("""COMPUTED_VALUE"""),-3.0) -> -3 | N78: =IFERROR(__xludf.DUMMYFUNCTION("""COMPUTED_VALUE"""),-2.0) -> -2 | O78: =IFERROR(__xludf.DUMMYFUNCTION("""COMPUTED_VALUE"""),-1.0) -> -1 | P78: =IFERROR(__xludf.DUMMYFUNCTION("""COMPUTED_VALUE"""),0.0) -> 0 | Q78: =IFERROR(__xludf.DUMMYFUNCTION("""COMPUTED_VALUE"""),1.0) -> 1 | R78: =IFERROR(__xludf.DUMMYFUNCTION("""COMPUTED_VALUE"""),2.0) -> 2 | S78: =IFERROR(__xludf.DUMMYFUNCTION("""COMPUTED_VALUE"""),3.0) -> 3 | T78: =IFERROR(__xludf.DUMMYFUNCTION("""COMPUTED_VALUE"""),4.0) -> 4 | U78: =IFERROR(__xludf.DUMMYFUNCTION("""COMPUTED_VALUE"""),5.0) -> 5 | V78: =IFERROR(__xludf.DUMMYFUNCTION("""COMPUTED_VALUE"""),7.0) -> 7 | W78: =IFERROR(__xludf.DUMMYFUNCTION("""COMPUTED_VALUE"""),46000.0) -> 46000 | X78: =IFERROR(__xludf.DUMMYFUNCTION("""COMPUTED_VALUE"""),46003.0) -> 46003 | Y78: =IFERROR(__xludf.DUMMYFUNCTION("""COMPUTED_VALUE"""),46008.0) -> 46008
D79: =IFERROR(__xludf.DUMMYFUNCTION("""COMPUTED_VALUE"""),"けまわし") -> けまわし | E79: =IFERROR(__xludf.DUMMYFUNCTION("""COMPUTED_VALUE"""),"パターン限界値±8cm") -> パターン限界値±8cm | F79: =IFERROR(__xludf.DUMMYFUNCTION("""COMPUTED_VALUE"""),-10.0) -> -10 | G79: =IFERROR(__xludf.DUMMYFUNCTION("""COMPUTED_VALUE"""),-9.0) -> -9 | H79: =IFERROR(__xludf.DUMMYFUNCTION("""COMPUTED_VALUE"""),-8.0) -> -8 | I79: =IFERROR(__xludf.DUMMYFUNCTION("""COMPUTED_VALUE"""),-7.0) -> -7 | J79: =IFERROR(__xludf.DUMMYFUNCTION("""COMPUTED_VALUE"""),-6.0) -> -6 | K79: =IFERROR(__xludf.DUMMYFUNCTION("""COMPUTED_VALUE"""),-5.0) -> -5 | L79: =IFERROR(__xludf.DUMMYFUNCTION("""COMPUTED_VALUE"""),-4.0) -> -4 | M79: =IFERROR(__xludf.DUMMYFUNCTION("""COMPUTED_VALUE"""),-3.0) -> -3 | N79: =IFERROR(__xludf.DUMMYFUNCTION("""COMPUTED_VALUE"""),-2.0) -> -2 | O79: =IFERROR(__xludf.DUMMYFUNCTION("""COMPUTED_VALUE"""),-1.0) -> -1 | P79: =IFERROR(__xludf.DUMMYFUNCTION("""COMPUTED_VALUE"""),0.0) -> 0 | Q79: =IFERROR(__xludf.DUMMYFUNCTION("""COMPUTED_VALUE"""),1.0) -> 1 | R79: =IFERROR(__xludf.DUMMYFUNCTION("""COMPUTED_VALUE"""),2.0) -> 2 | S79: =IFERROR(__xludf.DUMMYFUNCTION("""COMPUTED_VALUE"""),3.0) -> 3 | T79: =IFERROR(__xludf.DUMMYFUNCTION("""COMPUTED_VALUE"""),4.0) -> 4 | U79: =IFERROR(__xludf.DUMMYFUNCTION("""COMPUTED_VALUE"""),5.0) -> 5 | V79: =IFERROR(__xludf.DUMMYFUNCTION("""COMPUTED_VALUE"""),10.0) -> 10 | W79: =IFERROR(__xludf.DUMMYFUNCTION("""COMPUTED_VALUE"""),46003.0) -> 46003 | X79: =IFERROR(__xludf.DUMMYFUNCTION("""COMPUTED_VALUE"""),46003.0) -> 46003 | Y79: =IFERROR(__xludf.DUMMYFUNCTION("""COMPUTED_VALUE"""),46008.0) -> 46008
B81: =IFERROR(__xludf.DUMMYFUNCTION("""COMPUTED_VALUE"""),"トレンチ") -> トレンチ | C81: =IFERROR(__xludf.DUMMYFUNCTION("""COMPUTED_VALUE"""),"サイズ") -> サイズ | D81: =IFERROR(__xludf.DUMMYFUNCTION("""COMPUTED_VALUE"""),"肩巾") -> 肩巾 | E81: =IFERROR(__xludf.DUMMYFUNCTION("""COMPUTED_VALUE"""),"パターン限界値 -4cm~+6cm") -> パターン限界値 -4cm~+6cm | F81: =IFERROR(__xludf.DUMMYFUNCTION("""COMPUTED_VALUE"""),-10.0) -> -10 | G81: =IFERROR(__xludf.DUMMYFUNCTION("""COMPUTED_VALUE"""),-9.0) -> -9 | H81: =IFERROR(__xludf.DUMMYFUNCTION("""COMPUTED_VALUE"""),-8.0) -> -8 | I81: =IFERROR(__xludf.DUMMYFUNCTION("""COMPUTED_VALUE"""),-7.0) -> -7 | J81: =IFERROR(__xludf.DUMMYFUNCTION("""COMPUTED_VALUE"""),-6.0) -> -6 | K81: =IFERROR(__xludf.DUMMYFUNCTION("""COMPUTED_VALUE"""),-5.0) -> -5 | L81: =IFERROR(__xludf.DUMMYFUNCTION("""COMPUTED_VALUE"""),-4.0) -> -4 | M81: =IFERROR(__xludf.DUMMYFUNCTION("""COMPUTED_VALUE"""),-3.0) -> -3 | N81: =IFERROR(__xludf.DUMMYFUNCTION("""COMPUTED_VALUE"""),-2.0) -> -2 | O81: =IFERROR(__xludf.DUMMYFUNCTION("""COMPUTED_VALUE"""),-1.0) -> -1 | P81: =IFERROR(__xludf.DUMMYFUNCTION("""COMPUTED_VALUE"""),0.0) -> 0 | Q81: =IFERROR(__xludf.DUMMYFUNCTION("""COMPUTED_VALUE"""),1.0) -> 1 | R81: =IFERROR(__xludf.DUMMYFUNCTION("""COMPUTED_VALUE"""),2.0) -> 2 | S81: =IFERROR(__xludf.DUMMYFUNCTION("""COMPUTED_VALUE"""),3.0) -> 3 | T81: =IFERROR(__xludf.DUMMYFUNCTION("""COMPUTED_VALUE"""),4.0) -> 4 | U81: =IFERROR(__xludf.DUMMYFUNCTION("""COMPUTED_VALUE"""),5.0) -> 5 | V81: =IFERROR(__xludf.DUMMYFUNCTION("""COMPUTED_VALUE"""),"-") -> - | W81: =IFERROR(__xludf.DUMMYFUNCTION("""COMPUTED_VALUE"""),"-") -> - | X81: =IFERROR(__xludf.DUMMYFUNCTION("""COMPUTED_VALUE"""),46003.0) -> 46003 | Y81: =IFERROR(__xludf.DUMMYFUNCTION("""COMPUTED_VALUE"""),46008.0) -> 46008
D82: =IFERROR(__xludf.DUMMYFUNCTION("""COMPUTED_VALUE"""),"バスト") -> バスト | F82: =IFERROR(__xludf.DUMMYFUNCTION("""COMPUTED_VALUE"""),-10.0) -> -10 | G82: =IFERROR(__xludf.DUMMYFUNCTION("""COMPUTED_VALUE"""),-9.0) -> -9 | H82: =IFERROR(__xludf.DUMMYFUNCTION("""COMPUTED_VALUE"""),-8.0) -> -8 | I82: =IFERROR(__xludf.DUMMYFUNCTION("""COMPUTED_VALUE"""),-7.0) -> -7 | J82: =IFERROR(__xludf.DUMMYFUNCTION("""COMPUTED_VALUE"""),-6.0) -> -6 | K82: =IFERROR(__xludf.DUMMYFUNCTION("""COMPUTED_VALUE"""),-5.0) -> -5 | L82: =IFERROR(__xludf.DUMMYFUNCTION("""COMPUTED_VALUE"""),-4.0) -> -4 | M82: =IFERROR(__xludf.DUMMYFUNCTION("""COMPUTED_VALUE"""),-3.0) -> -3 | N82: =IFERROR(__xludf.DUMMYFUNCTION("""COMPUTED_VALUE"""),-2.0) -> -2 | O82: =IFERROR(__xludf.DUMMYFUNCTION("""COMPUTED_VALUE"""),-1.0) -> -1 | P82: =IFERROR(__xludf.DUMMYFUNCTION("""COMPUTED_VALUE"""),0.0) -> 0 | Q82: =IFERROR(__xludf.DUMMYFUNCTION("""COMPUTED_VALUE"""),1.0) -> 1 | R82: =IFERROR(__xludf.DUMMYFUNCTION("""COMPUTED_VALUE"""),2.0) -> 2 | S82: =IFERROR(__xludf.DUMMYFUNCTION("""COMPUTED_VALUE"""),3.0) -> 3 | T82: =IFERROR(__xludf.DUMMYFUNCTION("""COMPUTED_VALUE"""),4.0) -> 4 | U82: =IFERROR(__xludf.DUMMYFUNCTION("""COMPUTED_VALUE"""),5.0) -> 5 | V82: =IFERROR(__xludf.DUMMYFUNCTION("""COMPUTED_VALUE"""),"-") -> - | W82: =IFERROR(__xludf.DUMMYFUNCTION("""COMPUTED_VALUE"""),"-") -> - | X82: =IFERROR(__xludf.DUMMYFUNCTION("""COMPUTED_VALUE"""),46003.0) -> 46003 | Y82: =IFERROR(__xludf.DUMMYFUNCTION("""COMPUTED_VALUE"""),46008.0) -> 46008
D83: =IFERROR(__xludf.DUMMYFUNCTION("""COMPUTED_VALUE"""),"ウエスト") -> ウエスト | E83: =IFERROR(__xludf.DUMMYFUNCTION("""COMPUTED_VALUE"""),"パターン限界値 ±4cm") -> パターン限界値 ±4cm | F83: =IFERROR(__xludf.DUMMYFUNCTION("""COMPUTED_VALUE"""),-10.0) -> -10 | G83: =IFERROR(__xludf.DUMMYFUNCTION("""COMPUTED_VALUE"""),-9.0) -> -9 | H83: =IFERROR(__xludf.DUMMYFUNCTION("""COMPUTED_VALUE"""),-8.0) -> -8 | I83: =IFERROR(__xludf.DUMMYFUNCTION("""COMPUTED_VALUE"""),-7.0) -> -7 | J83: =IFERROR(__xludf.DUMMYFUNCTION("""COMPUTED_VALUE"""),-6.0) -> -6 | K83: =IFERROR(__xludf.DUMMYFUNCTION("""COMPUTED_VALUE"""),-5.0) -> -5 | L83: =IFERROR(__xludf.DUMMYFUNCTION("""COMPUTED_VALUE"""),-4.0) -> -4 | M83: =IFERROR(__xludf.DUMMYFUNCTION("""COMPUTED_VALUE"""),-3.0) -> -3 | N83: =IFERROR(__xludf.DUMMYFUNCTION("""COMPUTED_VALUE"""),-2.0) -> -2 | O83: =IFERROR(__xludf.DUMMYFUNCTION("""COMPUTED_VALUE"""),-1.0) -> -1 | P83: =IFERROR(__xludf.DUMMYFUNCTION("""COMPUTED_VALUE"""),0.0) -> 0 | Q83: =IFERROR(__xludf.DUMMYFUNCTION("""COMPUTED_VALUE"""),1.0) -> 1 | R83: =IFERROR(__xludf.DUMMYFUNCTION("""COMPUTED_VALUE"""),2.0) -> 2 | S83: =IFERROR(__xludf.DUMMYFUNCTION("""COMPUTED_VALUE"""),3.0) -> 3 | T83: =IFERROR(__xludf.DUMMYFUNCTION("""COMPUTED_VALUE"""),4.0) -> 4 | U83: =IFERROR(__xludf.DUMMYFUNCTION("""COMPUTED_VALUE"""),5.0) -> 5 | V83: =IFERROR(__xludf.DUMMYFUNCTION("""COMPUTED_VALUE"""),7.0) -> 7 | W83: =IFERROR(__xludf.DUMMYFUNCTION("""COMPUTED_VALUE"""),46000.0) -> 46000 | X83: =IFERROR(__xludf.DUMMYFUNCTION("""COMPUTED_VALUE"""),46003.0) -> 46003 | Y83: =IFERROR(__xludf.DUMMYFUNCTION("""COMPUTED_VALUE"""),46008.0) -> 46008
D84: =IFERROR(__xludf.DUMMYFUNCTION("""COMPUTED_VALUE"""),"袖丈") -> 袖丈 | F84: =IFERROR(__xludf.DUMMYFUNCTION("""COMPUTED_VALUE"""),-10.0) -> -10 | G84: =IFERROR(__xludf.DUMMYFUNCTION("""COMPUTED_VALUE"""),-9.0) -> -9 | H84: =IFERROR(__xludf.DUMMYFUNCTION("""COMPUTED_VALUE"""),-8.0) -> -8 | I84: =IFERROR(__xludf.DUMMYFUNCTION("""COMPUTED_VALUE"""),-7.0) -> -7 | J84: =IFERROR(__xludf.DUMMYFUNCTION("""COMPUTED_VALUE"""),-6.0) -> -6 | K84: =IFERROR(__xludf.DUMMYFUNCTION("""COMPUTED_VALUE"""),-5.0) -> -5 | L84: =IFERROR(__xludf.DUMMYFUNCTION("""COMPUTED_VALUE"""),-4.0) -> -4 | M84: =IFERROR(__xludf.DUMMYFUNCTION("""COMPUTED_VALUE"""),-3.0) -> -3 | N84: =IFERROR(__xludf.DUMMYFUNCTION("""COMPUTED_VALUE"""),-2.0) -> -2 | O84: =IFERROR(__xludf.DUMMYFUNCTION("""COMPUTED_VALUE"""),-1.0) -> -1 | P84: =IFERROR(__xludf.DUMMYFUNCTION("""COMPUTED_VALUE"""),0.0) -> 0 | Q84: =IFERROR(__xludf.DUMMYFUNCTION("""COMPUTED_VALUE"""),1.0) -> 1 | R84: =IFERROR(__xludf.DUMMYFUNCTION("""COMPUTED_VALUE"""),2.0) -> 2 | S84: =IFERROR(__xludf.DUMMYFUNCTION("""COMPUTED_VALUE"""),3.0) -> 3 | T84: =IFERROR(__xludf.DUMMYFUNCTION("""COMPUTED_VALUE"""),4.0) -> 4 | U84: =IFERROR(__xludf.DUMMYFUNCTION("""COMPUTED_VALUE"""),5.0) -> 5 | V84: =IFERROR(__xludf.DUMMYFUNCTION("""COMPUTED_VALUE"""),7.0) -> 7 | W84: =IFERROR(__xludf.DUMMYFUNCTION("""COMPUTED_VALUE"""),46000.0) -> 46000 | X84: =IFERROR(__xludf.DUMMYFUNCTION("""COMPUTED_VALUE"""),46003.0) -> 46003 | Y84: =IFERROR(__xludf.DUMMYFUNCTION("""COMPUTED_VALUE"""),46008.0) -> 46008
D85: =IFERROR(__xludf.DUMMYFUNCTION("""COMPUTED_VALUE"""),"着丈") -> 着丈 | E85: =IFERROR(__xludf.DUMMYFUNCTION("""COMPUTED_VALUE"""),"パターン限界値 着丈±20cm") -> パターン限界値 着丈±20cm | F85: =IFERROR(__xludf.DUMMYFUNCTION("""COMPUTED_VALUE"""),-10.0) -> -10 | G85: =IFERROR(__xludf.DUMMYFUNCTION("""COMPUTED_VALUE"""),-9.0) -> -9 | H85: =IFERROR(__xludf.DUMMYFUNCTION("""COMPUTED_VALUE"""),-8.0) -> -8 | I85: =IFERROR(__xludf.DUMMYFUNCTION("""COMPUTED_VALUE"""),-7.0) -> -7 | J85: =IFERROR(__xludf.DUMMYFUNCTION("""COMPUTED_VALUE"""),-6.0) -> -6 | K85: =IFERROR(__xludf.DUMMYFUNCTION("""COMPUTED_VALUE"""),-5.0) -> -5 | L85: =IFERROR(__xludf.DUMMYFUNCTION("""COMPUTED_VALUE"""),-4.0) -> -4 | M85: =IFERROR(__xludf.DUMMYFUNCTION("""COMPUTED_VALUE"""),-3.0) -> -3 | N85: =IFERROR(__xludf.DUMMYFUNCTION("""COMPUTED_VALUE"""),-2.0) -> -2 | O85: =IFERROR(__xludf.DUMMYFUNCTION("""COMPUTED_VALUE"""),-1.0) -> -1 | P85: =IFERROR(__xludf.DUMMYFUNCTION("""COMPUTED_VALUE"""),0.0) -> 0 | Q85: =IFERROR(__xludf.DUMMYFUNCTION("""COMPUTED_VALUE"""),1.0) -> 1 | R85: =IFERROR(__xludf.DUMMYFUNCTION("""COMPUTED_VALUE"""),2.0) -> 2 | S85: =IFERROR(__xludf.DUMMYFUNCTION("""COMPUTED_VALUE"""),3.0) -> 3 | T85: =IFERROR(__xludf.DUMMYFUNCTION("""COMPUTED_VALUE"""),4.0) -> 4 | U85: =IFERROR(__xludf.DUMMYFUNCTION("""COMPUTED_VALUE"""),5.0) -> 5 | V85: =IFERROR(__xludf.DUMMYFUNCTION("""COMPUTED_VALUE"""),7.0) -> 7 | W85: =IFERROR(__xludf.DUMMYFUNCTION("""COMPUTED_VALUE"""),46000.0) -> 46000 | X85: =IFERROR(__xludf.DUMMYFUNCTION("""COMPUTED_VALUE"""),46003.0) -> 46003 | Y85: =IFERROR(__xludf.DUMMYFUNCTION("""COMPUTED_VALUE"""),46008.0) -> 46008
D86: =IFERROR(__xludf.DUMMYFUNCTION("""COMPUTED_VALUE"""),"けまわし") -> けまわし | E86: =IFERROR(__xludf.DUMMYFUNCTION("""COMPUTED_VALUE"""),"パターン限界値±8cm") -> パターン限界値±8cm | F86: =IFERROR(__xludf.DUMMYFUNCTION("""COMPUTED_VALUE"""),-10.0) -> -10 | G86: =IFERROR(__xludf.DUMMYFUNCTION("""COMPUTED_VALUE"""),-9.0) -> -9 | H86: =IFERROR(__xludf.DUMMYFUNCTION("""COMPUTED_VALUE"""),-8.0) -> -8 | I86: =IFERROR(__xludf.DUMMYFUNCTION("""COMPUTED_VALUE"""),-7.0) -> -7 | J86: =IFERROR(__xludf.DUMMYFUNCTION("""COMPUTED_VALUE"""),-6.0) -> -6 | K86: =IFERROR(__xludf.DUMMYFUNCTION("""COMPUTED_VALUE"""),-5.0) -> -5 | L86: =IFERROR(__xludf.DUMMYFUNCTION("""COMPUTED_VALUE"""),-4.0) -> -4 | M86: =IFERROR(__xludf.DUMMYFUNCTION("""COMPUTED_VALUE"""),-3.0) -> -3 | N86: =IFERROR(__xludf.DUMMYFUNCTION("""COMPUTED_VALUE"""),-2.0) -> -2 | O86: =IFERROR(__xludf.DUMMYFUNCTION("""COMPUTED_VALUE"""),-1.0) -> -1 | P86: =IFERROR(__xludf.DUMMYFUNCTION("""COMPUTED_VALUE"""),0.0) -> 0 | Q86: =IFERROR(__xludf.DUMMYFUNCTION("""COMPUTED_VALUE"""),1.0) -> 1 | R86: =IFERROR(__xludf.DUMMYFUNCTION("""COMPUTED_VALUE"""),2.0) -> 2 | S86: =IFERROR(__xludf.DUMMYFUNCTION("""COMPUTED_VALUE"""),3.0) -> 3 | T86: =IFERROR(__xludf.DUMMYFUNCTION("""COMPUTED_VALUE"""),4.0) -> 4 | U86: =IFERROR(__xludf.DUMMYFUNCTION("""COMPUTED_VALUE"""),5.0) -> 5 | V86: =IFERROR(__xludf.DUMMYFUNCTION("""COMPUTED_VALUE"""),10.0) -> 10 | W86: =IFERROR(__xludf.DUMMYFUNCTION("""COMPUTED_VALUE"""),46003.0) -> 46003 | X86: =IFERROR(__xludf.DUMMYFUNCTION("""COMPUTED_VALUE"""),46003.0) -> 46003 | Y86: =IFERROR(__xludf.DUMMYFUNCTION("""COMPUTED_VALUE"""),46008.0) -> 46008
B88: =IFERROR(__xludf.DUMMYFUNCTION("""COMPUTED_VALUE"""),"ステンカラー フーデッド") -> ステンカラー フーデッド | C88: =IFERROR(__xludf.DUMMYFUNCTION("""COMPUTED_VALUE"""),"サイズ") -> サイズ | D88: =IFERROR(__xludf.DUMMYFUNCTION("""COMPUTED_VALUE"""),"肩巾") -> 肩巾 | E88: =IFERROR(__xludf.DUMMYFUNCTION("""COMPUTED_VALUE"""),"パターン限界値 -4cm~+6cm") -> パターン限界値 -4cm~+6cm | F88: =IFERROR(__xludf.DUMMYFUNCTION("""COMPUTED_VALUE"""),-10.0) -> -10 | G88: =IFERROR(__xludf.DUMMYFUNCTION("""COMPUTED_VALUE"""),-9.0) -> -9 | H88: =IFERROR(__xludf.DUMMYFUNCTION("""COMPUTED_VALUE"""),-8.0) -> -8 | I88: =IFERROR(__xludf.DUMMYFUNCTION("""COMPUTED_VALUE"""),-7.0) -> -7 | J88: =IFERROR(__xludf.DUMMYFUNCTION("""COMPUTED_VALUE"""),-6.0) -> -6 | K88: =IFERROR(__xludf.DUMMYFUNCTION("""COMPUTED_VALUE"""),-5.0) -> -5 | L88: =IFERROR(__xludf.DUMMYFUNCTION("""COMPUTED_VALUE"""),-4.0) -> -4 | M88: =IFERROR(__xludf.DUMMYFUNCTION("""COMPUTED_VALUE"""),-3.0) -> -3 | N88: =IFERROR(__xludf.DUMMYFUNCTION("""COMPUTED_VALUE"""),-2.0) -> -2 | O88: =IFERROR(__xludf.DUMMYFUNCTION("""COMPUTED_VALUE"""),-1.0) -> -1 | P88: =IFERROR(__xludf.DUMMYFUNCTION("""COMPUTED_VALUE"""),0.0) -> 0 | Q88: =IFERROR(__xludf.DUMMYFUNCTION("""COMPUTED_VALUE"""),1.0) -> 1 | R88: =IFERROR(__xludf.DUMMYFUNCTION("""COMPUTED_VALUE"""),2.0) -> 2 | S88: =IFERROR(__xludf.DUMMYFUNCTION("""COMPUTED_VALUE"""),3.0) -> 3 | T88: =IFERROR(__xludf.DUMMYFUNCTION("""COMPUTED_VALUE"""),4.0) -> 4 | U88: =IFERROR(__xludf.DUMMYFUNCTION("""COMPUTED_VALUE"""),5.0) -> 5 | V88: =IFERROR(__xludf.DUMMYFUNCTION("""COMPUTED_VALUE"""),"-") -> - | W88: =IFERROR(__xludf.DUMMYFUNCTION("""COMPUTED_VALUE"""),"-") -> - | X88: =IFERROR(__xludf.DUMMYFUNCTION("""COMPUTED_VALUE"""),46003.0) -> 46003 | Y88: =IFERROR(__xludf.DUMMYFUNCTION("""COMPUTED_VALUE"""),46008.0) -> 46008
D89: =IFERROR(__xludf.DUMMYFUNCTION("""COMPUTED_VALUE"""),"バスト") -> バスト | F89: =IFERROR(__xludf.DUMMYFUNCTION("""COMPUTED_VALUE"""),-10.0) -> -10 | G89: =IFERROR(__xludf.DUMMYFUNCTION("""COMPUTED_VALUE"""),-9.0) -> -9 | H89: =IFERROR(__xludf.DUMMYFUNCTION("""COMPUTED_VALUE"""),-8.0) -> -8 | I89: =IFERROR(__xludf.DUMMYFUNCTION("""COMPUTED_VALUE"""),-7.0) -> -7 | J89: =IFERROR(__xludf.DUMMYFUNCTION("""COMPUTED_VALUE"""),-6.0) -> -6 | K89: =IFERROR(__xludf.DUMMYFUNCTION("""COMPUTED_VALUE"""),-5.0) -> -5 | L89: =IFERROR(__xludf.DUMMYFUNCTION("""COMPUTED_VALUE"""),-4.0) -> -4 | M89: =IFERROR(__xludf.DUMMYFUNCTION("""COMPUTED_VALUE"""),-3.0) -> -3 | N89: =IFERROR(__xludf.DUMMYFUNCTION("""COMPUTED_VALUE"""),-2.0) -> -2 | O89: =IFERROR(__xludf.DUMMYFUNCTION("""COMPUTED_VALUE"""),-1.0) -> -1 | P89: =IFERROR(__xludf.DUMMYFUNCTION("""COMPUTED_VALUE"""),0.0) -> 0 | Q89: =IFERROR(__xludf.DUMMYFUNCTION("""COMPUTED_VALUE"""),1.0) -> 1 | R89: =IFERROR(__xludf.DUMMYFUNCTION("""COMPUTED_VALUE"""),2.0) -> 2 | S89: =IFERROR(__xludf.DUMMYFUNCTION("""COMPUTED_VALUE"""),3.0) -> 3 | T89: =IFERROR(__xludf.DUMMYFUNCTION("""COMPUTED_VALUE"""),4.0) -> 4 | U89: =IFERROR(__xludf.DUMMYFUNCTION("""COMPUTED_VALUE"""),5.0) -> 5 | V89: =IFERROR(__xludf.DUMMYFUNCTION("""COMPUTED_VALUE"""),"-") -> - | W89: =IFERROR(__xludf.DUMMYFUNCTION("""COMPUTED_VALUE"""),"-") -> - | X89: =IFERROR(__xludf.DUMMYFUNCTION("""COMPUTED_VALUE"""),46003.0) -> 46003 | Y89: =IFERROR(__xludf.DUMMYFUNCTION("""COMPUTED_VALUE"""),46008.0) -> 46008
D90: =IFERROR(__xludf.DUMMYFUNCTION("""COMPUTED_VALUE"""),"ウエスト") -> ウエスト | E90: =IFERROR(__xludf.DUMMYFUNCTION("""COMPUTED_VALUE"""),"パターン限界値 ±4cm") -> パターン限界値 ±4cm | F90: =IFERROR(__xludf.DUMMYFUNCTION("""COMPUTED_VALUE"""),-10.0) -> -10 | G90: =IFERROR(__xludf.DUMMYFUNCTION("""COMPUTED_VALUE"""),-9.0) -> -9 | H90: =IFERROR(__xludf.DUMMYFUNCTION("""COMPUTED_VALUE"""),-8.0) -> -8 | I90: =IFERROR(__xludf.DUMMYFUNCTION("""COMPUTED_VALUE"""),-7.0) -> -7 | J90: =IFERROR(__xludf.DUMMYFUNCTION("""COMPUTED_VALUE"""),-6.0) -> -6 | K90: =IFERROR(__xludf.DUMMYFUNCTION("""COMPUTED_VALUE"""),-5.0) -> -5 | L90: =IFERROR(__xludf.DUMMYFUNCTION("""COMPUTED_VALUE"""),-4.0) -> -4 | M90: =IFERROR(__xludf.DUMMYFUNCTION("""COMPUTED_VALUE"""),-3.0) -> -3 | N90: =IFERROR(__xludf.DUMMYFUNCTION("""COMPUTED_VALUE"""),-2.0) -> -2 | O90: =IFERROR(__xludf.DUMMYFUNCTION("""COMPUTED_VALUE"""),-1.0) -> -1 | P90: =IFERROR(__xludf.DUMMYFUNCTION("""COMPUTED_VALUE"""),0.0) -> 0 | Q90: =IFERROR(__xludf.DUMMYFUNCTION("""COMPUTED_VALUE"""),1.0) -> 1 | R90: =IFERROR(__xludf.DUMMYFUNCTION("""COMPUTED_VALUE"""),2.0) -> 2 | S90: =IFERROR(__xludf.DUMMYFUNCTION("""COMPUTED_VALUE"""),3.0) -> 3 | T90: =IFERROR(__xludf.DUMMYFUNCTION("""COMPUTED_VALUE"""),4.0) -> 4 | U90: =IFERROR(__xludf.DUMMYFUNCTION("""COMPUTED_VALUE"""),5.0) -> 5 | V90: =IFERROR(__xludf.DUMMYFUNCTION("""COMPUTED_VALUE"""),7.0) -> 7 | W90: =IFERROR(__xludf.DUMMYFUNCTION("""COMPUTED_VALUE"""),46000.0) -> 46000 | X90: =IFERROR(__xludf.DUMMYFUNCTION("""COMPUTED_VALUE"""),46003.0) -> 46003 | Y90: =IFERROR(__xludf.DUMMYFUNCTION("""COMPUTED_VALUE"""),46008.0) -> 46008
D91: =IFERROR(__xludf.DUMMYFUNCTION("""COMPUTED_VALUE"""),"袖丈") -> 袖丈 | F91: =IFERROR(__xludf.DUMMYFUNCTION("""COMPUTED_VALUE"""),-10.0) -> -10 | G91: =IFERROR(__xludf.DUMMYFUNCTION("""COMPUTED_VALUE"""),-9.0) -> -9 | H91: =IFERROR(__xludf.DUMMYFUNCTION("""COMPUTED_VALUE"""),-8.0) -> -8 | I91: =IFERROR(__xludf.DUMMYFUNCTION("""COMPUTED_VALUE"""),-7.0) -> -7 | J91: =IFERROR(__xludf.DUMMYFUNCTION("""COMPUTED_VALUE"""),-6.0) -> -6 | K91: =IFERROR(__xludf.DUMMYFUNCTION("""COMPUTED_VALUE"""),-5.0) -> -5 | L91: =IFERROR(__xludf.DUMMYFUNCTION("""COMPUTED_VALUE"""),-4.0) -> -4 | M91: =IFERROR(__xludf.DUMMYFUNCTION("""COMPUTED_VALUE"""),-3.0) -> -3 | N91: =IFERROR(__xludf.DUMMYFUNCTION("""COMPUTED_VALUE"""),-2.0) -> -2 | O91: =IFERROR(__xludf.DUMMYFUNCTION("""COMPUTED_VALUE"""),-1.0) -> -1 | P91: =IFERROR(__xludf.DUMMYFUNCTION("""COMPUTED_VALUE"""),0.0) -> 0 | Q91: =IFERROR(__xludf.DUMMYFUNCTION("""COMPUTED_VALUE"""),1.0) -> 1 | R91: =IFERROR(__xludf.DUMMYFUNCTION("""COMPUTED_VALUE"""),2.0) -> 2 | S91: =IFERROR(__xludf.DUMMYFUNCTION("""COMPUTED_VALUE"""),3.0) -> 3 | T91: =IFERROR(__xludf.DUMMYFUNCTION("""COMPUTED_VALUE"""),4.0) -> 4 | U91: =IFERROR(__xludf.DUMMYFUNCTION("""COMPUTED_VALUE"""),5.0) -> 5 | V91: =IFERROR(__xludf.DUMMYFUNCTION("""COMPUTED_VALUE"""),7.0) -> 7 | W91: =IFERROR(__xludf.DUMMYFUNCTION("""COMPUTED_VALUE"""),46000.0) -> 46000 | X91: =IFERROR(__xludf.DUMMYFUNCTION("""COMPUTED_VALUE"""),46003.0) -> 46003 | Y91: =IFERROR(__xludf.DUMMYFUNCTION("""COMPUTED_VALUE"""),46008.0) -> 46008
D92: =IFERROR(__xludf.DUMMYFUNCTION("""COMPUTED_VALUE"""),"着丈") -> 着丈 | E92: =IFERROR(__xludf.DUMMYFUNCTION("""COMPUTED_VALUE"""),"パターン限界値 着丈±20cm") -> パターン限界値 着丈±20cm | F92: =IFERROR(__xludf.DUMMYFUNCTION("""COMPUTED_VALUE"""),-10.0) -> -10 | G92: =IFERROR(__xludf.DUMMYFUNCTION("""COMPUTED_VALUE"""),-9.0) -> -9 | H92: =IFERROR(__xludf.DUMMYFUNCTION("""COMPUTED_VALUE"""),-8.0) -> -8 | I92: =IFERROR(__xludf.DUMMYFUNCTION("""COMPUTED_VALUE"""),-7.0) -> -7 | J92: =IFERROR(__xludf.DUMMYFUNCTION("""COMPUTED_VALUE"""),-6.0) -> -6 | K92: =IFERROR(__xludf.DUMMYFUNCTION("""COMPUTED_VALUE"""),-5.0) -> -5 | L92: =IFERROR(__xludf.DUMMYFUNCTION("""COMPUTED_VALUE"""),-4.0) -> -4 | M92: =IFERROR(__xludf.DUMMYFUNCTION("""COMPUTED_VALUE"""),-3.0) -> -3 | N92: =IFERROR(__xludf.DUMMYFUNCTION("""COMPUTED_VALUE"""),-2.0) -> -2 | O92: =IFERROR(__xludf.DUMMYFUNCTION("""COMPUTED_VALUE"""),-1.0) -> -1 | P92: =IFERROR(__xludf.DUMMYFUNCTION("""COMPUTED_VALUE"""),0.0) -> 0 | Q92: =IFERROR(__xludf.DUMMYFUNCTION("""COMPUTED_VALUE"""),1.0) -> 1 | R92: =IFERROR(__xludf.DUMMYFUNCTION("""COMPUTED_VALUE"""),2.0) -> 2 | S92: =IFERROR(__xludf.DUMMYFUNCTION("""COMPUTED_VALUE"""),3.0) -> 3 | T92: =IFERROR(__xludf.DUMMYFUNCTION("""COMPUTED_VALUE"""),4.0) -> 4 | U92: =IFERROR(__xludf.DUMMYFUNCTION("""COMPUTED_VALUE"""),5.0) -> 5 | V92: =IFERROR(__xludf.DUMMYFUNCTION("""COMPUTED_VALUE"""),7.0) -> 7 | W92: =IFERROR(__xludf.DUMMYFUNCTION("""COMPUTED_VALUE"""),46000.0) -> 46000 | X92: =IFERROR(__xludf.DUMMYFUNCTION("""COMPUTED_VALUE"""),46003.0) -> 46003 | Y92: =IFERROR(__xludf.DUMMYFUNCTION("""COMPUTED_VALUE"""),46008.0) -> 46008
D93: =IFERROR(__xludf.DUMMYFUNCTION("""COMPUTED_VALUE"""),"けまわし") -> けまわし | E93: =IFERROR(__xludf.DUMMYFUNCTION("""COMPUTED_VALUE"""),"パターン限界値±8cm") -> パターン限界値±8cm | F93: =IFERROR(__xludf.DUMMYFUNCTION("""COMPUTED_VALUE"""),-10.0) -> -10 | G93: =IFERROR(__xludf.DUMMYFUNCTION("""COMPUTED_VALUE"""),-9.0) -> -9 | H93: =IFERROR(__xludf.DUMMYFUNCTION("""COMPUTED_VALUE"""),-8.0) -> -8 | I93: =IFERROR(__xludf.DUMMYFUNCTION("""COMPUTED_VALUE"""),-7.0) -> -7 | J93: =IFERROR(__xludf.DUMMYFUNCTION("""COMPUTED_VALUE"""),-6.0) -> -6 | K93: =IFERROR(__xludf.DUMMYFUNCTION("""COMPUTED_VALUE"""),-5.0) -> -5 | L93: =IFERROR(__xludf.DUMMYFUNCTION("""COMPUTED_VALUE"""),-4.0) -> -4 | M93: =IFERROR(__xludf.DUMMYFUNCTION("""COMPUTED_VALUE"""),-3.0) -> -3 | N93: =IFERROR(__xludf.DUMMYFUNCTION("""COMPUTED_VALUE"""),-2.0) -> -2 | O93: =IFERROR(__xludf.DUMMYFUNCTION("""COMPUTED_VALUE"""),-1.0) -> -1 | P93: =IFERROR(__xludf.DUMMYFUNCTION("""COMPUTED_VALUE"""),0.0) -> 0 | Q93: =IFERROR(__xludf.DUMMYFUNCTION("""COMPUTED_VALUE"""),1.0) -> 1 | R93: =IFERROR(__xludf.DUMMYFUNCTION("""COMPUTED_VALUE"""),2.0) -> 2 | S93: =IFERROR(__xludf.DUMMYFUNCTION("""COMPUTED_VALUE"""),3.0) -> 3 | T93: =IFERROR(__xludf.DUMMYFUNCTION("""COMPUTED_VALUE"""),4.0) -> 4 | U93: =IFERROR(__xludf.DUMMYFUNCTION("""COMPUTED_VALUE"""),5.0) -> 5 | V93: =IFERROR(__xludf.DUMMYFUNCTION("""COMPUTED_VALUE"""),10.0) -> 10 | W93: =IFERROR(__xludf.DUMMYFUNCTION("""COMPUTED_VALUE"""),46003.0) -> 46003 | X93: =IFERROR(__xludf.DUMMYFUNCTION("""COMPUTED_VALUE"""),46003.0) -> 46003 | Y93: =IFERROR(__xludf.DUMMYFUNCTION("""COMPUTED_VALUE"""),46008.0) -> 46008
B95: =IFERROR(__xludf.DUMMYFUNCTION("""COMPUTED_VALUE""")," アルスター") -> アルスター | C95: =IFERROR(__xludf.DUMMYFUNCTION("""COMPUTED_VALUE"""),"サイズ") -> サイズ | D95: =IFERROR(__xludf.DUMMYFUNCTION("""COMPUTED_VALUE"""),"肩巾") -> 肩巾 | E95: =IFERROR(__xludf.DUMMYFUNCTION("""COMPUTED_VALUE"""),"パターン限界値 -4cm~+3cm") -> パターン限界値 -4cm~+3cm | F95: =IFERROR(__xludf.DUMMYFUNCTION("""COMPUTED_VALUE"""),-10.0) -> -10 | G95: =IFERROR(__xludf.DUMMYFUNCTION("""COMPUTED_VALUE"""),-9.0) -> -9 | H95: =IFERROR(__xludf.DUMMYFUNCTION("""COMPUTED_VALUE"""),-8.0) -> -8 | I95: =IFERROR(__xludf.DUMMYFUNCTION("""COMPUTED_VALUE"""),-7.0) -> -7 | J95: =IFERROR(__xludf.DUMMYFUNCTION("""COMPUTED_VALUE"""),-6.0) -> -6 | K95: =IFERROR(__xludf.DUMMYFUNCTION("""COMPUTED_VALUE"""),-5.0) -> -5 | L95: =IFERROR(__xludf.DUMMYFUNCTION("""COMPUTED_VALUE"""),-4.0) -> -4 | M95: =IFERROR(__xludf.DUMMYFUNCTION("""COMPUTED_VALUE"""),-3.0) -> -3 | N95: =IFERROR(__xludf.DUMMYFUNCTION("""COMPUTED_VALUE"""),-2.0) -> -2 | O95: =IFERROR(__xludf.DUMMYFUNCTION("""COMPUTED_VALUE"""),-1.0) -> -1 | P95: =IFERROR(__xludf.DUMMYFUNCTION("""COMPUTED_VALUE"""),0.0) -> 0 | Q95: =IFERROR(__xludf.DUMMYFUNCTION("""COMPUTED_VALUE"""),1.0) -> 1 | R95: =IFERROR(__xludf.DUMMYFUNCTION("""COMPUTED_VALUE"""),2.0) -> 2 | S95: =IFERROR(__xludf.DUMMYFUNCTION("""COMPUTED_VALUE"""),3.0) -> 3 | T95: =IFERROR(__xludf.DUMMYFUNCTION("""COMPUTED_VALUE"""),4.0) -> 4 | U95: =IFERROR(__xludf.DUMMYFUNCTION("""COMPUTED_VALUE"""),5.0) -> 5 | V95: =IFERROR(__xludf.DUMMYFUNCTION("""COMPUTED_VALUE"""),7.0) -> 7 | W95: =IFERROR(__xludf.DUMMYFUNCTION("""COMPUTED_VALUE"""),46000.0) -> 46000 | X95: =IFERROR(__xludf.DUMMYFUNCTION("""COMPUTED_VALUE"""),46003.0) -> 46003 | Y95: =IFERROR(__xludf.DUMMYFUNCTION("""COMPUTED_VALUE"""),46008.0) -> 46008
D96: =IFERROR(__xludf.DUMMYFUNCTION("""COMPUTED_VALUE"""),"バスト") -> バスト | F96: =IFERROR(__xludf.DUMMYFUNCTION("""COMPUTED_VALUE"""),-10.0) -> -10 | G96: =IFERROR(__xludf.DUMMYFUNCTION("""COMPUTED_VALUE"""),-9.0) -> -9 | H96: =IFERROR(__xludf.DUMMYFUNCTION("""COMPUTED_VALUE"""),-8.0) -> -8 | I96: =IFERROR(__xludf.DUMMYFUNCTION("""COMPUTED_VALUE"""),-7.0) -> -7 | J96: =IFERROR(__xludf.DUMMYFUNCTION("""COMPUTED_VALUE"""),-6.0) -> -6 | K96: =IFERROR(__xludf.DUMMYFUNCTION("""COMPUTED_VALUE"""),-5.0) -> -5 | L96: =IFERROR(__xludf.DUMMYFUNCTION("""COMPUTED_VALUE"""),-4.0) -> -4 | M96: =IFERROR(__xludf.DUMMYFUNCTION("""COMPUTED_VALUE"""),-3.0) -> -3 | N96: =IFERROR(__xludf.DUMMYFUNCTION("""COMPUTED_VALUE"""),-2.0) -> -2 | O96: =IFERROR(__xludf.DUMMYFUNCTION("""COMPUTED_VALUE"""),-1.0) -> -1 | P96: =IFERROR(__xludf.DUMMYFUNCTION("""COMPUTED_VALUE"""),0.0) -> 0 | Q96: =IFERROR(__xludf.DUMMYFUNCTION("""COMPUTED_VALUE"""),1.0) -> 1 | R96: =IFERROR(__xludf.DUMMYFUNCTION("""COMPUTED_VALUE"""),2.0) -> 2 | S96: =IFERROR(__xludf.DUMMYFUNCTION("""COMPUTED_VALUE"""),3.0) -> 3 | T96: =IFERROR(__xludf.DUMMYFUNCTION("""COMPUTED_VALUE"""),4.0) -> 4 | U96: =IFERROR(__xludf.DUMMYFUNCTION("""COMPUTED_VALUE"""),5.0) -> 5 | V96: =IFERROR(__xludf.DUMMYFUNCTION("""COMPUTED_VALUE"""),"-") -> - | W96: =IFERROR(__xludf.DUMMYFUNCTION("""COMPUTED_VALUE"""),"-") -> - | X96: =IFERROR(__xludf.DUMMYFUNCTION("""COMPUTED_VALUE"""),46003.0) -> 46003 | Y96: =IFERROR(__xludf.DUMMYFUNCTION("""COMPUTED_VALUE"""),46008.0) -> 46008
D97: =IFERROR(__xludf.DUMMYFUNCTION("""COMPUTED_VALUE"""),"ウエスト") -> ウエスト | E97: =IFERROR(__xludf.DUMMYFUNCTION("""COMPUTED_VALUE"""),"パターン限界値 ±4cm") -> パターン限界値 ±4cm | F97: =IFERROR(__xludf.DUMMYFUNCTION("""COMPUTED_VALUE"""),-10.0) -> -10 | G97: =IFERROR(__xludf.DUMMYFUNCTION("""COMPUTED_VALUE"""),-9.0) -> -9 | H97: =IFERROR(__xludf.DUMMYFUNCTION("""COMPUTED_VALUE"""),-8.0) -> -8 | I97: =IFERROR(__xludf.DUMMYFUNCTION("""COMPUTED_VALUE"""),-7.0) -> -7 | J97: =IFERROR(__xludf.DUMMYFUNCTION("""COMPUTED_VALUE"""),-6.0) -> -6 | K97: =IFERROR(__xludf.DUMMYFUNCTION("""COMPUTED_VALUE"""),-5.0) -> -5 | L97: =IFERROR(__xludf.DUMMYFUNCTION("""COMPUTED_VALUE"""),-4.0) -> -4 | M97: =IFERROR(__xludf.DUMMYFUNCTION("""COMPUTED_VALUE"""),-3.0) -> -3 | N97: =IFERROR(__xludf.DUMMYFUNCTION("""COMPUTED_VALUE"""),-2.0) -> -2 | O97: =IFERROR(__xludf.DUMMYFUNCTION("""COMPUTED_VALUE"""),-1.0) -> -1 | P97: =IFERROR(__xludf.DUMMYFUNCTION("""COMPUTED_VALUE"""),0.0) -> 0 | Q97: =IFERROR(__xludf.DUMMYFUNCTION("""COMPUTED_VALUE"""),1.0) -> 1 | R97: =IFERROR(__xludf.DUMMYFUNCTION("""COMPUTED_VALUE"""),2.0) -> 2 | S97: =IFERROR(__xludf.DUMMYFUNCTION("""COMPUTED_VALUE"""),3.0) -> 3 | T97: =IFERROR(__xludf.DUMMYFUNCTION("""COMPUTED_VALUE"""),4.0) -> 4 | U97: =IFERROR(__xludf.DUMMYFUNCTION("""COMPUTED_VALUE"""),5.0) -> 5 | V97: =IFERROR(__xludf.DUMMYFUNCTION("""COMPUTED_VALUE"""),7.0) -> 7 | W97: =IFERROR(__xludf.DUMMYFUNCTION("""COMPUTED_VALUE"""),46000.0) -> 46000 | X97: =IFERROR(__xludf.DUMMYFUNCTION("""COMPUTED_VALUE"""),46003.0) -> 46003 | Y97: =IFERROR(__xludf.DUMMYFUNCTION("""COMPUTED_VALUE"""),46008.0) -> 46008
D98: =IFERROR(__xludf.DUMMYFUNCTION("""COMPUTED_VALUE"""),"袖丈") -> 袖丈 | F98: =IFERROR(__xludf.DUMMYFUNCTION("""COMPUTED_VALUE"""),-10.0) -> -10 | G98: =IFERROR(__xludf.DUMMYFUNCTION("""COMPUTED_VALUE"""),-9.0) -> -9 | H98: =IFERROR(__xludf.DUMMYFUNCTION("""COMPUTED_VALUE"""),-8.0) -> -8 | I98: =IFERROR(__xludf.DUMMYFUNCTION("""COMPUTED_VALUE"""),-7.0) -> -7 | J98: =IFERROR(__xludf.DUMMYFUNCTION("""COMPUTED_VALUE"""),-6.0) -> -6 | K98: =IFERROR(__xludf.DUMMYFUNCTION("""COMPUTED_VALUE"""),-5.0) -> -5 | L98: =IFERROR(__xludf.DUMMYFUNCTION("""COMPUTED_VALUE"""),-4.0) -> -4 | M98: =IFERROR(__xludf.DUMMYFUNCTION("""COMPUTED_VALUE"""),-3.0) -> -3 | N98: =IFERROR(__xludf.DUMMYFUNCTION("""COMPUTED_VALUE"""),-2.0) -> -2 | O98: =IFERROR(__xludf.DUMMYFUNCTION("""COMPUTED_VALUE"""),-1.0) -> -1 | P98: =IFERROR(__xludf.DUMMYFUNCTION("""COMPUTED_VALUE"""),0.0) -> 0 | Q98: =IFERROR(__xludf.DUMMYFUNCTION("""COMPUTED_VALUE"""),1.0) -> 1 | R98: =IFERROR(__xludf.DUMMYFUNCTION("""COMPUTED_VALUE"""),2.0) -> 2 | S98: =IFERROR(__xludf.DUMMYFUNCTION("""COMPUTED_VALUE"""),3.0) -> 3 | T98: =IFERROR(__xludf.DUMMYFUNCTION("""COMPUTED_VALUE"""),4.0) -> 4 | U98: =IFERROR(__xludf.DUMMYFUNCTION("""COMPUTED_VALUE"""),5.0) -> 5 | V98: =IFERROR(__xludf.DUMMYFUNCTION("""COMPUTED_VALUE"""),7.0) -> 7 | W98: =IFERROR(__xludf.DUMMYFUNCTION("""COMPUTED_VALUE"""),46000.0) -> 46000 | X98: =IFERROR(__xludf.DUMMYFUNCTION("""COMPUTED_VALUE"""),46003.0) -> 46003 | Y98: =IFERROR(__xludf.DUMMYFUNCTION("""COMPUTED_VALUE"""),46008.0) -> 46008
D99: =IFERROR(__xludf.DUMMYFUNCTION("""COMPUTED_VALUE"""),"着丈") -> 着丈 | E99: =IFERROR(__xludf.DUMMYFUNCTION("""COMPUTED_VALUE"""),"パターン限界値 着丈±20cm") -> パターン限界値 着丈±20cm | F99: =IFERROR(__xludf.DUMMYFUNCTION("""COMPUTED_VALUE"""),-10.0) -> -10 | G99: =IFERROR(__xludf.DUMMYFUNCTION("""COMPUTED_VALUE"""),-9.0) -> -9 | H99: =IFERROR(__xludf.DUMMYFUNCTION("""COMPUTED_VALUE"""),-8.0) -> -8 | I99: =IFERROR(__xludf.DUMMYFUNCTION("""COMPUTED_VALUE"""),-7.0) -> -7 | J99: =IFERROR(__xludf.DUMMYFUNCTION("""COMPUTED_VALUE"""),-6.0) -> -6 | K99: =IFERROR(__xludf.DUMMYFUNCTION("""COMPUTED_VALUE"""),-5.0) -> -5 | L99: =IFERROR(__xludf.DUMMYFUNCTION("""COMPUTED_VALUE"""),-4.0) -> -4 | M99: =IFERROR(__xludf.DUMMYFUNCTION("""COMPUTED_VALUE"""),-3.0) -> -3 | N99: =IFERROR(__xludf.DUMMYFUNCTION("""COMPUTED_VALUE"""),-2.0) -> -2 | O99: =IFERROR(__xludf.DUMMYFUNCTION("""COMPUTED_VALUE"""),-1.0) -> -1 | P99: =IFERROR(__xludf.DUMMYFUNCTION("""COMPUTED_VALUE"""),0.0) -> 0 | Q99: =IFERROR(__xludf.DUMMYFUNCTION("""COMPUTED_VALUE"""),1.0) -> 1 | R99: =IFERROR(__xludf.DUMMYFUNCTION("""COMPUTED_VALUE"""),2.0) -> 2 | S99: =IFERROR(__xludf.DUMMYFUNCTION("""COMPUTED_VALUE"""),3.0) -> 3 | T99: =IFERROR(__xludf.DUMMYFUNCTION("""COMPUTED_VALUE"""),4.0) -> 4 | U99: =IFERROR(__xludf.DUMMYFUNCTION("""COMPUTED_VALUE"""),5.0) -> 5 | V99: =IFERROR(__xludf.DUMMYFUNCTION("""COMPUTED_VALUE"""),7.0) -> 7 | W99: =IFERROR(__xludf.DUMMYFUNCTION("""COMPUTED_VALUE"""),46000.0) -> 46000 | X99: =IFERROR(__xludf.DUMMYFUNCTION("""COMPUTED_VALUE"""),46003.0) -> 46003 | Y99: =IFERROR(__xludf.DUMMYFUNCTION("""COMPUTED_VALUE"""),46008.0) -> 46008
D100: =IFERROR(__xludf.DUMMYFUNCTION("""COMPUTED_VALUE"""),"けまわし") -> けまわし | E100: =IFERROR(__xludf.DUMMYFUNCTION("""COMPUTED_VALUE"""),"パターン限界値±8cm") -> パターン限界値±8cm | F100: =IFERROR(__xludf.DUMMYFUNCTION("""COMPUTED_VALUE"""),-10.0) -> -10 | G100: =IFERROR(__xludf.DUMMYFUNCTION("""COMPUTED_VALUE"""),-9.0) -> -9 | H100: =IFERROR(__xludf.DUMMYFUNCTION("""COMPUTED_VALUE"""),-8.0) -> -8 | I100: =IFERROR(__xludf.DUMMYFUNCTION("""COMPUTED_VALUE"""),-7.0) -> -7 | J100: =IFERROR(__xludf.DUMMYFUNCTION("""COMPUTED_VALUE"""),-6.0) -> -6 | K100: =IFERROR(__xludf.DUMMYFUNCTION("""COMPUTED_VALUE"""),-5.0) -> -5 | L100: =IFERROR(__xludf.DUMMYFUNCTION("""COMPUTED_VALUE"""),-4.0) -> -4 | M100: =IFERROR(__xludf.DUMMYFUNCTION("""COMPUTED_VALUE"""),-3.0) -> -3 | N100: =IFERROR(__xludf.DUMMYFUNCTION("""COMPUTED_VALUE"""),-2.0) -> -2 | O100: =IFERROR(__xludf.DUMMYFUNCTION("""COMPUTED_VALUE"""),-1.0) -> -1 | P100: =IFERROR(__xludf.DUMMYFUNCTION("""COMPUTED_VALUE"""),0.0) -> 0 | Q100: =IFERROR(__xludf.DUMMYFUNCTION("""COMPUTED_VALUE"""),1.0) -> 1 | R100: =IFERROR(__xludf.DUMMYFUNCTION("""COMPUTED_VALUE"""),2.0) -> 2 | S100: =IFERROR(__xludf.DUMMYFUNCTION("""COMPUTED_VALUE"""),3.0) -> 3 | T100: =IFERROR(__xludf.DUMMYFUNCTION("""COMPUTED_VALUE"""),4.0) -> 4 | U100: =IFERROR(__xludf.DUMMYFUNCTION("""COMPUTED_VALUE"""),5.0) -> 5 | V100: =IFERROR(__xludf.DUMMYFUNCTION("""COMPUTED_VALUE"""),10.0) -> 10 | W100: =IFERROR(__xludf.DUMMYFUNCTION("""COMPUTED_VALUE"""),46003.0) -> 46003 | X100: =IFERROR(__xludf.DUMMYFUNCTION("""COMPUTED_VALUE"""),46003.0) -> 46003 | Y100: =IFERROR(__xludf.DUMMYFUNCTION("""COMPUTED_VALUE"""),46008.0) -> 46008
B102: =IFERROR(__xludf.DUMMYFUNCTION("""COMPUTED_VALUE""")," ショートステン") -> ショートステン | C102: =IFERROR(__xludf.DUMMYFUNCTION("""COMPUTED_VALUE"""),"サイズ") -> サイズ | D102: =IFERROR(__xludf.DUMMYFUNCTION("""COMPUTED_VALUE"""),"肩巾") -> 肩巾 | E102: =IFERROR(__xludf.DUMMYFUNCTION("""COMPUTED_VALUE"""),"パターン限界値 -4cm~+3cm") -> パターン限界値 -4cm~+3cm | F102: =IFERROR(__xludf.DUMMYFUNCTION("""COMPUTED_VALUE"""),-10.0) -> -10 | G102: =IFERROR(__xludf.DUMMYFUNCTION("""COMPUTED_VALUE"""),-9.0) -> -9 | H102: =IFERROR(__xludf.DUMMYFUNCTION("""COMPUTED_VALUE"""),-8.0) -> -8 | I102: =IFERROR(__xludf.DUMMYFUNCTION("""COMPUTED_VALUE"""),-7.0) -> -7 | J102: =IFERROR(__xludf.DUMMYFUNCTION("""COMPUTED_VALUE"""),-6.0) -> -6 | K102: =IFERROR(__xludf.DUMMYFUNCTION("""COMPUTED_VALUE"""),-5.0) -> -5 | L102: =IFERROR(__xludf.DUMMYFUNCTION("""COMPUTED_VALUE"""),-4.0) -> -4 | M102: =IFERROR(__xludf.DUMMYFUNCTION("""COMPUTED_VALUE"""),-3.0) -> -3 | N102: =IFERROR(__xludf.DUMMYFUNCTION("""COMPUTED_VALUE"""),-2.0) -> -2 | O102: =IFERROR(__xludf.DUMMYFUNCTION("""COMPUTED_VALUE"""),-1.0) -> -1 | P102: =IFERROR(__xludf.DUMMYFUNCTION("""COMPUTED_VALUE"""),0.0) -> 0 | Q102: =IFERROR(__xludf.DUMMYFUNCTION("""COMPUTED_VALUE"""),1.0) -> 1 | R102: =IFERROR(__xludf.DUMMYFUNCTION("""COMPUTED_VALUE"""),2.0) -> 2 | S102: =IFERROR(__xludf.DUMMYFUNCTION("""COMPUTED_VALUE"""),3.0) -> 3 | T102: =IFERROR(__xludf.DUMMYFUNCTION("""COMPUTED_VALUE"""),4.0) -> 4 | U102: =IFERROR(__xludf.DUMMYFUNCTION("""COMPUTED_VALUE"""),5.0) -> 5 | V102: =IFERROR(__xludf.DUMMYFUNCTION("""COMPUTED_VALUE"""),"-") -> - | W102: =IFERROR(__xludf.DUMMYFUNCTION("""COMPUTED_VALUE"""),"-") -> - | X102: =IFERROR(__xludf.DUMMYFUNCTION("""COMPUTED_VALUE"""),46003.0) -> 46003 | Y102: =IFERROR(__xludf.DUMMYFUNCTION("""COMPUTED_VALUE"""),46008.0) -> 46008
D103: =IFERROR(__xludf.DUMMYFUNCTION("""COMPUTED_VALUE"""),"バスト") -> バスト | F103: =IFERROR(__xludf.DUMMYFUNCTION("""COMPUTED_VALUE"""),-10.0) -> -10 | G103: =IFERROR(__xludf.DUMMYFUNCTION("""COMPUTED_VALUE"""),-9.0) -> -9 | H103: =IFERROR(__xludf.DUMMYFUNCTION("""COMPUTED_VALUE"""),-8.0) -> -8 | I103: =IFERROR(__xludf.DUMMYFUNCTION("""COMPUTED_VALUE"""),-7.0) -> -7 | J103: =IFERROR(__xludf.DUMMYFUNCTION("""COMPUTED_VALUE"""),-6.0) -> -6 | K103: =IFERROR(__xludf.DUMMYFUNCTION("""COMPUTED_VALUE"""),-5.0) -> -5 | L103: =IFERROR(__xludf.DUMMYFUNCTION("""COMPUTED_VALUE"""),-4.0) -> -4 | M103: =IFERROR(__xludf.DUMMYFUNCTION("""COMPUTED_VALUE"""),-3.0) -> -3 | N103: =IFERROR(__xludf.DUMMYFUNCTION("""COMPUTED_VALUE"""),-2.0) -> -2 | O103: =IFERROR(__xludf.DUMMYFUNCTION("""COMPUTED_VALUE"""),-1.0) -> -1 | P103: =IFERROR(__xludf.DUMMYFUNCTION("""COMPUTED_VALUE"""),0.0) -> 0 | Q103: =IFERROR(__xludf.DUMMYFUNCTION("""COMPUTED_VALUE"""),1.0) -> 1 | R103: =IFERROR(__xludf.DUMMYFUNCTION("""COMPUTED_VALUE"""),2.0) -> 2 | S103: =IFERROR(__xludf.DUMMYFUNCTION("""COMPUTED_VALUE"""),3.0) -> 3 | T103: =IFERROR(__xludf.DUMMYFUNCTION("""COMPUTED_VALUE"""),4.0) -> 4 | U103: =IFERROR(__xludf.DUMMYFUNCTION("""COMPUTED_VALUE"""),5.0) -> 5 | V103: =IFERROR(__xludf.DUMMYFUNCTION("""COMPUTED_VALUE"""),"-") -> - | W103: =IFERROR(__xludf.DUMMYFUNCTION("""COMPUTED_VALUE"""),"-") -> - | X103: =IFERROR(__xludf.DUMMYFUNCTION("""COMPUTED_VALUE"""),46003.0) -> 46003 | Y103: =IFERROR(__xludf.DUMMYFUNCTION("""COMPUTED_VALUE"""),46008.0) -> 46008
D104: =IFERROR(__xludf.DUMMYFUNCTION("""COMPUTED_VALUE"""),"ウエスト") -> ウエスト | E104: =IFERROR(__xludf.DUMMYFUNCTION("""COMPUTED_VALUE"""),"パターン限界値 ±4cm") -> パターン限界値 ±4cm | F104: =IFERROR(__xludf.DUMMYFUNCTION("""COMPUTED_VALUE"""),-10.0) -> -10 | G104: =IFERROR(__xludf.DUMMYFUNCTION("""COMPUTED_VALUE"""),-9.0) -> -9 | H104: =IFERROR(__xludf.DUMMYFUNCTION("""COMPUTED_VALUE"""),-8.0) -> -8 | I104: =IFERROR(__xludf.DUMMYFUNCTION("""COMPUTED_VALUE"""),-7.0) -> -7 | J104: =IFERROR(__xludf.DUMMYFUNCTION("""COMPUTED_VALUE"""),-6.0) -> -6 | K104: =IFERROR(__xludf.DUMMYFUNCTION("""COMPUTED_VALUE"""),-5.0) -> -5 | L104: =IFERROR(__xludf.DUMMYFUNCTION("""COMPUTED_VALUE"""),-4.0) -> -4 | M104: =IFERROR(__xludf.DUMMYFUNCTION("""COMPUTED_VALUE"""),-3.0) -> -3 | N104: =IFERROR(__xludf.DUMMYFUNCTION("""COMPUTED_VALUE"""),-2.0) -> -2 | O104: =IFERROR(__xludf.DUMMYFUNCTION("""COMPUTED_VALUE"""),-1.0) -> -1 | P104: =IFERROR(__xludf.DUMMYFUNCTION("""COMPUTED_VALUE"""),0.0) -> 0 | Q104: =IFERROR(__xludf.DUMMYFUNCTION("""COMPUTED_VALUE"""),1.0) -> 1 | R104: =IFERROR(__xludf.DUMMYFUNCTION("""COMPUTED_VALUE"""),2.0) -> 2 | S104: =IFERROR(__xludf.DUMMYFUNCTION("""COMPUTED_VALUE"""),3.0) -> 3 | T104: =IFERROR(__xludf.DUMMYFUNCTION("""COMPUTED_VALUE"""),4.0) -> 4 | U104: =IFERROR(__xludf.DUMMYFUNCTION("""COMPUTED_VALUE"""),5.0) -> 5 | V104: =IFERROR(__xludf.DUMMYFUNCTION("""COMPUTED_VALUE"""),7.0) -> 7 | W104: =IFERROR(__xludf.DUMMYFUNCTION("""COMPUTED_VALUE"""),46000.0) -> 46000 | X104: =IFERROR(__xludf.DUMMYFUNCTION("""COMPUTED_VALUE"""),46003.0) -> 46003 | Y104: =IFERROR(__xludf.DUMMYFUNCTION("""COMPUTED_VALUE"""),46008.0) -> 46008
D105: =IFERROR(__xludf.DUMMYFUNCTION("""COMPUTED_VALUE"""),"袖丈") -> 袖丈 | F105: =IFERROR(__xludf.DUMMYFUNCTION("""COMPUTED_VALUE"""),-10.0) -> -10 | G105: =IFERROR(__xludf.DUMMYFUNCTION("""COMPUTED_VALUE"""),-9.0) -> -9 | H105: =IFERROR(__xludf.DUMMYFUNCTION("""COMPUTED_VALUE"""),-8.0) -> -8 | I105: =IFERROR(__xludf.DUMMYFUNCTION("""COMPUTED_VALUE"""),-7.0) -> -7 | J105: =IFERROR(__xludf.DUMMYFUNCTION("""COMPUTED_VALUE"""),-6.0) -> -6 | K105: =IFERROR(__xludf.DUMMYFUNCTION("""COMPUTED_VALUE"""),-5.0) -> -5 | L105: =IFERROR(__xludf.DUMMYFUNCTION("""COMPUTED_VALUE"""),-4.0) -> -4 | M105: =IFERROR(__xludf.DUMMYFUNCTION("""COMPUTED_VALUE"""),-3.0) -> -3 | N105: =IFERROR(__xludf.DUMMYFUNCTION("""COMPUTED_VALUE"""),-2.0) -> -2 | O105: =IFERROR(__xludf.DUMMYFUNCTION("""COMPUTED_VALUE"""),-1.0) -> -1 | P105: =IFERROR(__xludf.DUMMYFUNCTION("""COMPUTED_VALUE"""),0.0) -> 0 | Q105: =IFERROR(__xludf.DUMMYFUNCTION("""COMPUTED_VALUE"""),1.0) -> 1 | R105: =IFERROR(__xludf.DUMMYFUNCTION("""COMPUTED_VALUE"""),2.0) -> 2 | S105: =IFERROR(__xludf.DUMMYFUNCTION("""COMPUTED_VALUE"""),3.0) -> 3 | T105: =IFERROR(__xludf.DUMMYFUNCTION("""COMPUTED_VALUE"""),4.0) -> 4 | U105: =IFERROR(__xludf.DUMMYFUNCTION("""COMPUTED_VALUE"""),5.0) -> 5 | V105: =IFERROR(__xludf.DUMMYFUNCTION("""COMPUTED_VALUE"""),7.0) -> 7 | W105: =IFERROR(__xludf.DUMMYFUNCTION("""COMPUTED_VALUE"""),46000.0) -> 46000 | X105: =IFERROR(__xludf.DUMMYFUNCTION("""COMPUTED_VALUE"""),46003.0) -> 46003 | Y105: =IFERROR(__xludf.DUMMYFUNCTION("""COMPUTED_VALUE"""),46008.0) -> 46008
D106: =IFERROR(__xludf.DUMMYFUNCTION("""COMPUTED_VALUE"""),"着丈") -> 着丈 | E106: =IFERROR(__xludf.DUMMYFUNCTION("""COMPUTED_VALUE"""),"パターン限界値 着丈±20cm") -> パターン限界値 着丈±20cm | F106: =IFERROR(__xludf.DUMMYFUNCTION("""COMPUTED_VALUE"""),-10.0) -> -10 | G106: =IFERROR(__xludf.DUMMYFUNCTION("""COMPUTED_VALUE"""),-9.0) -> -9 | H106: =IFERROR(__xludf.DUMMYFUNCTION("""COMPUTED_VALUE"""),-8.0) -> -8 | I106: =IFERROR(__xludf.DUMMYFUNCTION("""COMPUTED_VALUE"""),-7.0) -> -7 | J106: =IFERROR(__xludf.DUMMYFUNCTION("""COMPUTED_VALUE"""),-6.0) -> -6 | K106: =IFERROR(__xludf.DUMMYFUNCTION("""COMPUTED_VALUE"""),-5.0) -> -5 | L106: =IFERROR(__xludf.DUMMYFUNCTION("""COMPUTED_VALUE"""),-4.0) -> -4 | M106: =IFERROR(__xludf.DUMMYFUNCTION("""COMPUTED_VALUE"""),-3.0) -> -3 | N106: =IFERROR(__xludf.DUMMYFUNCTION("""COMPUTED_VALUE"""),-2.0) -> -2 | O106: =IFERROR(__xludf.DUMMYFUNCTION("""COMPUTED_VALUE"""),-1.0) -> -1 | P106: =IFERROR(__xludf.DUMMYFUNCTION("""COMPUTED_VALUE"""),0.0) -> 0 | Q106: =IFERROR(__xludf.DUMMYFUNCTION("""COMPUTED_VALUE"""),1.0) -> 1 | R106: =IFERROR(__xludf.DUMMYFUNCTION("""COMPUTED_VALUE"""),2.0) -> 2 | S106: =IFERROR(__xludf.DUMMYFUNCTION("""COMPUTED_VALUE"""),3.0) -> 3 | T106: =IFERROR(__xludf.DUMMYFUNCTION("""COMPUTED_VALUE"""),4.0) -> 4 | U106: =IFERROR(__xludf.DUMMYFUNCTION("""COMPUTED_VALUE"""),5.0) -> 5 | V106: =IFERROR(__xludf.DUMMYFUNCTION("""COMPUTED_VALUE"""),7.0) -> 7 | W106: =IFERROR(__xludf.DUMMYFUNCTION("""COMPUTED_VALUE"""),46000.0) -> 46000 | X106: =IFERROR(__xludf.DUMMYFUNCTION("""COMPUTED_VALUE"""),46003.0) -> 46003 | Y106: =IFERROR(__xludf.DUMMYFUNCTION("""COMPUTED_VALUE"""),46008.0) -> 46008
D107: =IFERROR(__xludf.DUMMYFUNCTION("""COMPUTED_VALUE"""),"けまわし") -> けまわし | E107: =IFERROR(__xludf.DUMMYFUNCTION("""COMPUTED_VALUE"""),"パターン限界値±8cm") -> パターン限界値±8cm | F107: =IFERROR(__xludf.DUMMYFUNCTION("""COMPUTED_VALUE"""),-10.0) -> -10 | G107: =IFERROR(__xludf.DUMMYFUNCTION("""COMPUTED_VALUE"""),-9.0) -> -9 | H107: =IFERROR(__xludf.DUMMYFUNCTION("""COMPUTED_VALUE"""),-8.0) -> -8 | I107: =IFERROR(__xludf.DUMMYFUNCTION("""COMPUTED_VALUE"""),-7.0) -> -7 | J107: =IFERROR(__xludf.DUMMYFUNCTION("""COMPUTED_VALUE"""),-6.0) -> -6 | K107: =IFERROR(__xludf.DUMMYFUNCTION("""COMPUTED_VALUE"""),-5.0) -> -5 | L107: =IFERROR(__xludf.DUMMYFUNCTION("""COMPUTED_VALUE"""),-4.0) -> -4 | M107: =IFERROR(__xludf.DUMMYFUNCTION("""COMPUTED_VALUE"""),-3.0) -> -3 | N107: =IFERROR(__xludf.DUMMYFUNCTION("""COMPUTED_VALUE"""),-2.0) -> -2 | O107: =IFERROR(__xludf.DUMMYFUNCTION("""COMPUTED_VALUE"""),-1.0) -> -1 | P107: =IFERROR(__xludf.DUMMYFUNCTION("""COMPUTED_VALUE"""),0.0) -> 0 | Q107: =IFERROR(__xludf.DUMMYFUNCTION("""COMPUTED_VALUE"""),1.0) -> 1 | R107: =IFERROR(__xludf.DUMMYFUNCTION("""COMPUTED_VALUE"""),2.0) -> 2 | S107: =IFERROR(__xludf.DUMMYFUNCTION("""COMPUTED_VALUE"""),3.0) -> 3 | T107: =IFERROR(__xludf.DUMMYFUNCTION("""COMPUTED_VALUE"""),4.0) -> 4 | U107: =IFERROR(__xludf.DUMMYFUNCTION("""COMPUTED_VALUE"""),5.0) -> 5 | V107: =IFERROR(__xludf.DUMMYFUNCTION("""COMPUTED_VALUE"""),10.0) -> 10 | W107: =IFERROR(__xludf.DUMMYFUNCTION("""COMPUTED_VALUE"""),46003.0) -> 46003 | X107: =IFERROR(__xludf.DUMMYFUNCTION("""COMPUTED_VALUE"""),46003.0) -> 46003 | Y107: =IFERROR(__xludf.DUMMYFUNCTION("""COMPUTED_VALUE"""),46008.0) -> 46008
B109: =IFERROR(__xludf.DUMMYFUNCTION("""COMPUTED_VALUE""")," カットソー 長袖") -> カットソー 長袖 | C109: =IFERROR(__xludf.DUMMYFUNCTION("""COMPUTED_VALUE"""),"サイズ") -> サイズ | D109: =IFERROR(__xludf.DUMMYFUNCTION("""COMPUTED_VALUE"""),"裄丈") -> 裄丈 | E109: =IFERROR(__xludf.DUMMYFUNCTION("""COMPUTED_VALUE"""),"カフスあり") -> カフスあり | F109: =IFERROR(__xludf.DUMMYFUNCTION("""COMPUTED_VALUE"""),-10.0) -> -10 | G109: =IFERROR(__xludf.DUMMYFUNCTION("""COMPUTED_VALUE"""),-9.0) -> -9 | H109: =IFERROR(__xludf.DUMMYFUNCTION("""COMPUTED_VALUE"""),-8.0) -> -8 | I109: =IFERROR(__xludf.DUMMYFUNCTION("""COMPUTED_VALUE"""),-7.0) -> -7 | J109: =IFERROR(__xludf.DUMMYFUNCTION("""COMPUTED_VALUE"""),-6.0) -> -6 | K109: =IFERROR(__xludf.DUMMYFUNCTION("""COMPUTED_VALUE"""),-5.0) -> -5 | L109: =IFERROR(__xludf.DUMMYFUNCTION("""COMPUTED_VALUE"""),-4.0) -> -4 | M109: =IFERROR(__xludf.DUMMYFUNCTION("""COMPUTED_VALUE"""),-3.0) -> -3 | N109: =IFERROR(__xludf.DUMMYFUNCTION("""COMPUTED_VALUE"""),-2.0) -> -2 | O109: =IFERROR(__xludf.DUMMYFUNCTION("""COMPUTED_VALUE"""),-1.0) -> -1 | P109: =IFERROR(__xludf.DUMMYFUNCTION("""COMPUTED_VALUE"""),0.0) -> 0 | Q109: =IFERROR(__xludf.DUMMYFUNCTION("""COMPUTED_VALUE"""),1.0) -> 1 | R109: =IFERROR(__xludf.DUMMYFUNCTION("""COMPUTED_VALUE"""),2.0) -> 2 | S109: =IFERROR(__xludf.DUMMYFUNCTION("""COMPUTED_VALUE"""),3.0) -> 3 | T109: =IFERROR(__xludf.DUMMYFUNCTION("""COMPUTED_VALUE"""),4.0) -> 4 | U109: =IFERROR(__xludf.DUMMYFUNCTION("""COMPUTED_VALUE"""),5.0) -> 5 | V109: =IFERROR(__xludf.DUMMYFUNCTION("""COMPUTED_VALUE"""),7.0) -> 7 | W109: =IFERROR(__xludf.DUMMYFUNCTION("""COMPUTED_VALUE"""),46000.0) -> 46000 | X109: =IFERROR(__xludf.DUMMYFUNCTION("""COMPUTED_VALUE"""),46003.0) -> 46003 | Y109: =IFERROR(__xludf.DUMMYFUNCTION("""COMPUTED_VALUE"""),46008.0) -> 46008
D110: =IFERROR(__xludf.DUMMYFUNCTION("""COMPUTED_VALUE"""),"裄丈") -> 裄丈 | E110: =IFERROR(__xludf.DUMMYFUNCTION("""COMPUTED_VALUE"""),"カフスなし") -> カフスなし | F110: =IFERROR(__xludf.DUMMYFUNCTION("""COMPUTED_VALUE"""),-10.0) -> -10 | G110: =IFERROR(__xludf.DUMMYFUNCTION("""COMPUTED_VALUE"""),-9.0) -> -9 | H110: =IFERROR(__xludf.DUMMYFUNCTION("""COMPUTED_VALUE"""),-8.0) -> -8 | I110: =IFERROR(__xludf.DUMMYFUNCTION("""COMPUTED_VALUE"""),-7.0) -> -7 | J110: =IFERROR(__xludf.DUMMYFUNCTION("""COMPUTED_VALUE"""),-6.0) -> -6 | K110: =IFERROR(__xludf.DUMMYFUNCTION("""COMPUTED_VALUE"""),-5.0) -> -5 | L110: =IFERROR(__xludf.DUMMYFUNCTION("""COMPUTED_VALUE"""),-4.0) -> -4 | M110: =IFERROR(__xludf.DUMMYFUNCTION("""COMPUTED_VALUE"""),-3.0) -> -3 | N110: =IFERROR(__xludf.DUMMYFUNCTION("""COMPUTED_VALUE"""),-2.0) -> -2 | O110: =IFERROR(__xludf.DUMMYFUNCTION("""COMPUTED_VALUE"""),-1.0) -> -1 | P110: =IFERROR(__xludf.DUMMYFUNCTION("""COMPUTED_VALUE"""),0.0) -> 0 | Q110: =IFERROR(__xludf.DUMMYFUNCTION("""COMPUTED_VALUE"""),1.0) -> 1 | R110: =IFERROR(__xludf.DUMMYFUNCTION("""COMPUTED_VALUE"""),2.0) -> 2 | S110: =IFERROR(__xludf.DUMMYFUNCTION("""COMPUTED_VALUE"""),3.0) -> 3 | T110: =IFERROR(__xludf.DUMMYFUNCTION("""COMPUTED_VALUE"""),4.0) -> 4 | U110: =IFERROR(__xludf.DUMMYFUNCTION("""COMPUTED_VALUE"""),5.0) -> 5 | V110: =IFERROR(__xludf.DUMMYFUNCTION("""COMPUTED_VALUE"""),7.0) -> 7 | W110: =IFERROR(__xludf.DUMMYFUNCTION("""COMPUTED_VALUE"""),46000.0) -> 46000 | X110: =IFERROR(__xludf.DUMMYFUNCTION("""COMPUTED_VALUE"""),46003.0) -> 46003 | Y110: =IFERROR(__xludf.DUMMYFUNCTION("""COMPUTED_VALUE"""),46008.0) -> 46008
...

Sheet 新宿1_お直し対応シート
A1: =today() -> 45991 | D1: 新宿 | K1: 再製作：318-6372-0626
D3: {=index(A3:A5,0)}
A4: お客さま詳細・管理メモテンプレ | D4: お客さま詳細・管理メモテンプレ
A5: =$A$7 & $A$8 & CHAR(10) & $A$10 & CHAR(10) & CHAR(10) & $A$11 -> FABRIC TOKYO 新宿 2025-11-30 お直し適用サイズ ◼︎ シャツ（対応着地：再製作） 《修正数値》 着丈 : 4 cm 《仕上がり数値》 着丈 : cm 【お直し詳細】 ① お客さまのご要望：例）ウエストがゆるい気がする ②「体型変動」程度の大幅なヌード寸の差異：あり・なし ③ お直しが起きた原因：例）もう少し上側で穿きたかったという要望のすり合わせ不足 【備考・エピソード】 | B5: ="【お直し来店済み】" & CHAR(10) & "来店⽇時：" & text($A$1," yyyy/mm/dd")& CHAR(10) & "来店店舗：" & $D$1 & CHAR(10) & CHAR(10) & "お直し着地：" & CHAR(10) & $A$10 -> 【お直し来店済み】 来店⽇時： 2025/11/30 来店店舗：新宿 お直し着地： ◼︎ シャツ（対応着地：再製作） 《修正数値》 着丈 : 4 cm 《仕上がり数値》 着丈 : cm | D5: FABRIC TOKYO 新宿 2025-11-30 お直し適用サイズ ◼︎ シャツ（対応着地：再製作） 《修正数値》 着丈 : 4 cm 《仕上がり数値》 着丈 : cm 【お直し詳細】 ① お客さまのご要望：例）ウエストがゆるい気がする ②「体型変動」程度の大幅なヌード寸の差異：あり・なし ③ お直しが起きた原因：例）もう少し上側で穿きたかったという要望のすり合わせ不足 【備考・エピソード】 | I5: ="【お直し来店済み】" & CHAR(10) & "来店⽇時：" & text($A$1," yyyy/mm/dd")& CHAR(10) & "来店店舗：" & $D$1 & CHAR(10) & CHAR(10) & "お直し着地：" & CHAR(10) & $A$10 -> 【お直し来店済み】 来店⽇時： 2025/11/30 来店店舗：新宿 お直し着地： ◼︎ シャツ（対応着地：再製作） 《修正数値》 着丈 : 4 cm 《仕上がり数値》 着丈 : cm | K5: CS確認依頼・共有事項テンプレ
A7: =IF((SUM(LEN(I11), LEN(N11), LEN(S11), LEN(X11), LEN(AC11), LEN(AH11), LEN(AM11), LEN(AR11), LEN(AW11), LEN(BB11), LEN(BG11)))>0, "FABRIC TOKYO "& $D$1 & " " & TEXT($A$1, "yyyy-m-d") & " お直し適用サイズ" & CHAR(10), "") -> FABRIC TOKYO 新宿 2025-11-30 お直し適用サイズ | D7: 2P / 3P / セットアップ お直し納期判定
A8: =ifs($D$11<>"", "FABRIC TOKYO "& $D$1& "" & text($A$1," yyyy-m-d"&" お直し適用サイズ ＊スーツサイズ") & CHAR(10) & "FABRIC TOKYO "& $D$1& "" & text($A$1," yyyy-m-d"&" お直し適用サイズ ＊ビジネスカジュアルサイズ" & CHAR(10)) , $D$11="", "") | E8: 袖丈・裄丈・股下は左右であっても1箇所換算 シャツバスト・AHは二つで1箇所換算。AHのみいじりたいなど、AHの数値指定は一発再製作です 過去に股下お直しをしたことがあるパンツは、股下出しができません | N8: 緑セル以外触らないでください。 保護をかけているので編集できないはずです。 万が一編集できたらモンさんまでご一報ください。
A10: {=TRIM( IF($A$14<>"",TEXTJOIN(CHAR(10),TRUE,IF($A$14:$A$17<>"",$A$14:$A$17,"")) & CHAR(10) & CHAR(10),"") & IF($A$19<>"",TEXTJOIN(CHAR(10),TRUE,IF($A$19:$A$22<>"",$A$19:$A$22,"")) & CHAR(10) & CHAR(10),"") & IF($A$24<>"",TEXTJOIN(CHAR(10),TRUE,IF($A$24:$A$27<>"",$A$24:$A$27,"")) & CHAR(10) & CHAR(10),"") & IF($A$29<>"",TEXTJOIN(CHAR(10),TRUE,IF($A$29:$A$32<>"",$A$29:$A$32,"")) & CHAR(10) & CHAR(10),"") & IF($A$34<>"",TEXTJOIN(CHAR(10),TRUE,IF($A$34:$A$37<>"",$A$34:$A$37,"")) & CHAR(10) & CHAR(10),"") & IF($A$39<>"",TEXTJOIN(CHAR(10),TRUE,IF($A$39:$A$42<>"",$A$39:$A$42,"")) & CHAR(10) & CHAR(10),"") & IF($A$44<>"",TEXTJOIN(CHAR(10),TRUE,IF($A$44:$A$47<>"",$A$44:$A$47,"")) & CHAR(10) & CHAR(10),"") & IF($A$49<>"",TEXTJOIN(CHAR(10),TRUE,IF($A$49:$A$52<>"",$A$49:$A$52,"")) & CHAR(10) & CHAR(10),"") & IF($A$54<>"",TEXTJOIN(CHAR(10),TRUE,IF($A$54:$A$57<>"",$A$54:$A$57,"")) & CHAR(10) & CHAR(10),"") & IF($A$59<>"",TEXTJOIN(CHAR(10),TRUE,IF($A$59:$A$62<>"",$A$59:$A$62,"")) & CHAR(10) & CHAR(10),"") & IF($A$64<>"",TEXTJOIN(CHAR(10),TRUE,IF($A$64:$A$67<>"",$A$64:$A$67,"")) & CHAR(10) & CHAR(10),"") & IF($A$69<>"",TEXTJOIN(CHAR(10),TRUE,IF($A$69:$A$72<>"",$A$69:$A$72,"")) & CHAR(10) & CHAR(10),"") )} -> ◼︎ シャツ（対応着地：再製作） 《修正数値》 着丈 : 4 cm 《仕上がり数値》 着丈 : cm | D10: ジャケット / ジャコット | G10: ↓ 税込料金 ↓ | I10: スラックス / カジュアルパンツ | L10: ↓ 税込料金 ↓ | N10: ベスト | Q10: ↓ 税込料金 ↓ | S10: チノパン | V10: ↓ 税込料金 ↓ | X10: シャツ (フォーマル / タックアウト) | AA10: ↓ 税込料金 ↓ | AC10: ポロシャツ | AF10: ↓ 税込料金 ↓ | AH10: アルスターコート | AK10: ↓ 税込料金 ↓ | AM10: ショートステンカラーコート | AP10: ↓ 税込料金 ↓ | AR10: ステンカラーコート | AU10: ↓ 税込料金 ↓ | AW10: チェスターコート | AZ10: ↓ 税込料金 ↓ | BB10: トレンチコート | BE10: ↓ 税込料金 ↓ | BG10: フーデッドコート | BJ10: ↓ 税込料金 ↓ | BL10: カットソー | BO10: ↓ 税込料金 ↓
A11: 【お直し詳細】 ① お客さまのご要望：例）ウエストがゆるい気がする ②「体型変動」程度の大幅なヌード寸の差異：あり・なし ③ お直しが起きた原因：例）もう少し上側で穿きたかったという要望のすり合わせ不足 【備考・エピソード】 | D11: {=IFS( COUNTA(F$13:F27) = 0, "", COUNTIF(F$13:F27, "再製作") > 0, "再製作", COUNTIF(F$13:F27, ">0") = 1, INDEX(F$13:F27, MATCH(TRUE, ISNUMBER(F$13:F27), 0)), COUNTIF(F$13:F27, ">0") = 2, 'アイテム別限界値DB'!$S$4, COUNTIF(F$13:F27, ">0") >= 3, 'アイテム別限界値DB'!$S$6, TRUE, "" )} | E11: お直し ↓ 数値 ↓ | F11: ↓ DB参照結果 ↓ | G11: =sum(G12:G72) -> 0 | I11: {=IFS( COUNTA(K$13:K27) = 0, "", COUNTIF(K$13:K27, "再製作") > 0, "再製作", COUNTIF(K$13:K27, ">0") = 1, INDEX(K$13:K27, MATCH(TRUE, ISNUMBER(K$13:K27), 0)), COUNTIF(K$13:K27, ">0") = 2, 'アイテム別限界値DB'!$S$8, COUNTIF(K$13:K27, ">0") >= 3, 'アイテム別限界値DB'!$S$10, TRUE, "" )} | J11: お直し ↓ 数値 ↓ | K11: ↓ DB参照結果 ↓ | L11: =sum(L12:L72) -> 0 | N11: {=IFS( COUNTA(P$13:P27) = 0, "", COUNTIF(P$13:P27, "再製作") > 0, "再製作", COUNTIF(P$13:P27, ">0") = 1, INDEX(P$13:P27, MATCH(TRUE, ISNUMBER(P$13:P27), 0)), COUNTIF(P$13:P27, ">0") = 2, 'アイテム別限界値DB'!$S$4, COUNTIF(P$13:P27, ">0") >= 3, 'アイテム別限界値DB'!$S$6, TRUE, "" )} | O11: お直し ↓ 数値 ↓ | P11: ↓ DB参照結果 ↓ | Q11: =sum(Q12:Q72) -> 0 | S11: {=IFS( COUNTA(U$13:U27) = 0, "", COUNTIF(U$13:U27, "再製作") > 0, "再製作", COUNTIF(U$13:U27, ">0") = 1, INDEX(U$13:U27, MATCH(TRUE, ISNUMBER(U$13:U27), 0)), COUNTIF(U$13:U27, ">0") = 2, 'アイテム別限界値DB'!$S$8, COUNTIF(U$13:U27, ">0") >= 3, 'アイテム別限界値DB'!$S$10, TRUE, "" )} | T11: お直し ↓ 数値 ↓ | U11: ↓ DB参照結果 ↓ | V11: =sum(V12:V72) -> 0 | X11: {=IFS( COUNTA(Z$13:Z27) = 0, "", COUNTIF(Z$13:Z27, "再製作") > 0, "再製作", COUNTIF(Z$13:Z27, ">0") = 1, INDEX(Z$13:Z27, MATCH(TRUE, ISNUMBER(Z$13:Z27), 0)), COUNTIF(Z$13:Z27, ">0") = 2, 'アイテム別限界値DB'!$S$4, COUNTIF(Z$13:Z27, ">0") >= 3, 'アイテム別限界値DB'!$S$6, TRUE, "" )} -> 再製作 | Y11: お直し ↓ 数値 ↓ | Z11: ↓ DB参照結果 ↓ | AA11: =sum(AA12:AA72) -> 0 | AC11: {=IFS( COUNTA(AE$13:AE27) = 0, "", COUNTIF(AE$13:AE27, "再製作") > 0, "再製作", COUNTIF(AE$13:AE27, ">0") = 1, INDEX(AE$13:AE27, MATCH(TRUE, ISNUMBER(AE$13:AE27), 0)), COUNTIF(AE$13:AE27, ">0") = 2, 'アイテム別限界値DB'!$S$4, COUNTIF(AE$13:AE27, ">0") >= 3, 'アイテム別限界値DB'!$S$6, TRUE, "" )} | AD11: お直し ↓ 数値 ↓ | AE11: ↓ DB参照結果 ↓ | AF11: =sum(AF12:AF72) -> 0 | AH11: {=IFS( COUNTA(AJ$13:AJ27) = 0, "", COUNTIF(AJ$13:AJ27, "再製作") > 0, "再製作", COUNTIF(AJ$13:AJ27, ">0") = 1, INDEX(AJ$13:AJ27, MATCH(TRUE, ISNUMBER(AJ$13:AJ27), 0)), COUNTIF(AJ$13:AJ27, ">0") = 2, 'アイテム別限界値DB'!$S$4, COUNTIF(AJ$13:AJ27, ">0") >= 3, 'アイテム別限界値DB'!$S$6, TRUE, "" )} | AI11: お直し ↓ 数値 ↓ | AJ11: ↓ DB参照結果 ↓ | AK11: =sum(AK12:AK72) -> 0 | AM11: {=IFS( COUNTA(AO$13:AO27) = 0, "", COUNTIF(AO$13:AO27, "再製作") > 0, "再製作", COUNTIF(AO$13:AO27, ">0") = 1, INDEX(AO$13:AO27, MATCH(TRUE, ISNUMBER(AO$13:AO27), 0)), COUNTIF(AO$13:AO27, ">0") = 2, 'アイテム別限界値DB'!$S$4, COUNTIF(AO$13:AO27, ">0") >= 3, 'アイテム別限界値DB'!$S$6, TRUE, "" )} | AN11: お直し ↓ 数値 ↓ | AO11: ↓ DB参照結果 ↓ | AP11: =sum(AP12:AP72) -> 0 | AR11: {=IFS( COUNTA(AT$13:AT27) = 0, "", COUNTIF(AT$13:AT27, "再製作") > 0, "再製作", COUNTIF(AT$13:AT27, ">0") = 1, INDEX(AT$13:AT27, MATCH(TRUE, ISNUMBER(AT$13:AT27), 0)), COUNTIF(AT$13:AT27, ">0") = 2, 'アイテム別限界値DB'!$S$4, COUNTIF(AT$13:AT27, ">0") >= 3, 'アイテム別限界値DB'!$S$6, TRUE, "" )} | AS11: お直し ↓ 数値 ↓ | AT11: ↓ DB参照結果 ↓ | AU11: =sum(AU12:AU72) -> 0 | AW11: {=IFS( COUNTA(AY$13:AY27) = 0, "", COUNTIF(AY$13:AY27, "再製作") > 0, "再製作", COUNTIF(AY$13:AY27, ">0") = 1, INDEX(AY$13:AY27, MATCH(TRUE, ISNUMBER(AY$13:AY27), 0)), COUNTIF(AY$13:AY27, ">0") = 2, 'アイテム別限界値DB'!$S$4, COUNTIF(AY$13:AY27, ">0") >= 3, 'アイテム別限界値DB'!$S$6, TRUE, "" )} | AX11: お直し ↓ 数値 ↓ | AY11: ↓ DB参照結果 ↓ | AZ11: =sum(AZ12:AZ72) -> 0 | BB11: {=IFS( COUNTA(BD$13:BD27) = 0, "", COUNTIF(BD$13:BD27, "再製作") > 0, "再製作", COUNTIF(BD$13:BD27, ">0") = 1, INDEX(BD$13:BD27, MATCH(TRUE, ISNUMBER(BD$13:BD27), 0)), COUNTIF(BD$13:BD27, ">0") = 2, 'アイテム別限界値DB'!$S$4, COUNTIF(BD$13:BD27, ">0") >= 3, 'アイテム別限界値DB'!$S$6, TRUE, "" )} | BC11: お直し ↓ 数値 ↓ | BD11: ↓ DB参照結果 ↓ | BE11: =sum(BE12:BE72) -> 0 | BG11: {=IFS( COUNTA(BI$13:BI27) = 0, "", COUNTIF(BI$13:BI27, "再製作") > 0, "再製作", COUNTIF(BI$13:BI27, ">0") = 1, INDEX(BI$13:BI27, MATCH(TRUE, ISNUMBER(BI$13:BI27), 0)), COUNTIF(BI$13:BI27, ">0") = 2, 'アイテム別限界値DB'!$S$4, COUNTIF(BI$13:BI27, ">0") >= 3, 'アイテム別限界値DB'!$S$6, TRUE, "" )} | BH11: お直し ↓ 数値 ↓ | BI11: ↓ DB参照結果 ↓ | BJ11: =sum(BJ12:BJ72) -> 0 | BL11: {=IFS( COUNTA(BN$13:BN27) = 0, "", COUNTIF(BN$13:BN27, "再製作") > 0, "再製作", COUNTIF(BN$13:BN27, ">0") = 1, INDEX(BN$13:BN27, MATCH(TRUE, ISNUMBER(BN$13:BN27), 0)), COUNTIF(BN$13:BN27, ">0") = 2, 'アイテム別限界値DB'!$S$4, COUNTIF(BN$13:BN27, ">0") >= 3, 'アイテム別限界値DB'!$S$6, TRUE, "" )} -> 46003 | BM11: お直し ↓ 数値 ↓ | BN11: ↓ DB参照結果 ↓ | BO11: =sum(BO12:BO72) -> 0
D12: 仕上げプレス | E12: =IF(D11="再製作", "再製作", IF(D11<>"", "お直し", "")) | G12: {=IF( E12 = "再製作", "", if(E12="", "", IFERROR( INDEX( 'アイテム別限界値DB'!$L:$L, MATCH( 1, ('アイテム別限界値DB'!$B:$B = D$10) * ('アイテム別限界値DB'!$C:$C = D12), 0 ) ), "再製作" ) ))} | I12: 仕上げプレス | J12: =IF(I11="再製作", "再製作", IF(I11<>"", "お直し", "")) | L12: {=IF( J12 = "再製作", "", if(J12="", "", IFERROR( INDEX( 'アイテム別限界値DB'!$L:$L, MATCH( 1, ('アイテム別限界値DB'!$B:$B = I$10) * ('アイテム別限界値DB'!$C:$C = I12), 0 ) ), "再製作" ) ))} | N12: 仕上げプレス | O12: =IF(N11="再製作", "再製作", IF(N11<>"", "お直し", "")) | Q12: {=IF( O12 = "再製作", "", if(O12="", "", IFERROR( INDEX( 'アイテム別限界値DB'!$L:$L, MATCH( 1, ('アイテム別限界値DB'!$B:$B = N$10) * ('アイテム別限界値DB'!$C:$C = N12), 0 ) ), "再製作" ) ))} | S12: 仕上げプレス | T12: =IF(S11="再製作", "再製作", IF(S11<>"", "お直し", "")) | V12: {=IF( T12 = "再製作", "", if(T12="", "", IFERROR( INDEX( 'アイテム別限界値DB'!$L:$L, MATCH( 1, ('アイテム別限界値DB'!$B:$B = S$10) * ('アイテム別限界値DB'!$C:$C = S12), 0 ) ), "再製作" ) ))} | X12: 仕上げプレス | Y12: =IF(X11="再製作", "再製作", IF(X11<>"", "お直し", "")) -> 再製作 | AA12: {=IF( Y12 = "再製作", "", if(Y12="", "", IFERROR( INDEX( 'アイテム別限界値DB'!$L:$L, MATCH( 1, ('アイテム別限界値DB'!$B:$B = X$10) * ('アイテム別限界値DB'!$C:$C = X12), 0 ) ), "再製作" ) ))} | AC12: 仕上げプレス | AD12: =IF(AC11="再製作", "再製作", IF(AC11<>"", "お直し", "")) | AF12: {=IF( AD12 = "再製作", "", if(AD12="", "", IFERROR( INDEX( 'アイテム別限界値DB'!$L:$L, MATCH( 1, ('アイテム別限界値DB'!$B:$B = AC$10) * ('アイテム別限界値DB'!$C:$C = AC12), 0 ) ), "再製作" ) ))} | AH12: 仕上げプレス | AI12: =IF(AH11="再製作", "再製作", IF(AH11<>"", "お直し", "")) | AK12: {=IF( AI12 = "再製作", "", if(AI12="", "", IFERROR( INDEX( 'アイテム別限界値DB'!$L:$L, MATCH( 1, ('アイテム別限界値DB'!$B:$B = AH$10) * ('アイテム別限界値DB'!$C:$C = AH12), 0 ) ), "再製作" ) ))} | AM12: 仕上げプレス | AN12: =IF(AM11="再製作", "再製作", IF(AM11<>"", "お直し", "")) | AP12: {=IF( AN12 = "再製作", "", if(AN12="", "", IFERROR( INDEX( 'アイテム別限界値DB'!$L:$L, MATCH( 1, ('アイテム別限界値DB'!$B:$B = AM$10) * ('アイテム別限界値DB'!$C:$C = AM12), 0 ) ), "再製作" ) ))} | AR12: 仕上げプレス | AS12: =IF(AR11="再製作", "再製作", IF(AR11<>"", "お直し", "")) | AU12: {=IF( AS12 = "再製作", "", if(AS12="", "", IFERROR( INDEX( 'アイテム別限界値DB'!$L:$L, MATCH( 1, ('アイテム別限界値DB'!$B:$B = AR$10) * ('アイテム別限界値DB'!$C:$C = AR12), 0 ) ), "再製作" ) ))} | AW12: 仕上げプレス | AX12: =IF(AW11="再製作", "再製作", IF(AW11<>"", "お直し", "")) | AZ12: {=IF( AX12 = "再製作", "", if(AX12="", "", IFERROR( INDEX( 'アイテム別限界値DB'!$L:$L, MATCH( 1, ('アイテム別限界値DB'!$B:$B = AW$10) * ('アイテム別限界値DB'!$C:$C = AW12), 0 ) ), "再製作" ) ))} | BB12: 仕上げプレス | BC12: =IF(BB11="再製作", "再製作", IF(BB11<>"", "お直し", "")) | BE12: {=IF( BC12 = "再製作", "", if(BC12="", "", IFERROR( INDEX( 'アイテム別限界値DB'!$L:$L, MATCH( 1, ('アイテム別限界値DB'!$B:$B = BB$10) * ('アイテム別限界値DB'!$C:$C = BB12), 0 ) ), "再製作" ) ))} | BG12: 仕上げプレス | BH12: =IF(BG11="再製作", "再製作", IF(BG11<>"", "お直し", "")) | BJ12: {=IF( BH12 = "再製作", "", if(BH12="", "", IFERROR( INDEX( 'アイテム別限界値DB'!$L:$L, MATCH( 1, ('アイテム別限界値DB'!$B:$B = BG$10) * ('アイテム別限界値DB'!$C:$C = BG12), 0 ) ), "再製作" ) ))} | BL12: 仕上げプレス | BM12: =IF(BL11="再製作", "再製作", IF(BL11<>"", "お直し", "")) -> お直し | BO12: {=IF( BM12 = "再製作", "", if(BM12="", "", IFERROR( INDEX( 'アイテム別限界値DB'!$L:$L, MATCH( 1, ('アイテム別限界値DB'!$B:$B = BL$10) * ('アイテム別限界値DB'!$C:$C = BL12), 0 ) ), "再製作" ) ))}
A13: //ジャケット// | D13: {=UNIQUE(IF( ('アイテム別限界値DB'!$B:$B = D$10) * ('アイテム別限界値DB'!$A:$A = "サイズ"), IF('アイテム別限界値DB'!$B:$B = D$10, 'アイテム別限界値DB'!$F:$F, "") ))} -> FALSE | I13: {=UNIQUE(IF( ('アイテム別限界値DB'!$B:$B = I$10) * ('アイテム別限界値DB'!$A:$A = "サイズ"), IF('アイテム別限界値DB'!$B:$B = I$10, 'アイテム別限界値DB'!$F:$F, "") ))} -> FALSE | N13: {=UNIQUE(IF( ('アイテム別限界値DB'!$B:$B = N$10) * ('アイテム別限界値DB'!$A:$A = "サイズ"), IF('アイテム別限界値DB'!$B:$B = N$10, 'アイテム別限界値DB'!$C:$C, "") ))} -> FALSE | S13: {=UNIQUE(IF( ('アイテム別限界値DB'!$B:$B = S$10) * ('アイテム別限界値DB'!$A:$A = "サイズ"), IF('アイテム別限界値DB'!$B:$B = S$10, 'アイテム別限界値DB'!$F:$F, "") ))} -> FALSE | X13: {=UNIQUE(IF( ('アイテム別限界値DB'!$B:$B = X$10) * ('アイテム別限界値DB'!$A:$A = "サイズ"), IF('アイテム別限界値DB'!$B:$B = X$10, 'アイテム別限界値DB'!$C:$C, "") ))} -> FALSE | AC13: {=UNIQUE(IF( ('アイテム別限界値DB'!$B:$B = AC$10) * ('アイテム別限界値DB'!$A:$A = "サイズ"), IF('アイテム別限界値DB'!$B:$B = AC$10, 'アイテム別限界値DB'!$F:$F, "") ))} -> FALSE | AH13: {=UNIQUE(IF( ('アイテム別限界値DB'!$B:$B = AH$10) * ('アイテム別限界値DB'!$A:$A = "サイズ"), IF('アイテム別限界値DB'!$B:$B = AH$10, 'アイテム別限界値DB'!$F:$F, "") ))} -> FALSE | AM13: {=UNIQUE(IF( ('アイテム別限界値DB'!$B:$B = AM$10) * ('アイテム別限界値DB'!$A:$A = "サイズ"), IF('アイテム別限界値DB'!$B:$B = AM$10, 'アイテム別限界値DB'!$F:$F, "") ))} -> FALSE | AR13: {=UNIQUE(IF( ('アイテム別限界値DB'!$B:$B = AR$10) * ('アイテム別限界値DB'!$A:$A = "サイズ"), IF('アイテム別限界値DB'!$B:$B = AR$10, 'アイテム別限界値DB'!$F:$F, "") ))} -> FALSE | AW13: {=UNIQUE(IF( ('アイテム別限界値DB'!$B:$B = AW$10) * ('アイテム別限界値DB'!$A:$A = "サイズ"), IF('アイテム別限界値DB'!$B:$B = AW$10, 'アイテム別限界値DB'!$F:$F, "") ))} -> FALSE | BB13: {=UNIQUE(IF( ('アイテム別限界値DB'!$B:$B = BB$10) * ('アイテム別限界値DB'!$A:$A = "サイズ"), IF('アイテム別限界値DB'!$B:$B = BB$10, 'アイテム別限界値DB'!$F:$F, "") ))} -> FALSE | BG13: {=UNIQUE(IF( ('アイテム別限界値DB'!$B:$B = BG$10) * ('アイテム別限界値DB'!$A:$A = "サイズ"), IF('アイテム別限界値DB'!$B:$B = BG$10, 'アイテム別限界値DB'!$F:$F, "") ))} -> FALSE | BL13: {=UNIQUE(IF( ('アイテム別限界値DB'!$B:$B = BL$10) * ('アイテム別限界値DB'!$A:$A = "サイズ"), IF('アイテム別限界値DB'!$B:$B = BL$10, 'アイテム別限界値DB'!$F:$F, "") ))} -> FALSE
A14: =IF($D$11 = "再製作", "◼︎ ジャケット（対応着地：再製作）" & char(10) & "《修正数値》", IF( $D$11 <>"", "◼︎ ジャケット（対応着地：お直し）" & char(10) & "《修正数値》", "")) | D14: 仕上げプレス | F14: {=IF( E14 = 0, "", IFERROR( INDEX( 'アイテム別限界値DB'!$K:$K, MATCH( 1, ('アイテム別限界値DB'!$B:$B = D$10) * ('アイテム別限界値DB'!$F:$F = D14) * ('アイテム別限界値DB'!$H:$H = E14), 0 ) ), "再製作" ) )} | G14: {=IF( E14 = 0, "", IFERROR( INDEX( 'アイテム別限界値DB'!$L:$L, MATCH( 1, ('アイテム別限界値DB'!$B:$B = D$10) * ('アイテム別限界値DB'!$C:$C = D14) * ('アイテム別限界値DB'!$F:$F = E14), 0 ) ), "" ) )} | I14: 仕上げプレス | K14: {=IF( J14 = 0, "", IFERROR( INDEX( 'アイテム別限界値DB'!$K:$K, MATCH( 1, ('アイテム別限界値DB'!$B:$B = I$10) * ('アイテム別限界値DB'!$F:$F = I14) * ('アイテム別限界値DB'!$H:$H = J14), 0 ) ), "再製作" ) )} | L14: {=IF( J14 = 0, "", IFERROR( INDEX( 'アイテム別限界値DB'!$L:$L, MATCH( 1, ('アイテム別限界値DB'!$B:$B = I$10) * ('アイテム別限界値DB'!$C:$C = I14) * ('アイテム別限界値DB'!$F:$F = J14), 0 ) ), "" ) )} | N14: 仕上げプレス | P14: {=IF( O14 = 0, "", IFERROR( INDEX( 'アイテム別限界値DB'!$K:$K, MATCH( 1, ('アイテム別限界値DB'!$B:$B = N$10) * ('アイテム別限界値DB'!$F:$F = N14) * ('アイテム別限界値DB'!$H:$H = O14), 0 ) ), "再製作" ) )} | Q14: {=IF( O14 = 0, "", IFERROR( INDEX( 'アイテム別限界値DB'!$L:$L, MATCH( 1, ('アイテム別限界値DB'!$B:$B = N$10) * ('アイテム別限界値DB'!$C:$C = N14) * ('アイテム別限界値DB'!$F:$F = O14), 0 ) ), "" ) )} | S14: 仕上げプレス | U14: {=IF( T14 = 0, "", IFERROR( INDEX( 'アイテム別限界値DB'!$K:$K, MATCH( 1, ('アイテム別限界値DB'!$B:$B = S$10) * ('アイテム別限界値DB'!$F:$F = S14) * ('アイテム別限界値DB'!$H:$H = T14), 0 ) ), "再製作" ) )} | V14: {=IF( T14 = 0, "", IFERROR( INDEX( 'アイテム別限界値DB'!$L:$L, MATCH( 1, ('アイテム別限界値DB'!$B:$B = S$10) * ('アイテム別限界値DB'!$C:$C = S14) * ('アイテム別限界値DB'!$F:$F = T14), 0 ) ), "" ) )} | X14: 仕上げプレス | Z14: {=IF( Y14 = 0, "", IFERROR( INDEX( 'アイテム別限界値DB'!$K:$K, MATCH( 1, ('アイテム別限界値DB'!$B:$B = X$10) * ('アイテム別限界値DB'!$F:$F = X14) * ('アイテム別限界値DB'!$H:$H = Y14), 0 ) ), "再製作" ) )} | AA14: {=IF( Y14 = 0, "", IFERROR( INDEX( 'アイテム別限界値DB'!$L:$L, MATCH( 1, ('アイテム別限界値DB'!$B:$B = X$10) * ('アイテム別限界値DB'!$C:$C = X14) * ('アイテム別限界値DB'!$F:$F = Y14), 0 ) ), "" ) )} | AC14: 仕上げプレス | AE14: {=IF( AD14 = 0, "", IFERROR( INDEX( 'アイテム別限界値DB'!$K:$K, MATCH( 1, ('アイテム別限界値DB'!$B:$B = AC$10) * ('アイテム別限界値DB'!$F:$F = AC14) * ('アイテム別限界値DB'!$H:$H = AD14), 0 ) ), "再製作" ) )} | AF14: {=IF( AD14 = 0, "", IFERROR( INDEX( 'アイテム別限界値DB'!$L:$L, MATCH( 1, ('アイテム別限界値DB'!$B:$B = AC$10) * ('アイテム別限界値DB'!$C:$C = AC14) * ('アイテム別限界値DB'!$F:$F = AD14), 0 ) ), "" ) )} | AH14: 仕上げプレス | AJ14: {=IF( AI14 = 0, "", IFERROR( INDEX( 'アイテム別限界値DB'!$K:$K, MATCH( 1, ('アイテム別限界値DB'!$B:$B = AH$10) * ('アイテム別限界値DB'!$F:$F = AH14) * ('アイテム別限界値DB'!$H:$H = AI14), 0 ) ), "再製作" ) )} | AK14: {=IF( AI14 = 0, "", IFERROR( INDEX( 'アイテム別限界値DB'!$L:$L, MATCH( 1, ('アイテム別限界値DB'!$B:$B = AH$10) * ('アイテム別限界値DB'!$C:$C = AH14) * ('アイテム別限界値DB'!$F:$F = AI14), 0 ) ), "" ) )} | AM14: 仕上げプレス | AO14: {=IF( AN14 = 0, "", IFERROR( INDEX( 'アイテム別限界値DB'!$K:$K, MATCH( 1, ('アイテム別限界値DB'!$B:$B = AM$10) * ('アイテム別限界値DB'!$F:$F = AM14) * ('アイテム別限界値DB'!$H:$H = AN14), 0 ) ), "再製作" ) )} | AP14: {=IF( AN14 = 0, "", IFERROR( INDEX( 'アイテム別限界値DB'!$L:$L, MATCH( 1, ('アイテム別限界値DB'!$B:$B = AM$10) * ('アイテム別限界値DB'!$C:$C = AM14) * ('アイテム別限界値DB'!$F:$F = AN14), 0 ) ), "" ) )} | AR14: 仕上げプレス | AT14: {=IF( AS14 = 0, "", IFERROR( INDEX( 'アイテム別限界値DB'!$K:$K, MATCH( 1, ('アイテム別限界値DB'!$B:$B = AR$10) * ('アイテム別限界値DB'!$F:$F = AR14) * ('アイテム別限界値DB'!$H:$H = AS14), 0 ) ), "再製作" ) )} | AU14: {=IF( AS14 = 0, "", IFERROR( INDEX( 'アイテム別限界値DB'!$L:$L, MATCH( 1, ('アイテム別限界値DB'!$B:$B = AR$10) * ('アイテム別限界値DB'!$C:$C = AR14) * ('アイテム別限界値DB'!$F:$F = AS14), 0 ) ), "" ) )} | AW14: 仕上げプレス | AY14: {=IF( AX14 = 0, "", IFERROR( INDEX( 'アイテム別限界値DB'!$K:$K, MATCH( 1, ('アイテム別限界値DB'!$B:$B = AW$10) * ('アイテム別限界値DB'!$F:$F = AW14) * ('アイテム別限界値DB'!$H:$H = AX14), 0 ) ), "再製作" ) )} | AZ14: {=IF( AX14 = 0, "", IFERROR( INDEX( 'アイテム別限界値DB'!$L:$L, MATCH( 1, ('アイテム別限界値DB'!$B:$B = AW$10) * ('アイテム別限界値DB'!$C:$C = AW14) * ('アイテム別限界値DB'!$F:$F = AX14), 0 ) ), "" ) )} | BB14: 仕上げプレス | BD14: {=IF( BC14 = 0, "", IFERROR( INDEX( 'アイテム別限界値DB'!$K:$K, MATCH( 1, ('アイテム別限界値DB'!$B:$B = BB$10) * ('アイテム別限界値DB'!$F:$F = BB14) * ('アイテム別限界値DB'!$H:$H = BC14), 0 ) ), "再製作" ) )} | BE14: {=IF( BC14 = 0, "", IFERROR( INDEX( 'アイテム別限界値DB'!$L:$L, MATCH( 1, ('アイテム別限界値DB'!$B:$B = BB$10) * ('アイテム別限界値DB'!$C:$C = BB14) * ('アイテム別限界値DB'!$F:$F = BC14), 0 ) ), "" ) )} | BG14: 仕上げプレス | BI14: {=IF( BH14 = 0, "", IFERROR( INDEX( 'アイテム別限界値DB'!$K:$K, MATCH( 1, ('アイテム別限界値DB'!$B:$B = BG$10) * ('アイテム別限界値DB'!$F:$F = BG14) * ('アイテム別限界値DB'!$H:$H = BH14), 0 ) ), "再製作" ) )} | BJ14: {=IF( BH14 = 0, "", IFERROR( INDEX( 'アイテム別限界値DB'!$L:$L, MATCH( 1, ('アイテム別限界値DB'!$B:$B = BG$10) * ('アイテム別限界値DB'!$C:$C = BG14) * ('アイテム別限界値DB'!$F:$F = BH14), 0 ) ), "" ) )} | BL14: 仕上げプレス | BN14: {=IF( BM14 = 0, "", IFERROR( INDEX( 'アイテム別限界値DB'!$K:$K, MATCH( 1, ('アイテム別限界値DB'!$B:$B = BL$10) * ('アイテム別限界値DB'!$F:$F = BL14) * ('アイテム別限界値DB'!$H:$H = BM14), 0 ) ), "再製作" ) )} | BO14: {=IF( BM14 = 0, "", IFERROR( INDEX( 'アイテム別限界値DB'!$L:$L, MATCH( 1, ('アイテム別限界値DB'!$B:$B = BL$10) * ('アイテム別限界値DB'!$C:$C = BL14) * ('アイテム別限界値DB'!$F:$F = BM14), 0 ) ), "" ) )}
